Workbook

Sheet PRAZO_GRADE
Z2: ↓ | AA2: ↓ | AB2: ↓
B3: V. 4.0 08/04 | C3: 46120 | R3: PREENCHER PARA IGUALAR AO CONTA CRÉDITO | T3: PREENCHER PARA ALTERAR GRADE | X3: PREENCHER PARA ALTERAR PRAZO
L4: ↓ | T4: ATUAL | W4: PROPOSTO | X4: ATUAL | Y4: PROPOSTO | AC4: ↓ | AD4: ↓ | AE4: ↓
B5: PERÍODO NEGOCIAÇÃO INÍCIO | C5: PERÍODO NEGOCIAÇÃO FIM | D5: MARCA SOLICITANTE | E5: FILIAL | F5: GV | G5: SUPERVISOR | H5: ORGANIZAÇÃO DE VENDAS | I5: CÓDIGO SAP CLIENTE | J5: CÓDIGO PFAT CLIENTE | K5: RAZÃO SOCIAL | L5: CNPJ | M5: CÓD. REDE | N5: NOME REDE | O5: CÓD. BAND | P5: NOME BANDEIRA | Q5: AÇÃO PARA REDE OU CLIENTE? | R5: CONTA CRÉDITO | S5: IGUALAR COM CONTA CRÉDITO? | T5: GRADE ATUAL | U5: MÍDIA | V5: DESC. FIN CLI/REDE | W5: GRADE PROPOSTA | X5: PRAZO ATUAL CLI / REDE | Y5: TIPO PARCELAMENTO / PRAZO PROPOSTO | Z5: MATERIAL BANDEIRA GMR GERAL | AA5: DESCRIÇÃO | AB5: CANAL DE FATURAMENTO (EPAN , PE OU OL) | AC5: MD TRIM | AD5: VOLUME PROPOSTO PARA O PERÍODO | AE5: OBS
B7: =TODAY() -> 46135 | C7: INDETERMINADO | D7: SANTA CRUZ | E7: =IFERROR(VLOOKUP($J7,'Base 1'!A:S,19,0),"-") -> - | F7: =IFERROR(VLOOKUP($J7,'Base 1'!$A:$N,14,0),"-") -> - | G7: =IFERROR(VLOOKUP($J7,'Base 1'!$A:$O,15,0),"-") -> - | H7: =IFERROR(VLOOKUP($J7,'Base 1'!$A:$T,20,0),"-") -> - | I7: =IFERROR(VLOOKUP($J7,'Base 1'!$A:$C,3,0),"-") -> - | K7: =IFERROR(VLOOKUP($J7,'Base 1'!$A:$E,5,0),"-") -> - | L7: =IFERROR(VLOOKUP($J7,'Base 1'!$A:$B,2,0),"-") -> - | M7: =IFERROR(VLOOKUP($J7,'Base 1'!$A:$Q,17,0),"-") -> - | N7: =IFERROR(VLOOKUP($J7,'Base 1'!$A:$R,18,0),"-") -> - | O7: =IFERROR(VLOOKUP($J7,'Base 1'!$A:$F,6,0),"-") -> - | P7: =IFERROR(VLOOKUP($J7,'Base 1'!$A:$G,7,0),"-") -> - | R7: =IFERROR(VLOOKUP(J7,'Base 1'!$A:$L,12,0),"-") -> - | T7: =IFERROR(VLOOKUP(J7,'Base 1'!$A:$J,10,0),"-") -> - | X7: =IFERROR(VLOOKUP(J7,'Base 1'!$A:$I,9,0),"-") -> - | AC7: =IFERROR(VLOOKUP($J7,'Base 1'!$A:$Q,16,0),"-") -> -
B8: =TODAY() -> 46135 | C8: INDETERMINADO | D8: SANTA CRUZ | E8: =IFERROR(VLOOKUP($J8,'Base 1'!A:S,19,0),"-") -> - | F8: =IFERROR(VLOOKUP($J8,'Base 1'!$A:$N,14,0),"-") -> - | G8: =IFERROR(VLOOKUP($J8,'Base 1'!$A:$O,15,0),"-") -> - | H8: =IFERROR(VLOOKUP($J8,'Base 1'!$A:$T,20,0),"-") -> - | I8: =IFERROR(VLOOKUP($J8,'Base 1'!$A:$C,3,0),"-") -> - | K8: =IFERROR(VLOOKUP($J8,'Base 1'!$A:$E,5,0),"-") -> - | L8: =IFERROR(VLOOKUP($J8,'Base 1'!$A:$B,2,0),"-") -> - | M8: =IFERROR(VLOOKUP($J8,'Base 1'!$A:$Q,17,0),"-") -> - | N8: =IFERROR(VLOOKUP($J8,'Base 1'!$A:$R,18,0),"-") -> - | O8: =IFERROR(VLOOKUP($J8,'Base 1'!$A:$F,6,0),"-") -> - | P8: =IFERROR(VLOOKUP($J8,'Base 1'!$A:$G,7,0),"-") -> - | R8: =IFERROR(VLOOKUP(J8,'Base 1'!$A:$L,12,0),"-") -> - | T8: =IFERROR(VLOOKUP(J8,'Base 1'!$A:$J,10,0),"-") -> - | X8: =IFERROR(VLOOKUP(J8,'Base 1'!$A:$I,9,0),"-") -> - | AC8: =IFERROR(VLOOKUP($J8,'Base 1'!$A:$Q,16,0),"-") -> -
B9: =TODAY() -> 46135 | C9: INDETERMINADO | D9: SANTA CRUZ | E9: =IFERROR(VLOOKUP($J9,'Base 1'!A:S,19,0),"-") -> - | F9: =IFERROR(VLOOKUP($J9,'Base 1'!$A:$N,14,0),"-") -> - | G9: =IFERROR(VLOOKUP($J9,'Base 1'!$A:$O,15,0),"-") -> - | H9: =IFERROR(VLOOKUP($J9,'Base 1'!$A:$T,20,0),"-") -> - | I9: =IFERROR(VLOOKUP($J9,'Base 1'!$A:$C,3,0),"-") -> - | K9: =IFERROR(VLOOKUP($J9,'Base 1'!$A:$E,5,0),"-") -> - | L9: =IFERROR(VLOOKUP($J9,'Base 1'!$A:$B,2,0),"-") -> - | M9: =IFERROR(VLOOKUP($J9,'Base 1'!$A:$Q,17,0),"-") -> - | N9: =IFERROR(VLOOKUP($J9,'Base 1'!$A:$R,18,0),"-") -> - | O9: =IFERROR(VLOOKUP($J9,'Base 1'!$A:$F,6,0),"-") -> - | P9: =IFERROR(VLOOKUP($J9,'Base 1'!$A:$G,7,0),"-") -> - | R9: =IFERROR(VLOOKUP(J9,'Base 1'!$A:$L,12,0),"-") -> - | T9: =IFERROR(VLOOKUP(J9,'Base 1'!$A:$J,10,0),"-") -> - | X9: =IFERROR(VLOOKUP(J9,'Base 1'!$A:$I,9,0),"-") -> - | AC9: =IFERROR(VLOOKUP($J9,'Base 1'!$A:$Q,16,0),"-") -> -
B10: =TODAY() -> 46135 | C10: INDETERMINADO | D10: SANTA CRUZ | E10: =IFERROR(VLOOKUP($J10,'Base 1'!A:S,19,0),"-") -> - | F10: =IFERROR(VLOOKUP($J10,'Base 1'!$A:$N,14,0),"-") -> - | G10: =IFERROR(VLOOKUP($J10,'Base 1'!$A:$O,15,0),"-") -> - | H10: =IFERROR(VLOOKUP($J10,'Base 1'!$A:$T,20,0),"-") -> - | I10: =IFERROR(VLOOKUP($J10,'Base 1'!$A:$C,3,0),"-") -> - | K10: =IFERROR(VLOOKUP($J10,'Base 1'!$A:$E,5,0),"-") -> - | L10: =IFERROR(VLOOKUP($J10,'Base 1'!$A:$B,2,0),"-") -> - | M10: =IFERROR(VLOOKUP($J10,'Base 1'!$A:$Q,17,0),"-") -> - | N10: =IFERROR(VLOOKUP($J10,'Base 1'!$A:$R,18,0),"-") -> - | O10: =IFERROR(VLOOKUP($J10,'Base 1'!$A:$F,6,0),"-") -> - | P10: =IFERROR(VLOOKUP($J10,'Base 1'!$A:$G,7,0),"-") -> - | R10: =IFERROR(VLOOKUP(J10,'Base 1'!$A:$L,12,0),"-") -> - | T10: =IFERROR(VLOOKUP(J10,'Base 1'!$A:$J,10,0),"-") -> - | X10: =IFERROR(VLOOKUP(J10,'Base 1'!$A:$I,9,0),"-") -> - | AC10: =IFERROR(VLOOKUP($J10,'Base 1'!$A:$Q,16,0),"-") -> -
B11: =TODAY() -> 46135 | C11: INDETERMINADO | D11: SANTA CRUZ | E11: =IFERROR(VLOOKUP($J11,'Base 1'!A:S,19,0),"-") -> - | F11: =IFERROR(VLOOKUP($J11,'Base 1'!$A:$N,14,0),"-") -> - | G11: =IFERROR(VLOOKUP($J11,'Base 1'!$A:$O,15,0),"-") -> - | H11: =IFERROR(VLOOKUP($J11,'Base 1'!$A:$T,20,0),"-") -> - | I11: =IFERROR(VLOOKUP($J11,'Base 1'!$A:$C,3,0),"-") -> - | K11: =IFERROR(VLOOKUP($J11,'Base 1'!$A:$E,5,0),"-") -> - | L11: =IFERROR(VLOOKUP($J11,'Base 1'!$A:$B,2,0),"-") -> - | M11: =IFERROR(VLOOKUP($J11,'Base 1'!$A:$Q,17,0),"-") -> - | N11: =IFERROR(VLOOKUP($J11,'Base 1'!$A:$R,18,0),"-") -> - | O11: =IFERROR(VLOOKUP($J11,'Base 1'!$A:$F,6,0),"-") -> - | P11: =IFERROR(VLOOKUP($J11,'Base 1'!$A:$G,7,0),"-") -> - | R11: =IFERROR(VLOOKUP(J11,'Base 1'!$A:$L,12,0),"-") -> - | T11: =IFERROR(VLOOKUP(J11,'Base 1'!$A:$J,10,0),"-") -> - | X11: =IFERROR(VLOOKUP(J11,'Base 1'!$A:$I,9,0),"-") -> - | AC11: =IFERROR(VLOOKUP($J11,'Base 1'!$A:$Q,16,0),"-") -> -
B12: =TODAY() -> 46135 | C12: INDETERMINADO | D12: SANTA CRUZ | E12: =IFERROR(VLOOKUP($J12,'Base 1'!A:S,19,0),"-") -> - | F12: =IFERROR(VLOOKUP($J12,'Base 1'!$A:$N,14,0),"-") -> - | G12: =IFERROR(VLOOKUP($J12,'Base 1'!$A:$O,15,0),"-") -> - | H12: =IFERROR(VLOOKUP($J12,'Base 1'!$A:$T,20,0),"-") -> - | I12: =IFERROR(VLOOKUP($J12,'Base 1'!$A:$C,3,0),"-") -> - | K12: =IFERROR(VLOOKUP($J12,'Base 1'!$A:$E,5,0),"-") -> - | L12: =IFERROR(VLOOKUP($J12,'Base 1'!$A:$B,2,0),"-") -> - | M12: =IFERROR(VLOOKUP($J12,'Base 1'!$A:$Q,17,0),"-") -> - | N12: =IFERROR(VLOOKUP($J12,'Base 1'!$A:$R,18,0),"-") -> - | O12: =IFERROR(VLOOKUP($J12,'Base 1'!$A:$F,6,0),"-") -> - | P12: =IFERROR(VLOOKUP($J12,'Base 1'!$A:$G,7,0),"-") -> - | R12: =IFERROR(VLOOKUP(J12,'Base 1'!$A:$L,12,0),"-") -> - | T12: =IFERROR(VLOOKUP(J12,'Base 1'!$A:$J,10,0),"-") -> - | X12: =IFERROR(VLOOKUP(J12,'Base 1'!$A:$I,9,0),"-") -> - | AC12: =IFERROR(VLOOKUP($J12,'Base 1'!$A:$Q,16,0),"-") -> -
B13: =TODAY() -> 46135 | C13: INDETERMINADO | D13: SANTA CRUZ | E13: =IFERROR(VLOOKUP($J13,'Base 1'!A:S,19,0),"-") -> - | F13: =IFERROR(VLOOKUP($J13,'Base 1'!$A:$N,14,0),"-") -> - | G13: =IFERROR(VLOOKUP($J13,'Base 1'!$A:$O,15,0),"-") -> - | H13: =IFERROR(VLOOKUP($J13,'Base 1'!$A:$T,20,0),"-") -> - | I13: =IFERROR(VLOOKUP($J13,'Base 1'!$A:$C,3,0),"-") -> - | K13: =IFERROR(VLOOKUP($J13,'Base 1'!$A:$E,5,0),"-") -> - | L13: =IFERROR(VLOOKUP($J13,'Base 1'!$A:$B,2,0),"-") -> - | M13: =IFERROR(VLOOKUP($J13,'Base 1'!$A:$Q,17,0),"-") -> - | N13: =IFERROR(VLOOKUP($J13,'Base 1'!$A:$R,18,0),"-") -> - | O13: =IFERROR(VLOOKUP($J13,'Base 1'!$A:$F,6,0),"-") -> - | P13: =IFERROR(VLOOKUP($J13,'Base 1'!$A:$G,7,0),"-") -> - | R13: =IFERROR(VLOOKUP(J13,'Base 1'!$A:$L,12,0),"-") -> - | T13: =IFERROR(VLOOKUP(J13,'Base 1'!$A:$J,10,0),"-") -> - | X13: =IFERROR(VLOOKUP(J13,'Base 1'!$A:$I,9,0),"-") -> - | AC13: =IFERROR(VLOOKUP($J13,'Base 1'!$A:$Q,16,0),"-") -> -
B14: =TODAY() -> 46135 | C14: INDETERMINADO | D14: SANTA CRUZ | E14: =IFERROR(VLOOKUP($J14,'Base 1'!A:S,19,0),"-") -> - | F14: =IFERROR(VLOOKUP($J14,'Base 1'!$A:$N,14,0),"-") -> - | G14: =IFERROR(VLOOKUP($J14,'Base 1'!$A:$O,15,0),"-") -> - | H14: =IFERROR(VLOOKUP($J14,'Base 1'!$A:$T,20,0),"-") -> - | I14: =IFERROR(VLOOKUP($J14,'Base 1'!$A:$C,3,0),"-") -> - | K14: =IFERROR(VLOOKUP($J14,'Base 1'!$A:$E,5,0),"-") -> - | L14: =IFERROR(VLOOKUP($J14,'Base 1'!$A:$B,2,0),"-") -> - | M14: =IFERROR(VLOOKUP($J14,'Base 1'!$A:$Q,17,0),"-") -> - | N14: =IFERROR(VLOOKUP($J14,'Base 1'!$A:$R,18,0),"-") -> - | O14: =IFERROR(VLOOKUP($J14,'Base 1'!$A:$F,6,0),"-") -> - | P14: =IFERROR(VLOOKUP($J14,'Base 1'!$A:$G,7,0),"-") -> - | R14: =IFERROR(VLOOKUP(J14,'Base 1'!$A:$L,12,0),"-") -> - | T14: =IFERROR(VLOOKUP(J14,'Base 1'!$A:$J,10,0),"-") -> - | X14: =IFERROR(VLOOKUP(J14,'Base 1'!$A:$I,9,0),"-") -> - | AC14: =IFERROR(VLOOKUP($J14,'Base 1'!$A:$Q,16,0),"-") -> -
B15: =TODAY() -> 46135 | C15: INDETERMINADO | D15: SANTA CRUZ | E15: =IFERROR(VLOOKUP($J15,'Base 1'!A:S,19,0),"-") -> - | F15: =IFERROR(VLOOKUP($J15,'Base 1'!$A:$N,14,0),"-") -> - | G15: =IFERROR(VLOOKUP($J15,'Base 1'!$A:$O,15,0),"-") -> - | H15: =IFERROR(VLOOKUP($J15,'Base 1'!$A:$T,20,0),"-") -> - | I15: =IFERROR(VLOOKUP($J15,'Base 1'!$A:$C,3,0),"-") -> - | K15: =IFERROR(VLOOKUP($J15,'Base 1'!$A:$E,5,0),"-") -> - | L15: =IFERROR(VLOOKUP($J15,'Base 1'!$A:$B,2,0),"-") -> - | M15: =IFERROR(VLOOKUP($J15,'Base 1'!$A:$Q,17,0),"-") -> - | N15: =IFERROR(VLOOKUP($J15,'Base 1'!$A:$R,18,0),"-") -> - | O15: =IFERROR(VLOOKUP($J15,'Base 1'!$A:$F,6,0),"-") -> - | P15: =IFERROR(VLOOKUP($J15,'Base 1'!$A:$G,7,0),"-") -> - | R15: =IFERROR(VLOOKUP(J15,'Base 1'!$A:$L,12,0),"-") -> - | T15: =IFERROR(VLOOKUP(J15,'Base 1'!$A:$J,10,0),"-") -> - | X15: =IFERROR(VLOOKUP(J15,'Base 1'!$A:$I,9,0),"-") -> - | AC15: =IFERROR(VLOOKUP($J15,'Base 1'!$A:$Q,16,0),"-") -> -
B16: =TODAY() -> 46135 | C16: INDETERMINADO | D16: SANTA CRUZ | E16: =IFERROR(VLOOKUP($J16,'Base 1'!A:S,19,0),"-") -> - | F16: =IFERROR(VLOOKUP($J16,'Base 1'!$A:$N,14,0),"-") -> - | G16: =IFERROR(VLOOKUP($J16,'Base 1'!$A:$O,15,0),"-") -> - | H16: =IFERROR(VLOOKUP($J16,'Base 1'!$A:$T,20,0),"-") -> - | I16: =IFERROR(VLOOKUP($J16,'Base 1'!$A:$C,3,0),"-") -> - | K16: =IFERROR(VLOOKUP($J16,'Base 1'!$A:$E,5,0),"-") -> - | L16: =IFERROR(VLOOKUP($J16,'Base 1'!$A:$B,2,0),"-") -> - | M16: =IFERROR(VLOOKUP($J16,'Base 1'!$A:$Q,17,0),"-") -> - | N16: =IFERROR(VLOOKUP($J16,'Base 1'!$A:$R,18,0),"-") -> - | O16: =IFERROR(VLOOKUP($J16,'Base 1'!$A:$F,6,0),"-") -> - | P16: =IFERROR(VLOOKUP($J16,'Base 1'!$A:$G,7,0),"-") -> - | R16: =IFERROR(VLOOKUP(J16,'Base 1'!$A:$L,12,0),"-") -> - | T16: =IFERROR(VLOOKUP(J16,'Base 1'!$A:$J,10,0),"-") -> - | X16: =IFERROR(VLOOKUP(J16,'Base 1'!$A:$I,9,0),"-") -> - | AC16: =IFERROR(VLOOKUP($J16,'Base 1'!$A:$Q,16,0),"-") -> -
B17: =TODAY() -> 46135 | C17: INDETERMINADO | D17: SANTA CRUZ | E17: =IFERROR(VLOOKUP($J17,'Base 1'!A:S,19,0),"-") -> - | F17: =IFERROR(VLOOKUP($J17,'Base 1'!$A:$N,14,0),"-") -> - | G17: =IFERROR(VLOOKUP($J17,'Base 1'!$A:$O,15,0),"-") -> - | H17: =IFERROR(VLOOKUP($J17,'Base 1'!$A:$T,20,0),"-") -> - | I17: =IFERROR(VLOOKUP($J17,'Base 1'!$A:$C,3,0),"-") -> - | K17: =IFERROR(VLOOKUP($J17,'Base 1'!$A:$E,5,0),"-") -> - | L17: =IFERROR(VLOOKUP($J17,'Base 1'!$A:$B,2,0),"-") -> - | M17: =IFERROR(VLOOKUP($J17,'Base 1'!$A:$Q,17,0),"-") -> - | N17: =IFERROR(VLOOKUP($J17,'Base 1'!$A:$R,18,0),"-") -> - | O17: =IFERROR(VLOOKUP($J17,'Base 1'!$A:$F,6,0),"-") -> - | P17: =IFERROR(VLOOKUP($J17,'Base 1'!$A:$G,7,0),"-") -> - | R17: =IFERROR(VLOOKUP(J17,'Base 1'!$A:$L,12,0),"-") -> - | T17: =IFERROR(VLOOKUP(J17,'Base 1'!$A:$J,10,0),"-") -> - | X17: =IFERROR(VLOOKUP(J17,'Base 1'!$A:$I,9,0),"-") -> - | AC17: =IFERROR(VLOOKUP($J17,'Base 1'!$A:$Q,16,0),"-") -> -
B18: =TODAY() -> 46135 | C18: INDETERMINADO | D18: SANTA CRUZ | E18: =IFERROR(VLOOKUP($J18,'Base 1'!A:S,19,0),"-") -> - | F18: =IFERROR(VLOOKUP($J18,'Base 1'!$A:$N,14,0),"-") -> - | G18: =IFERROR(VLOOKUP($J18,'Base 1'!$A:$O,15,0),"-") -> - | H18: =IFERROR(VLOOKUP($J18,'Base 1'!$A:$T,20,0),"-") -> - | I18: =IFERROR(VLOOKUP($J18,'Base 1'!$A:$C,3,0),"-") -> - | K18: =IFERROR(VLOOKUP($J18,'Base 1'!$A:$E,5,0),"-") -> - | L18: =IFERROR(VLOOKUP($J18,'Base 1'!$A:$B,2,0),"-") -> - | M18: =IFERROR(VLOOKUP($J18,'Base 1'!$A:$Q,17,0),"-") -> - | N18: =IFERROR(VLOOKUP($J18,'Base 1'!$A:$R,18,0),"-") -> - | O18: =IFERROR(VLOOKUP($J18,'Base 1'!$A:$F,6,0),"-") -> - | P18: =IFERROR(VLOOKUP($J18,'Base 1'!$A:$G,7,0),"-") -> - | R18: =IFERROR(VLOOKUP(J18,'Base 1'!$A:$L,12,0),"-") -> - | T18: =IFERROR(VLOOKUP(J18,'Base 1'!$A:$J,10,0),"-") -> - | X18: =IFERROR(VLOOKUP(J18,'Base 1'!$A:$I,9,0),"-") -> - | AC18: =IFERROR(VLOOKUP($J18,'Base 1'!$A:$Q,16,0),"-") -> -
... B748: =TODAY() -> 46135 | C748: INDETERMINADO | D748: SANTA CRUZ | E748: =IFERROR(VLOOKUP($J748,'Base 1'!A:S,19,0),"-") -> - | F748: =IFERROR(VLOOKUP($J748,'Base 1'!$A:$N,14,0),"-") -> - | G748: =IFERROR(VLOOKUP($J748,'Base 1'!$A:$O,15,0),"-") -> - | H748: =IFERROR(VLOOKUP($J748,'Base 1'!$A:$T,20,0),"-") -> - | I748: =IFERROR(VLOOKUP($J748,'Base 1'!$A:$C,3,0),"-") -> - | K748: =IFERROR(VLOOKUP($J748,'Base 1'!$A:$E,5,0),"-") -> - | L748: =IFERROR(VLOOKUP($J748,'Base 1'!$A:$B,2,0),"-") -> - | M748: =IFERROR(VLOOKUP($J748,'Base 1'!$A:$Q,17,0),"-") -> - | N748: =IFERROR(VLOOKUP($J748,'Base 1'!$A:$R,18,0),"-") -> - | O748: =IFERROR(VLOOKUP($J748,'Base 1'!$A:$F,6,0),"-") -> - | P748: =IFERROR(VLOOKUP($J748,'Base 1'!$A:$G,7,0),"-") -> - | R748: =IFERROR(VLOOKUP(J748,'Base 1'!$A:$L,12,0),"-") -> - | T748: =IFERROR(VLOOKUP(J748,'Base 1'!$A:$J,10,0),"-") -> - | X748: =IFERROR(VLOOKUP(J748,'Base 1'!$A:$I,9,0),"-") -> - | AC748: =IFERROR(VLOOKUP($J748,'Base 1'!$A:$Q,16,0),"-") -> -

Sheet MEDIA TRI
H2: Ano | I2: 2026 | J2: 2026 | K2: 2026 | L2: 2026 | M2: 2026 | N2: 2026 | O2: 2026 | P2: 2026 | Q2: 2026 | R2: 2026 | S2: 2026 | T2: 2026 | U2: 2026 | V2: 2026 | W2: 2026 | X2: 2026 | Y2: 2026 | Z2: 2026
H3: Mês | I3: Jan 2026 | J3: Jan 2026 | K3: Jan 2026 | L3: Jan 2026 | M3: Jan 2026 | N3: Jan 2026 | O3: Fev 2026 | P3: Fev 2026 | Q3: Fev 2026 | R3: Fev 2026 | S3: Fev 2026 | T3: Fev 2026 | U3: Mar 2026 | V3: Mar 2026 | W3: Mar 2026 | X3: Mar 2026 | Y3: Mar 2026 | Z3: Mar 2026
B4: Bandeira Agrupada | C4: Band Cliente | D4: Seg Cli | F4: CNPJ | G4: CPF | H4: UF | I4: Meta VB | J4: Meta P.P. VB | K4: VB | L4: Desvio VB | M4: % | N4: Cresc % | O4: Meta VB | P4: Meta P.P. VB | Q4: VB | R4: Desvio VB | S4: % | T4: Cresc % | U4: Meta VB | V4: Meta P.P. VB | W4: VB | X4: Desvio VB | Y4: % | Z4: Cresc % | AA4: MEDIA TRI
B5: Total | I5: =SUBTOTAL(9,I6:I1048576) -> 1.2064471e+08 | J5: =SUBTOTAL(9,J6:J1048576) -> 1.2064471e+08 | K5: =SUBTOTAL(9,K6:K1048576) -> 1.1705069e+08 | L5: -1808390.6 | M5: -0.028655179 | N5: - | O5: =SUBTOTAL(9,O6:O1048576) -> 1.2286468e+08 | P5: =SUBTOTAL(9,P6:P1048576) -> 1.2286468e+08 | Q5: =SUBTOTAL(9,Q6:Q1048576) -> 1.1090509e+08 | R5: -6631802.4 | S5: -0.10447063 | T5: -0.072626577 | U5: =SUBTOTAL(9,U6:U1048576) -> 1.5076836e+08 | V5: =SUBTOTAL(9,V6:V1048576) -> 1.5076836e+08 | W5: =SUBTOTAL(9,W6:W1048576) -> 1.4143219e+08 | X5: -3473084.2 | Y5: -0.046489956 | Z5: 0.25303804 | AA5: =SUM(K5,Q5,W5)/3 -> 1.2312933e+08
A6: =_xlfn.XLOOKUP('[1]CMK - 30.09.2025'!$N$1:$N$1048576,'[1]CMK - 30.09.2025'!$J$1:$J$1048576,"-",0) -> #NAME? | B6: INDIVIDUAL | C6: INDIVIDUAL | D6: INDEPENDENTES | E6: 86860000190 | F6: 00086860000190 - DROGARIA SERRA LTDA | H6: MG | I6: 45264.589 | J6: 45264.589 | K6: 46339.63 | L6: 1075.041 | M6: 0.023750155 | N6: - | O6: 30522.507 | P6: 30522.507 | Q6: 27147.79 | R6: -3374.717 | S6: -0.11056487 | T6: -0.41415609 | U6: 37509.61 | V6: 37509.61 | W6: 53891.02 | X6: 16381.41 | Y6: 0.43672568 | Z6: 0.98509787 | AA6: =SUM(K6,Q6,W6)/3 -> 42459.48
A7: =_xlfn.XLOOKUP('[1]CMK - 30.09.2025'!$N$1:$N$1048576,'[1]CMK - 30.09.2025'!$J$1:$J$1048576,"-",0) -> #NAME? | B7: INDIVIDUAL | C7: INDIVIDUAL | D7: INDEPENDENTES | E7: 112154000175 | F7: 00112154000175 - DROGAZILLE LTDA ME | H7: MG | I7: 5440.774 | J7: 5440.774 | K7: 7055.02 | L7: 1614.246 | M7: 0.29669418 | N7: - | O7: 1451.481 | P7: 1451.481 | Q7: 5016.58 | R7: 3565.099 | S7: 2.4561803 | T7: -0.28893469 | U7: 2963.036 | V7: 2963.036 | W7: 5934.01 | X7: 2970.974 | Y7: 1.002679 | Z7: 0.18287957 | AA7: =SUM(K7,Q7,W7)/3 -> 6001.87
A8: =_xlfn.XLOOKUP('[1]CMK - 30.09.2025'!$N$1:$N$1048576,'[1]CMK - 30.09.2025'!$J$1:$J$1048576,"-",0) -> #NAME? | B8: INDIVIDUAL | C8: INDIVIDUAL | D8: INDEPENDENTES | E8: 149893000131 | F8: 00149893000131 - DROG E PERF TORRES E FILHO LTDA | H8: MG | I8: 4691.774 | J8: 4691.774 | K8: 1771.29 | L8: -2920.484 | M8: -0.62246903 | N8: - | O8: 17281.807 | P8: 17281.807 | Q8: 1298.71 | R8: -15983.097 | S8: -0.92485103 | T8: -0.2667999 | U8: 8846.805 | V8: 8846.805 | W8: 668.69 | X8: -8178.115 | Y8: -0.92441452 | Z8: -0.48511215 | AA8: =SUM(K8,Q8,W8)/3 -> 1246.23
A9: =_xlfn.XLOOKUP('[1]CMK - 30.09.2025'!$N$1:$N$1048576,'[1]CMK - 30.09.2025'!$J$1:$J$1048576,"-",0) -> #NAME? | B9: INDIVIDUAL | C9: INDIVIDUAL | D9: INDEPENDENTES | E9: 204120000100 | F9: 00204120000100 - REGINA RIBEIRO PEIXOTO ME | H9: MG | I9: 1815.92 | J9: 1815.92 | K9: 3022.36 | L9: 1206.44 | M9: 0.66436847 | N9: - | O9: 1964.929 | P9: 1964.929 | Q9: 3050.93 | R9: 1086.001 | S9: 0.55269223 | T9: 0.0094528779 | U9: 1996.988 | V9: 1996.988 | W9: 5093.25 | X9: 3096.262 | Y9: 1.550466 | Z9: 0.669409 | AA9: =SUM(K9,Q9,W9)/3 -> 3722.18
A10: =_xlfn.XLOOKUP('[1]CMK - 30.09.2025'!$N$1:$N$1048576,'[1]CMK - 30.09.2025'!$J$1:$J$1048576,"-",0) -> #NAME? | B10: INDIVIDUAL | C10: INDIVIDUAL | D10: INDEPENDENTES | E10: 207500000107 | F10: 00207500000107 - MULTIMEDIC COMERCIAL LTDA | H10: MG | I10: 38.219 | J10: 38.219 | K10: 0 | L10: -38.219 | M10: -1 | N10: - | O10: 297.141 | P10: 297.141 | Q10: 0 | R10: -297.141 | S10: -1 | T10: - | U10: 66.847 | V10: 66.847 | W10: 0 | X10: -66.847 | Y10: -1 | Z10: - | AA10: =SUM(K10,Q10,W10)/3 -> 0
A11: =_xlfn.XLOOKUP('[1]CMK - 30.09.2025'!$N$1:$N$1048576,'[1]CMK - 30.09.2025'!$J$1:$J$1048576,"-",0) -> #NAME? | B11: INDIVIDUAL | C11: INDIVIDUAL | D11: INDEPENDENTES | E11: 268176000129 | F11: 00268176000129 - DROG SAO JOSE DE NOVA ERA LTDA | H11: MG | I11: 8248.576 | J11: 8248.576 | K11: 4386.82 | L11: -3861.756 | M11: -0.46817245 | N11: - | O11: 17117.66 | P11: 17117.66 | Q11: 6178.08 | R11: -10939.58 | S11: -0.63908151 | T11: 0.40832767 | U11: 26718.28 | V11: 26718.28 | W11: 7392 | X11: -19326.28 | Y11: -0.72333548 | Z11: 0.19648823 | AA11: =SUM(K11,Q11,W11)/3 -> 5985.6333
A12: =_xlfn.XLOOKUP('[1]CMK - 30.09.2025'!$N$1:$N$1048576,'[1]CMK - 30.09.2025'!$J$1:$J$1048576,"-",0) -> #NAME? | B12: INDIVIDUAL | C12: INDIVIDUAL | D12: INDEPENDENTES | E12: 325618000121 | F12: 00325618000121 - DROGARIA JARA LTDA | H12: MG | I12: 10000.933 | J12: 10000.933 | K12: 7422.02 | L12: -2578.913 | M12: -0.25786724 | N12: - | O12: 10298.849 | P12: 10298.849 | Q12: 2992.31 | R12: -7306.539 | S12: -0.709452 | T12: -0.59683348 | U12: 8370.841 | V12: 8370.841 | W12: 7791.47 | X12: -579.371 | Y12: -0.069212998 | Z12: 1.6038312 | AA12: =SUM(K12,Q12,W12)/3 -> 6068.6
A13: =_xlfn.XLOOKUP('[1]CMK - 30.09.2025'!$N$1:$N$1048576,'[1]CMK - 30.09.2025'!$J$1:$J$1048576,"-",0) -> #NAME? | B13: INDIVIDUAL | C13: INDIVIDUAL | D13: INDEPENDENTES | E13: 363241000103 | F13: 00363241000103 - DROG LIMA E BAIAO LTDA ME | H13: MG | I13: 313.35 | J13: 313.35 | K13: 810.07 | L13: 496.72 | M13: 1.5851923 | N13: - | O13: 462.059 | P13: 462.059 | Q13: 574.26 | R13: 112.201 | S13: 0.2428283 | T13: -0.2910983 | U13: 0 | V13: 0 | W13: 514.75 | X13: 514.75 | Y13: - | Z13: -0.10362902 | AA13: =SUM(K13,Q13,W13)/3 -> 633.02667
A14: =_xlfn.XLOOKUP('[1]CMK - 30.09.2025'!$N$1:$N$1048576,'[1]CMK - 30.09.2025'!$J$1:$J$1048576,"-",0) -> #NAME? | B14: INDIVIDUAL | C14: INDIVIDUAL | D14: INDEPENDENTES | E14: 374879000131 | F14: 00374879000131 - ELIANE MARIA BICALHO | H14: MG | I14: 1665.157 | J14: 1665.157 | K14: 1516.69 | L14: -148.467 | M14: -0.089160962 | N14: - | O14: 495.572 | P14: 495.572 | Q14: 248.99 | R14: -246.582 | S14: -0.49757048 | T14: -0.83583329 | U14: 2317.982 | V14: 2317.982 | W14: 531.68 | X14: -1786.302 | Y14: -0.77062807 | Z14: 1.1353468 | AA14: =SUM(K14,Q14,W14)/3 -> 765.78667
A15: =_xlfn.XLOOKUP('[1]CMK - 30.09.2025'!$N$1:$N$1048576,'[1]CMK - 30.09.2025'!$J$1:$J$1048576,"-",0) -> #NAME? | B15: INDIVIDUAL | C15: INDIVIDUAL | D15: INDEPENDENTES | E15: 427688000190 | F15: 00427688000190 - A & D MEDICAMENTOS LTDA | H15: MG | I15: 14026.516 | J15: 14026.516 | K15: 10181.05 | L15: -3845.466 | M15: -0.27415689 | N15: - | O15: 8958.363 | P15: 8958.363 | Q15: 10972.47 | R15: 2014.107 | S15: 0.2248298 | T15: 0.077734615 | U15: 11279.193 | V15: 11279.193 | W15: 14818.84 | X15: 3539.647 | Y15: 0.31382094 | Z15: 0.35054732 | AA15: =SUM(K15,Q15,W15)/3 -> 11990.787
A16: =_xlfn.XLOOKUP('[1]CMK - 30.09.2025'!$N$1:$N$1048576,'[1]CMK - 30.09.2025'!$J$1:$J$1048576,"-",0) -> #NAME? | B16: INDIVIDUAL | C16: INDIVIDUAL | D16: INDEPENDENTES | E16: 517985000127 | F16: 00517985000127 - JOSE CARNEIRO OS & CIA LT ME | H16: MG | I16: 352.965 | J16: 352.965 | K16: 937.81 | L16: 584.845 | M16: 1.656949 | N16: - | O16: 2311.822 | P16: 2311.822 | Q16: 1113.99 | R16: -1197.832 | S16: -0.51813332 | T16: 0.18786321 | U16: 342.385 | V16: 342.385 | W16: 753.98 | X16: 411.595 | Y16: 1.2021409 | Z16: -0.32317166 | AA16: =SUM(K16,Q16,W16)/3 -> 935.26
A17: =_xlfn.XLOOKUP('[1]CMK - 30.09.2025'!$N$1:$N$1048576,'[1]CMK - 30.09.2025'!$J$1:$J$1048576,"-",0) -> #NAME? | B17: INDIVIDUAL | C17: INDIVIDUAL | D17: INDEPENDENTES | E17: 571664000100 | F17: 00571664000100 - DROG MAGALHAES ARAUJO LT | H17: MG | I17: 17355.929 | J17: 17355.929 | K17: 19784.92 | L17: 2428.991 | M17: 0.13995166 | N17: - | O17: 17947.001 | P17: 17947.001 | Q17: 23613.58 | R17: 5666.579 | S17: 0.3157396 | T17: 0.19351405 | U17: 25082.974 | V17: 25082.974 | W17: 34433.63 | X17: 9350.656 | Y17: 0.37278897 | Z17: 0.45821303 | AA17: =SUM(K17,Q17,W17)/3 -> 25944.043
A18: =_xlfn.XLOOKUP('[1]CMK - 30.09.2025'!$N$1:$N$1048576,'[1]CMK - 30.09.2025'!$J$1:$J$1048576,"-",0) -> #NAME? | B18: INDIVIDUAL | C18: INDIVIDUAL | D18: INDEPENDENTES | E18: 592069000151 | F18: 00592069000151 - FABIO FERREIRA DA SILVA | H18: MG | I18: 14913.844 | J18: 14913.844 | K18: 24461.92 | L18: 9548.076 | M18: 0.64021563 | N18: - | O18: 12227.216 | P18: 12227.216 | Q18: 8732.4 | R18: -3494.816 | S18: -0.28582271 | T18: -0.64302066 | U18: 13282.631 | V18: 13282.631 | W18: 4802.4 | X18: -8480.231 | Y18: -0.63844512 | Z18: -0.4500481 | AA18: =SUM(K18,Q18,W18)/3 -> 12665.573
A19: =_xlfn.XLOOKUP('[1]CMK - 30.09.2025'!$N$1:$N$1048576,'[1]CMK - 30.09.2025'!$J$1:$J$1048576,"-",0) -> #NAME? | B19: INDIVIDUAL | C19: INDIVIDUAL | D19: INDEPENDENTES | E19: 595692000168 | F19: 00595692000168 - GILSON JOSE DE MATOS ME | H19: MG | I19: 1048.504 | J19: 1048.504 | K19: 1045.53 | L19: -2.974 | M19: -0.0028364222 | N19: - | O19: 1210.733 | P19: 1210.733 | Q19: 676.67 | R19: -534.063 | S19: -0.44110716 | T19: -0.35279715 | U19: 2080.785 | V19: 2080.785 | W19: 1428.32 | X19: -652.465 | Y19: -0.31356675 | Z19: 1.1108073 | AA19: =SUM(K19,Q19,W19)/3 -> 1050.1733
A20: =_xlfn.XLOOKUP('[1]CMK - 30.09.2025'!$N$1:$N$1048576,'[1]CMK - 30.09.2025'!$J$1:$J$1048576,"-",0) -> #NAME? | B20: INDIVIDUAL | C20: INDIVIDUAL | D20: INDEPENDENTES | E20: 600161000116 | F20: 00600161000116 - FARMACIA GOMES & OLIVEIRA LTDA | H20: MG | I20: 6761.644 | J20: 6761.644 | K20: 1206.84 | L20: -5554.804 | M20: -0.82151678 | N20: - | O20: 17659.458 | P20: 17659.458 | Q20: 1799.26 | R20: -15860.198 | S20: -0.89811352 | T20: 0.49088529 | U20: 10427.283 | V20: 10427.283 | W20: 4967.94 | X20: -5459.343 | Y20: -0.52356333 | Z20: 1.7611018 | AA20: =SUM(K20,Q20,W20)/3 -> 2658.0133
A21: =_xlfn.XLOOKUP('[1]CMK - 30.09.2025'!$N$1:$N$1048576,'[1]CMK - 30.09.2025'!$J$1:$J$1048576,"-",0) -> #NAME? | B21: INDIVIDUAL | C21: INDIVIDUAL | D21: INDEPENDENTES | E21: 614946000148 | F21: 00614946000148 - DROGA MED REIS LTDA | H21: MG | I21: 554.788 | J21: 554.788 | K21: 1393.6 | L21: 838.812 | M21: 1.5119505 | N21: - | O21: 1385.398 | P21: 1385.398 | Q21: 1557.49 | R21: 172.092 | S21: 0.12421846 | T21: 0.11760189 | U21: 5592.523 | V21: 5592.523 | W21: 1674.26 | X21: -3918.263 | Y21: -0.70062528 | Z21: 0.074973194 | AA21: =SUM(K21,Q21,W21)/3 -> 1541.7833
A22: =_xlfn.XLOOKUP('[1]CMK - 30.09.2025'!$N$1:$N$1048576,'[1]CMK - 30.09.2025'!$J$1:$J$1048576,"-",0) -> #NAME? | B22: INDIVIDUAL | C22: INDIVIDUAL | D22: INDEPENDENTES | E22: 616871000134 | F22: 00616871000134 - FARMACIA DO PAULINHO EIRELI | H22: MG | I22: 1608.494 | J22: 1608.494 | K22: 1136.82 | L22: -471.674 | M22: -0.29323951 | N22: - | O22: 860.253 | P22: 860.253 | Q22: 708.76 | R22: -151.493 | S22: -0.17610284 | T22: -0.37654158 | U22: 1462.302 | V22: 1462.302 | W22: 1217.26 | X22: -245.042 | Y22: -0.16757277 | Z22: 0.71745019 | AA22: =SUM(K22,Q22,W22)/3 -> 1020.9467
A23: =_xlfn.XLOOKUP('[1]CMK - 30.09.2025'!$N$1:$N$1048576,'[1]CMK - 30.09.2025'!$J$1:$J$1048576,"-",0) -> #NAME? | B23: INDIVIDUAL | C23: INDIVIDUAL | D23: INDEPENDENTES | E23: 619378000178 | F23: 00619378000178 - FCIA E DROG LUERSEN LT | H23: MG | I23: - | J23: - | K23: - | L23: - | M23: - | N23: - | O23: - | P23: - | Q23: - | R23: - | S23: - | T23: - | U23: 0 | V23: 0 | W23: 714.92 | X23: 714.92 | Y23: - | Z23: - | AA23: =SUM(K23,Q23,W23)/3 -> 238.30667
A24: =_xlfn.XLOOKUP('[1]CMK - 30.09.2025'!$N$1:$N$1048576,'[1]CMK - 30.09.2025'!$J$1:$J$1048576,"-",0) -> #NAME? | B24: INDIVIDUAL | C24: INDIVIDUAL | D24: INDEPENDENTES | E24: 624132000194 | F24: 00624132000194 - SAULO BRUNO ALVES E CIA LTDA | H24: MG | I24: 9699.609 | J24: 9699.609 | K24: 19479.11 | L24: 9779.501 | M24: 1.0082366 | N24: - | O24: 2329.763 | P24: 2329.763 | Q24: 718.09 | R24: -1611.673 | S24: -0.69177552 | T24: -0.96313538 | U24: 98.96 | V24: 98.96 | W24: 730.91 | X24: 631.95 | Y24: 6.3859135 | Z24: 0.017852915 | AA24: =SUM(K24,Q24,W24)/3 -> 6976.0367
A25: =_xlfn.XLOOKUP('[1]CMK - 30.09.2025'!$N$1:$N$1048576,'[1]CMK - 30.09.2025'!$J$1:$J$1048576,"-",0) -> #NAME? | B25: INDIVIDUAL | C25: INDIVIDUAL | D25: INDEPENDENTES | E25: 794195000199 | F25: 00794195000199 - DROGARIA MARILENE DRUGSTORE LTDA | H25: MG | I25: 8353.166 | J25: 8353.166 | K25: 16120.33 | L25: 7767.164 | M25: 0.92984672 | N25: - | O25: 5692.939 | P25: 5692.939 | Q25: 15306.81 | R25: 9613.871 | S25: 1.688736 | T25: -0.050465468 | U25: 8290.001 | V25: 8290.001 | W25: 20407.67 | X25: 12117.669 | Y25: 1.4617211 | Z25: 0.33324122 | AA25: =SUM(K25,Q25,W25)/3 -> 17278.27
A26: =_xlfn.XLOOKUP('[1]CMK - 30.09.2025'!$N$1:$N$1048576,'[1]CMK - 30.09.2025'!$J$1:$J$1048576,"-",0) -> #NAME? | B26: INDIVIDUAL | C26: INDIVIDUAL | D26: INDEPENDENTES | E26: 808730000113 | F26: 00808730000113 - ELEMENTAR DROGARIAS LTDA | H26: MG | I26: 39936.619 | J26: 39936.619 | K26: 19971.84 | L26: -19964.779 | M26: -0.4999116 | N26: - | O26: 33969.634 | P26: 33969.634 | Q26: 19905.99 | R26: -14063.644 | S26: -0.41400634 | T26: -0.0032971424 | U26: 58686.035 | V26: 58686.035 | W26: 33510.48 | X26: -25175.555 | Y26: -0.42898715 | Z26: 0.683437 | AA26: =SUM(K26,Q26,W26)/3 -> 24462.77
A27: =_xlfn.XLOOKUP('[1]CMK - 30.09.2025'!$N$1:$N$1048576,'[1]CMK - 30.09.2025'!$J$1:$J$1048576,"-",0) -> #NAME? | B27: INDIVIDUAL | C27: INDIVIDUAL | D27: INDEPENDENTES | E27: 808730000709 | F27: 00808730000709 - ELEMENTAR DROGARIAS LTDA EPP | H27: MG | I27: 81121.781 | J27: 81121.781 | K27: 51051.98 | L27: -30069.801 | M27: -0.37067481 | N27: - | O27: 67958.471 | P27: 67958.471 | Q27: 40767.02 | R27: -27191.451 | S27: -0.40011864 | T27: -0.20146055 | U27: 97055.663 | V27: 97055.663 | W27: 50569.9 | X27: -46485.763 | Y27: -0.47895982 | Z27: 0.24046104 | AA27: =SUM(K27,Q27,W27)/3 -> 47462.967
A28: =_xlfn.XLOOKUP('[1]CMK - 30.09.2025'!$N$1:$N$1048576,'[1]CMK - 30.09.2025'!$J$1:$J$1048576,"-",0) -> #NAME? | B28: INDIVIDUAL | C28: INDIVIDUAL | D28: INDEPENDENTES | E28: 823568000102 | F28: 00823568000102 - ORG REIS ARAUJO LTDA ME | H28: MG | I28: 9178.908 | J28: 9178.908 | K28: 5803.05 | L28: -3375.858 | M28: -0.36778427 | N28: - | O28: 10457.922 | P28: 10457.922 | Q28: 3632.87 | R28: -6825.052 | S28: -0.65262028 | T28: -0.37397231 | U28: 17807.597 | V28: 17807.597 | W28: 6209.69 | X28: -11597.907 | Y28: -0.65128984 | Z28: 0.70930697 | AA28: =SUM(K28,Q28,W28)/3 -> 5215.2033
A29: =_xlfn.XLOOKUP('[1]CMK - 30.09.2025'!$N$1:$N$1048576,'[1]CMK - 30.09.2025'!$J$1:$J$1048576,"-",0) -> #NAME? | B29: INDIVIDUAL | C29: INDIVIDUAL | D29: INDEPENDENTES | E29: 858625000199 | F29: 00858625000199 - DROGARIA CAJU DE FRUTAL LTDA | H29: MG | I29: 3225.929 | J29: 3225.929 | K29: 2948.15 | L29: -277.779 | M29: -0.086108219 | N29: - | O29: 429.235 | P29: 429.235 | Q29: 92.77 | R29: -336.465 | S29: -0.78387131 | T29: -0.96853281 | U29: 209.152 | V29: 209.152 | W29: 0 | X29: -209.152 | Y29: -1 | Z29: -1 | AA29: =SUM(K29,Q29,W29)/3 -> 1013.64
A30: =_xlfn.XLOOKUP('[1]CMK - 30.09.2025'!$N$1:$N$1048576,'[1]CMK - 30.09.2025'!$J$1:$J$1048576,"-",0) -> #NAME? | B30: INDIVIDUAL | C30: INDIVIDUAL | D30: INDEPENDENTES | E30: 861004000164 | F30: 00861004000164 - CAROL MEDICAMENTOS LTDA | H30: MG | I30: 2009.721 | J30: 2009.721 | K30: 956.55 | L30: -1053.171 | M30: -0.52403841 | N30: - | O30: 1546.64 | P30: 1546.64 | Q30: 742.15 | R30: -804.49 | S30: -0.52015336 | T30: -0.22413883 | U30: 4256.497 | V30: 4256.497 | W30: 1479.89 | X30: -2776.607 | Y30: -0.65232209 | Z30: 0.99405781 | AA30: =SUM(K30,Q30,W30)/3 -> 1059.53
A31: =_xlfn.XLOOKUP('[1]CMK - 30.09.2025'!$N$1:$N$1048576,'[1]CMK - 30.09.2025'!$J$1:$J$1048576,"-",0) -> #NAME? | B31: INDIVIDUAL | C31: INDIVIDUAL | D31: INDEPENDENTES | E31: 887337000162 | F31: 00887337000162 - REIS & MATOS LTDA | H31: MG | I31: 11791.021 | J31: 11791.021 | K31: 21275.43 | L31: 9484.409 | M31: 0.80437555 | N31: - | O31: 15551.836 | P31: 15551.836 | Q31: 13603.95 | R31: -1947.886 | S31: -0.12525119 | T31: -0.36057932 | U31: 19639.423 | V31: 19639.423 | W31: 17534.53 | X31: -2104.893 | Y31: -0.10717693 | Z31: 0.28892932 | AA31: =SUM(K31,Q31,W31)/3 -> 17471.303
A32: =_xlfn.XLOOKUP('[1]CMK - 30.09.2025'!$N$1:$N$1048576,'[1]CMK - 30.09.2025'!$J$1:$J$1048576,"-",0) -> #NAME? | B32: INDIVIDUAL | C32: INDIVIDUAL | D32: INDEPENDENTES | E32: 969186000191 | F32: 00969186000191 - DROGARIA 3R & V LTDA ME | H32: MG | I32: 17795.741 | J32: 17795.741 | K32: 17603.04 | L32: -192.701 | M32: -0.01082849 | N32: - | O32: 15040.282 | P32: 15040.282 | Q32: 15643.46 | R32: 603.178 | S32: 0.040104168 | T32: -0.11132054 | U32: 16919.165 | V32: 16919.165 | W32: 20854.76 | X32: 3935.595 | Y32: 0.23261166 | Z32: 0.33312963 | AA32: =SUM(K32,Q32,W32)/3 -> 18033.753
A33: =_xlfn.XLOOKUP('[1]CMK - 30.09.2025'!$N$1:$N$1048576,'[1]CMK - 30.09.2025'!$J$1:$J$1048576,"-",0) -> #NAME? | B33: INDIVIDUAL | C33: INDIVIDUAL | D33: INDEPENDENTES | E33: 981525000155 | F33: 00981525000155 - MENDONCA & MENDONCA LTDA ME | H33: MG | I33: - | J33: - | K33: - | L33: - | M33: - | N33: - | O33: 0 | P33: 0 | Q33: 1002.3 | R33: 1002.3 | S33: - | T33: - | U33: 0 | V33: 0 | W33: 0 | X33: 0 | Y33: - | Z33: -1 | AA33: =SUM(K33,Q33,W33)/3 -> 334.1
A34: =_xlfn.XLOOKUP('[1]CMK - 30.09.2025'!$N$1:$N$1048576,'[1]CMK - 30.09.2025'!$J$1:$J$1048576,"-",0) -> #NAME? | B34: INDIVIDUAL | C34: INDIVIDUAL | D34: INDEPENDENTES | E34: 1001654000100 | F34: 01001654000100 - JOSE OSORIO FERREIRA & CIA LT | H34: MG | I34: 1426.98 | J34: 1426.98 | K34: 1613.52 | L34: 186.54 | M34: 0.13072363 | N34: - | O34: 3696.914 | P34: 3696.914 | Q34: 516.6 | R34: -3180.314 | S34: -0.86026183 | T34: -0.67983043 | U34: 2583.379 | V34: 2583.379 | W34: 1003.33 | X34: -1580.049 | Y34: -0.61162106 | Z34: 0.94217964 | AA34: =SUM(K34,Q34,W34)/3 -> 1044.4833
A35: =_xlfn.XLOOKUP('[1]CMK - 30.09.2025'!$N$1:$N$1048576,'[1]CMK - 30.09.2025'!$J$1:$J$1048576,"-",0) -> #NAME? | B35: INDIVIDUAL | C35: INDIVIDUAL | D35: INDEPENDENTES | E35: 1091254000125 | F35: 01091254000125 - ELIANA IGNACIO FERNANDES E SILVA | H35: MG | I35: 453.764 | J35: 453.764 | K35: 640.06 | L35: 186.296 | M35: 0.41055703 | N35: - | O35: 200.424 | P35: 200.424 | Q35: 71.1 | R35: -129.324 | S35: -0.64525207 | T35: -0.88891666 | U35: 387.627 | V35: 387.627 | W35: 601.86 | X35: 214.233 | Y35: 0.55267822 | Z35: 7.4649789 | AA35: =SUM(K35,Q35,W35)/3 -> 437.67333
A36: =_xlfn.XLOOKUP('[1]CMK - 30.09.2025'!$N$1:$N$1048576,'[1]CMK - 30.09.2025'!$J$1:$J$1048576,"-",0) -> #NAME? | B36: INDIVIDUAL | C36: INDIVIDUAL | D36: INDEPENDENTES | E36: 1122922000134 | F36: 01122922000134 - DROGALON LTDA ME | H36: MG | I36: 54.919 | J36: 54.919 | K36: 372.78 | L36: 317.861 | M36: 5.7878148 | N36: - | O36: 0 | P36: 0 | Q36: 0 | R36: 0 | S36: - | T36: -1 | U36: 70.289 | V36: 70.289 | W36: 112.16 | X36: 41.871 | Y36: 0.59569776 | Z36: - | AA36: =SUM(K36,Q36,W36)/3 -> 161.64667
A37: =_xlfn.XLOOKUP('[1]CMK - 30.09.2025'!$N$1:$N$1048576,'[1]CMK - 30.09.2025'!$J$1:$J$1048576,"-",0) -> #NAME? | B37: INDIVIDUAL | C37: INDIVIDUAL | D37: INDEPENDENTES | E37: 1218314000128 | F37: 01218314000128 - HELIO ANTONIO MACHADO LTDA | H37: MG | I37: 12550.637 | J37: 12550.637 | K37: 20741.64 | L37: 8191.003 | M37: 0.65263644 | N37: - | O37: 14121.031 | P37: 14121.031 | Q37: 40056.61 | R37: 25935.579 | S37: 1.8366633 | T37: 0.93121711 | U37: 16015.567 | V37: 16015.567 | W37: 17253.39 | X37: 1237.823 | Y37: 0.07728874 | Z37: -0.56927483 | AA37: =SUM(K37,Q37,W37)/3 -> 26017.213
A38: =_xlfn.XLOOKUP('[1]CMK - 30.09.2025'!$N$1:$N$1048576,'[1]CMK - 30.09.2025'!$J$1:$J$1048576,"-",0) -> #NAME? | B38: INDIVIDUAL | C38: INDIVIDUAL | D38: INDEPENDENTES | E38: 1379836000101 | F38: 01379836000101 - DROG PERF S R VITERBO LTDA ME | H38: MG | I38: 3480.026 | J38: 3480.026 | K38: 2600.25 | L38: -879.776 | M38: -0.25280731 | N38: - | O38: 8875.334 | P38: 8875.334 | Q38: 1349.69 | R38: -7525.644 | S38: -0.84792798 | T38: -0.48093837 | U38: 6573.932 | V38: 6573.932 | W38: 3824.77 | X38: -2749.162 | Y38: -0.41819143 | Z38: 1.8338137 | AA38: =SUM(K38,Q38,W38)/3 -> 2591.57
A39: =_xlfn.XLOOKUP('[1]CMK - 30.09.2025'!$N$1:$N$1048576,'[1]CMK - 30.09.2025'!$J$1:$J$1048576,"-",0) -> #NAME? | B39: INDIVIDUAL | C39: INDIVIDUAL | D39: INDEPENDENTES | E39: 1416103000108 | F39: 01416103000108 - J E G MEDICAMENTOS E PERFUMARIA LTD | H39: MG | I39: 3162.508 | J39: 3162.508 | K39: 3656.88 | L39: 494.372 | M39: 0.15632277 | N39: - | O39: 2839.145 | P39: 2839.145 | Q39: 1935.14 | R39: -904.005 | S39: -0.31840748 | T39: -0.47082212 | U39: 3347.925 | V39: 3347.925 | W39: 3446.62 | X39: 98.695 | Y39: 0.029479454 | Z39: 0.7810701 | AA39: =SUM(K39,Q39,W39)/3 -> 3012.88
A40: =_xlfn.XLOOKUP('[1]CMK - 30.09.2025'!$N$1:$N$1048576,'[1]CMK - 30.09.2025'!$J$1:$J$1048576,"-",0) -> #NAME? | B40: INDIVIDUAL | C40: INDIVIDUAL | D40: INDEPENDENTES | E40: 1417694000120 | F40: 01417694000120 - DISTRIMIX DIST DE MED LTDA | H40: MG | I40: 18110.764 | J40: 18110.764 | K40: 11863.11 | L40: -6247.654 | M40: -0.3449691 | N40: - | O40: 26008.069 | P40: 26008.069 | Q40: 22696.84 | R40: -3311.229 | S40: -0.12731545 | T40: 0.91322849 | U40: 45830.996 | V40: 45830.996 | W40: 15113.51 | X40: -30717.486 | Y40: -0.67023387 | Z40: -0.33411391 | AA40: =SUM(K40,Q40,W40)/3 -> 16557.82
A41: =_xlfn.XLOOKUP('[1]CMK - 30.09.2025'!$N$1:$N$1048576,'[1]CMK - 30.09.2025'!$J$1:$J$1048576,"-",0) -> #NAME? | B41: INDIVIDUAL | C41: INDIVIDUAL | D41: INDEPENDENTES | E41: 1468894000101 | F41: 01468894000101 - DROGARIA ANGELO RONCALLI LTDA | H41: MG | I41: 2176.175 | J41: 2176.175 | K41: 1806.13 | L41: -370.045 | M41: -0.17004377 | N41: - | O41: 487.969 | P41: 487.969 | Q41: 1539.52 | R41: 1051.551 | S41: 2.1549545 | T41: -0.14761396 | U41: 1081.998 | V41: 1081.998 | W41: 2617.32 | X41: 1535.322 | Y41: 1.4189694 | Z41: 0.70008834 | AA41: =SUM(K41,Q41,W41)/3 -> 1987.6567
A42: =_xlfn.XLOOKUP('[1]CMK - 30.09.2025'!$N$1:$N$1048576,'[1]CMK - 30.09.2025'!$J$1:$J$1048576,"-",0) -> #NAME? | B42: INDIVIDUAL | C42: INDIVIDUAL | D42: INDEPENDENTES | E42: 1487601000133 | F42: 01487601000133 - BH DIET A CASA DIABETICO LTDA | H42: MG | I42: 53.077 | J42: 53.077 | K42: 0 | L42: -53.077 | M42: -1 | N42: - | O42: 46.555 | P42: 46.555 | Q42: 0 | R42: -46.555 | S42: -1 | T42: - | U42: - | V42: - | W42: - | X42: - | Y42: - | Z42: - | AA42: =SUM(K42,Q42,W42)/3 -> 0
A43: =_xlfn.XLOOKUP('[1]CMK - 30.09.2025'!$N$1:$N$1048576,'[1]CMK - 30.09.2025'!$J$1:$J$1048576,"-",0) -> #NAME? | B43: INDIVIDUAL | C43: INDIVIDUAL | D43: INDEPENDENTES | E43: 1487601000303 | F43: 01487601000303 - BH DIET A CASA DO DIABETICO LTDA | H43: MG | I43: 3517.329 | J43: 3517.329 | K43: 4548.32 | L43: 1030.991 | M43: 0.29311759 | N43: - | O43: 7361.813 | P43: 7361.813 | Q43: 434.96 | R43: -6926.853 | S43: -0.94091673 | T43: -0.90436909 | U43: 22334.007 | V43: 22334.007 | W43: 368.45 | X43: -21965.557 | Y43: -0.98350274 | Z43: -0.15291061 | AA43: =SUM(K43,Q43,W43)/3 -> 1783.91
A44: =_xlfn.XLOOKUP('[1]CMK - 30.09.2025'!$N$1:$N$1048576,'[1]CMK - 30.09.2025'!$J$1:$J$1048576,"-",0) -> #NAME? | B44: INDIVIDUAL | C44: INDIVIDUAL | D44: INDEPENDENTES | E44: 1503902000103 | F44: 01503902000103 - H D SOUZA E CIA LTDA | H44: MG | I44: 1922.428 | J44: 1922.428 | K44: 1892.33 | L44: -30.098 | M44: -0.015656243 | N44: - | O44: 643.712 | P44: 643.712 | Q44: 1195.69 | R44: 551.978 | S44: 0.85749217 | T44: -0.36813875 | U44: 0 | V44: 0 | W44: 497.77 | X44: 497.77 | Y44: - | Z44: -0.58369644 | AA44: =SUM(K44,Q44,W44)/3 -> 1195.2633
A45: =_xlfn.XLOOKUP('[1]CMK - 30.09.2025'!$N$1:$N$1048576,'[1]CMK - 30.09.2025'!$J$1:$J$1048576,"-",0) -> #NAME? | B45: INDIVIDUAL | C45: INDIVIDUAL | D45: INDEPENDENTES | E45: 1554175000103 | F45: 01554175000103 - DROGARIA OLIVEIRA MENEZES LTDA | H45: MG | I45: - | J45: - | K45: - | L45: - | M45: - | N45: - | O45: - | P45: - | Q45: - | R45: - | S45: - | T45: - | U45: 0 | V45: 0 | W45: 144.38 | X45: 144.38 | Y45: - | Z45: - | AA45: =SUM(K45,Q45,W45)/3 -> 48.126667
A46: =_xlfn.XLOOKUP('[1]CMK - 30.09.2025'!$N$1:$N$1048576,'[1]CMK - 30.09.2025'!$J$1:$J$1048576,"-",0) -> #NAME? | B46: INDIVIDUAL | C46: INDIVIDUAL | D46: INDEPENDENTES | E46: 1559907000158 | F46: 01559907000158 - FARMALUZ FARMACIA LTDA | H46: MG | I46: 44569.319 | J46: 44569.319 | K46: 28582.52 | L46: -15986.799 | M46: -0.35869516 | N46: - | O46: 68772.934 | P46: 68772.934 | Q46: 21948.26 | R46: -46824.674 | S46: -0.68085904 | T46: -0.232109 | U46: 86162.981 | V46: 86162.981 | W46: 32972.25 | X46: -53190.731 | Y46: -0.61732696 | Z46: 0.50227171 | AA46: =SUM(K46,Q46,W46)/3 -> 27834.343
A47: =_xlfn.XLOOKUP('[1]CMK - 30.09.2025'!$N$1:$N$1048576,'[1]CMK - 30.09.2025'!$J$1:$J$1048576,"-",0) -> #NAME? | B47: INDIVIDUAL | C47: INDIVIDUAL | D47: INDEPENDENTES | E47: 1579758000199 | F47: 01579758000199 - PERFUMARIA SUL AMERICANA LT | H47: MG | I47: 601.425 | J47: 601.425 | K47: 0 | L47: -601.425 | M47: -1 | N47: - | O47: 343.402 | P47: 343.402 | Q47: 0 | R47: -343.402 | S47: -1 | T47: - | U47: 1313.659 | V47: 1313.659 | W47: 196.87 | X47: -1116.789 | Y47: -0.85013615 | Z47: - | AA47: =SUM(K47,Q47,W47)/3 -> 65.623333
A48: =_xlfn.XLOOKUP('[1]CMK - 30.09.2025'!$N$1:$N$1048576,'[1]CMK - 30.09.2025'!$J$1:$J$1048576,"-",0) -> #NAME? | B48: INDIVIDUAL | C48: INDIVIDUAL | D48: INDEPENDENTES | E48: 1593817000183 | F48: 01593817000183 - GIOVANI MANOEL DA SILVA ME | H48: MG | I48: 938.513 | J48: 938.513 | K48: 3584.5 | L48: 2645.987 | M48: 2.8193397 | N48: - | O48: 1145.758 | P48: 1145.758 | Q48: 3245.64 | R48: 2099.882 | S48: 1.8327448 | T48: -0.094534803 | U48: 454.38 | V48: 454.38 | W48: 1507.56 | X48: 1053.18 | Y48: 2.3178397 | Z48: -0.53551226 | AA48: =SUM(K48,Q48,W48)/3 -> 2779.2333
A49: =_xlfn.XLOOKUP('[1]CMK - 30.09.2025'!$N$1:$N$1048576,'[1]CMK - 30.09.2025'!$J$1:$J$1048576,"-",0) -> #NAME? | B49: INDIVIDUAL | C49: INDIVIDUAL | D49: INDEPENDENTES | E49: 1653069000187 | F49: 01653069000187 - ROMULO SOARES FERREIRA JR ME | H49: MG | I49: 2256.157 | J49: 2256.157 | K49: 5340.82 | L49: 3084.663 | M49: 1.36722 | N49: - | O49: 2523.132 | P49: 2523.132 | Q49: 1911.04 | R49: -612.092 | S49: -0.24259214 | T49: -0.64218229 | U49: 2719.6 | V49: 2719.6 | W49: 4342.51 | X49: 1622.91 | Y49: 0.59674584 | Z49: 1.2723282 | AA49: =SUM(K49,Q49,W49)/3 -> 3864.79
A50: =_xlfn.XLOOKUP('[1]CMK - 30.09.2025'!$N$1:$N$1048576,'[1]CMK - 30.09.2025'!$J$1:$J$1048576,"-",0) -> #NAME? | B50: INDIVIDUAL | C50: INDIVIDUAL | D50: INDEPENDENTES | E50: 1722349000108 | F50: 01722349000108 - DROGARIA TAPIRA LTDA ME | H50: MG | I50: 2002.327 | J50: 2002.327 | K50: 1196.69 | L50: -805.637 | M50: -0.40235037 | N50: - | O50: 1623.611 | P50: 1623.611 | Q50: 2198.63 | R50: 575.019 | S50: 0.35416057 | T50: 0.83725944 | U50: 2373.209 | V50: 2373.209 | W50: 2210.47 | X50: -162.739 | Y50: -0.068573396 | Z50: 0.0053851717 | AA50: =SUM(K50,Q50,W50)/3 -> 1868.5967
A51: =_xlfn.XLOOKUP('[1]CMK - 30.09.2025'!$N$1:$N$1048576,'[1]CMK - 30.09.2025'!$J$1:$J$1048576,"-",0) -> #NAME? | B51: INDIVIDUAL | C51: INDIVIDUAL | D51: INDEPENDENTES | E51: 1753162000163 | F51: 01753162000163 - COMERCIAL VIANA E LANA LTDA | H51: MG | I51: 1862.168 | J51: 1862.168 | K51: 1009.69 | L51: -852.478 | M51: -0.45778791 | N51: - | O51: 1155.43 | P51: 1155.43 | Q51: 1590.37 | R51: 434.94 | S51: 0.37643129 | T51: 0.57510721 | U51: 1367.099 | V51: 1367.099 | W51: 2773.78 | X51: 1406.681 | Y51: 1.0289533 | Z51: 0.74410986 | AA51: =SUM(K51,Q51,W51)/3 -> 1791.28
A52: =_xlfn.XLOOKUP('[1]CMK - 30.09.2025'!$N$1:$N$1048576,'[1]CMK - 30.09.2025'!$J$1:$J$1048576,"-",0) -> #NAME? | B52: INDIVIDUAL | C52: INDIVIDUAL | D52: INDEPENDENTES | E52: 1773180000107 | F52: 01773180000107 - DROGARIA SOUZA E CASTRO LTDA | H52: MG | I52: 15115.102 | J52: 15115.102 | K52: 13036.14 | L52: -2078.962 | M52: -0.13754204 | N52: - | O52: 13675.621 | P52: 13675.621 | Q52: 12913.56 | R52: -762.061 | S52: -0.055724051 | T52: -0.0094030902 | U52: 15709.657 | V52: 15709.657 | W52: 13806.89 | X52: -1902.767 | Y52: -0.12112085 | Z52: 0.069177671 | AA52: =SUM(K52,Q52,W52)/3 -> 13252.197
A53: =_xlfn.XLOOKUP('[1]CMK - 30.09.2025'!$N$1:$N$1048576,'[1]CMK - 30.09.2025'!$J$1:$J$1048576,"-",0) -> #NAME? | B53: INDIVIDUAL | C53: INDIVIDUAL | D53: INDEPENDENTES | E53: 1793079000118 | F53: 01793079000118 - J M DUARTE & V L BRAGA LTDA ME | H53: MG | I53: 1542.051 | J53: 1542.051 | K53: 223.88 | L53: -1318.171 | M53: -0.85481673 | N53: - | O53: 1652.09 | P53: 1652.09 | Q53: 860.85 | R53: -791.24 | S53: -0.47893275 | T53: 2.8451403 | U53: 1268.874 | V53: 1268.874 | W53: 270.35 | X53: -998.524 | Y53: -0.78693708 | Z53: -0.68594993 | AA53: =SUM(K53,Q53,W53)/3 -> 451.69333
A54: =_xlfn.XLOOKUP('[1]CMK - 30.09.2025'!$N$1:$N$1048576,'[1]CMK - 30.09.2025'!$J$1:$J$1048576,"-",0) -> #NAME? | B54: INDIVIDUAL | C54: INDIVIDUAL | D54: INDEPENDENTES | E54: 1803984000101 | F54: 01803984000101 - DROG MARQUES & PAULA LTDA ME | H54: MG | I54: 6022.002 | J54: 6022.002 | K54: 6242.62 | L54: 220.618 | M54: 0.036635325 | N54: - | O54: 3666.939 | P54: 3666.939 | Q54: 9973.88 | R54: 6306.941 | S54: 1.7199471 | T54: 0.59770737 | U54: 12142.365 | V54: 12142.365 | W54: 6333.65 | X54: -5808.715 | Y54: -0.47838415 | Z54: -0.36497632 | AA54: =SUM(K54,Q54,W54)/3 -> 7516.7167
A55: =_xlfn.XLOOKUP('[1]CMK - 30.09.2025'!$N$1:$N$1048576,'[1]CMK - 30.09.2025'!$J$1:$J$1048576,"-",0) -> #NAME? | B55: INDIVIDUAL | C55: INDIVIDUAL | D55: INDEPENDENTES | E55: 1814357000176 | F55: 01814357000176 - DROGARIA DIAS E LOPES LTDA | H55: MG | I55: 14717.413 | J55: 14717.413 | K55: 19551.84 | L55: 4834.427 | M55: 0.32848348 | N55: - | O55: 18638.438 | P55: 18638.438 | Q55: 16308.19 | R55: -2330.248 | S55: -0.12502378 | T55: -0.16589999 | U55: 13527.078 | V55: 13527.078 | W55: 19165.32 | X55: 5638.242 | Y55: 0.41681152 | Z55: 0.17519602 | AA55: =SUM(K55,Q55,W55)/3 -> 18341.783
A56: =_xlfn.XLOOKUP('[1]CMK - 30.09.2025'!$N$1:$N$1048576,'[1]CMK - 30.09.2025'!$J$1:$J$1048576,"-",0) -> #NAME? | B56: INDIVIDUAL | C56: INDIVIDUAL | D56: INDEPENDENTES | E56: 1814832000104 | F56: 01814832000104 - DROGACELIO LTDA ME | H56: MG | I56: 8653.895 | J56: 8653.895 | K56: 8017.71 | L56: -636.185 | M56: -0.073514296 | N56: - | O56: 7261.819 | P56: 7261.819 | Q56: 10005.85 | R56: 2744.031 | S56: 0.37787103 | T56: 0.24796856 | U56: 9074.701 | V56: 9074.701 | W56: 9291.88 | X56: 217.179 | Y56: 0.023932359 | Z56: -0.071355257 | AA56: =SUM(K56,Q56,W56)/3 -> 9105.1467
A57: =_xlfn.XLOOKUP('[1]CMK - 30.09.2025'!$N$1:$N$1048576,'[1]CMK - 30.09.2025'!$J$1:$J$1048576,"-",0) -> #NAME? | B57: INDIVIDUAL | C57: INDIVIDUAL | D57: INDEPENDENTES | E57: 1815812000158 | F57: 01815812000158 - DROGARIA NOVA ALVORADA LTDA ME | H57: MG | I57: 12348.595 | J57: 12348.595 | K57: 11311.43 | L57: -1037.165 | M57: -0.083990527 | N57: - | O57: 2585.611 | P57: 2585.611 | Q57: 14945.11 | R57: 12359.499 | S57: 4.7801077 | T57: 0.32123967 | U57: 7227.948 | V57: 7227.948 | W57: 18641.24 | X57: 11413.292 | Y57: 1.5790501 | Z57: 0.24731367 | AA57: =SUM(K57,Q57,W57)/3 -> 14965.927
A58: =_xlfn.XLOOKUP('[1]CMK - 30.09.2025'!$N$1:$N$1048576,'[1]CMK - 30.09.2025'!$J$1:$J$1048576,"-",0) -> #NAME? | B58: INDIVIDUAL | C58: INDIVIDUAL | D58: INDEPENDENTES | E58: 1833506000144 | F58: 01833506000144 - MARIA ZILDA DA CRUZ ASSIS | H58: MG | I58: 177.606 | J58: 177.606 | K58: 0 | L58: -177.606 | M58: -1 | N58: - | O58: 1668.215 | P58: 1668.215 | Q58: 467.64 | R58: -1200.575 | S58: -0.71967642 | T58: - | U58: 3502.225 | V58: 3502.225 | W58: 204.92 | X58: -3297.305 | Y58: -0.94148863 | Z58: -0.56179967 | AA58: =SUM(K58,Q58,W58)/3 -> 224.18667
A59: =_xlfn.XLOOKUP('[1]CMK - 30.09.2025'!$N$1:$N$1048576,'[1]CMK - 30.09.2025'!$J$1:$J$1048576,"-",0) -> #NAME? | B59: INDIVIDUAL | C59: INDIVIDUAL | D59: INDEPENDENTES | E59: 1839790000166 | F59: 01839790000166 - DROG MARQUES VIEIRA LTDA | H59: MG | I59: 3229.161 | J59: 3229.161 | K59: 2675.91 | L59: -553.251 | M59: -0.17132964 | N59: - | O59: 2033.968 | P59: 2033.968 | Q59: 2477.42 | R59: 443.452 | S59: 0.2180231 | T59: -0.074176635 | U59: 3719.649 | V59: 3719.649 | W59: 2917.73 | X59: -801.919 | Y59: -0.21558997 | Z59: 0.17772925 | AA59: =SUM(K59,Q59,W59)/3 -> 2690.3533
A60: =_xlfn.XLOOKUP('[1]CMK - 30.09.2025'!$N$1:$N$1048576,'[1]CMK - 30.09.2025'!$J$1:$J$1048576,"-",0) -> #NAME? | B60: INDIVIDUAL | C60: INDIVIDUAL | D60: INDEPENDENTES | E60: 1845535000126 | F60: 01845535000126 - DROGARIA ALTO DA CRUZ LTDA | H60: MG | I60: 2455.451 | J60: 2455.451 | K60: 2871.3 | L60: 415.849 | M60: 0.16935748 | N60: - | O60: 3371.362 | P60: 3371.362 | Q60: 2720.66 | R60: -650.702 | S60: -0.19300864 | T60: -0.052464041 | U60: 977.387 | V60: 977.387 | W60: 3900.93 | X60: 2923.543 | Y60: 2.9911826 | Z60: 0.43381753 | AA60: =SUM(K60,Q60,W60)/3 -> 3164.2967
A61: =_xlfn.XLOOKUP('[1]CMK - 30.09.2025'!$N$1:$N$1048576,'[1]CMK - 30.09.2025'!$J$1:$J$1048576,"-",0) -> #NAME? | B61: INDIVIDUAL | C61: INDIVIDUAL | D61: INDEPENDENTES | E61: 1910759000174 | F61: 01910759000174 - EDNALDO CARDOSO SILVA ME | H61: MG | I61: 1532.707 | J61: 1532.707 | K61: 3711.19 | L61: 2178.483 | M61: 1.4213304 | N61: - | O61: 1527.059 | P61: 1527.059 | Q61: 1590.5 | R61: 63.441 | S61: 0.041544564 | T61: -0.57143127 | U61: 2400.201 | V61: 2400.201 | W61: 4655.17 | X61: 2254.969 | Y61: 0.93949173 | Z61: 1.9268595 | AA61: =SUM(K61,Q61,W61)/3 -> 3318.9533
A62: =_xlfn.XLOOKUP('[1]CMK - 30.09.2025'!$N$1:$N$1048576,'[1]CMK - 30.09.2025'!$J$1:$J$1048576,"-",0) -> #NAME? | B62: INDIVIDUAL | C62: INDIVIDUAL | D62: INDEPENDENTES | E62: 1912063000187 | F62: 01912063000187 - DIMAS GONZAGA DA SILVA | H62: MG | I62: 3983.128 | J62: 3983.128 | K62: 3121.02 | L62: -862.108 | M62: -0.21643994 | N62: - | O62: 3575.107 | P62: 3575.107 | Q62: 3904.43 | R62: 329.323 | S62: 0.092115565 | T62: 0.25101089 | U62: 2583.184 | V62: 2583.184 | W62: 7640.33 | X62: 5057.146 | Y62: 1.9577181 | Z62: 0.95683621 | AA62: =SUM(K62,Q62,W62)/3 -> 4888.5933
A63: =_xlfn.XLOOKUP('[1]CMK - 30.09.2025'!$N$1:$N$1048576,'[1]CMK - 30.09.2025'!$J$1:$J$1048576,"-",0) -> #NAME? | B63: INDIVIDUAL | C63: INDIVIDUAL | D63: INDEPENDENTES | E63: 1917982000143 | F63: 01917982000143 - MT DROG E PERF LTDA | H63: MG | I63: 1719.098 | J63: 1719.098 | K63: 790.37 | L63: -928.728 | M63: -0.54024145 | N63: - | O63: 2045.183 | P63: 2045.183 | Q63: 1524.56 | R63: -520.623 | S63: -0.25456059 | T63: 0.92891937 | U63: 4516.289 | V63: 4516.289 | W63: 232.15 | X63: -4284.139 | Y63: -0.94859718 | Z63: -0.84772656 | AA63: =SUM(K63,Q63,W63)/3 -> 849.02667
A64: =_xlfn.XLOOKUP('[1]CMK - 30.09.2025'!$N$1:$N$1048576,'[1]CMK - 30.09.2025'!$J$1:$J$1048576,"-",0) -> #NAME? | B64: INDIVIDUAL | C64: INDIVIDUAL | D64: INDEPENDENTES | E64: 1937488000140 | F64: 01937488000140 - NILDA FCA SILVA E CIA LTDA ME | H64: MG | I64: 10169.816 | J64: 10169.816 | K64: 14135.91 | L64: 3966.094 | M64: 0.3899868 | N64: - | O64: 7999.447 | P64: 7999.447 | Q64: 7117.65 | R64: -881.797 | S64: -0.11023224 | T64: -0.49648449 | U64: 9757.885 | V64: 9757.885 | W64: 2992.16 | X64: -6765.725 | Y64: -0.69335978 | Z64: -0.57961406 | AA64: =SUM(K64,Q64,W64)/3 -> 8081.9067
A65: =_xlfn.XLOOKUP('[1]CMK - 30.09.2025'!$N$1:$N$1048576,'[1]CMK - 30.09.2025'!$J$1:$J$1048576,"-",0) -> #NAME? | B65: INDIVIDUAL | C65: INDIVIDUAL | D65: INDEPENDENTES | E65: 1946195000120 | F65: 01946195000120 - FELISBERTO E BEM LTDA | H65: MG | I65: 1183.968 | J65: 1183.968 | K65: 410.96 | L65: -773.008 | M65: -0.65289602 | N65: - | O65: 242.721 | P65: 242.721 | Q65: 1625.01 | R65: 1382.289 | S65: 5.6949708 | T65: 2.9541805 | U65: 1636.109 | V65: 1636.109 | W65: 1148.15 | X65: -487.959 | Y65: -0.29824358 | Z65: -0.2934505 | AA65: =SUM(K65,Q65,W65)/3 -> 1061.3733
A66: =_xlfn.XLOOKUP('[1]CMK - 30.09.2025'!$N$1:$N$1048576,'[1]CMK - 30.09.2025'!$J$1:$J$1048576,"-",0) -> #NAME? | B66: INDIVIDUAL | C66: INDIVIDUAL | D66: INDEPENDENTES | E66: 1946779000103 | F66: 01946779000103 - DROGARIA DIARIA LTDA | H66: MG | I66: 358.63 | J66: 358.63 | K66: 438.66 | L66: 80.03 | M66: 0.22315478 | N66: - | O66: 393.269 | P66: 393.269 | Q66: 0 | R66: -393.269 | S66: -1 | T66: -1 | U66: 486.242 | V66: 486.242 | W66: 0 | X66: -486.242 | Y66: -1 | Z66: - | AA66: =SUM(K66,Q66,W66)/3 -> 146.22
A67: =_xlfn.XLOOKUP('[1]CMK - 30.09.2025'!$N$1:$N$1048576,'[1]CMK - 30.09.2025'!$J$1:$J$1048576,"-",0) -> #NAME? | B67: INDIVIDUAL | C67: INDIVIDUAL | D67: INDEPENDENTES | E67: 1958959000105 | F67: 01958959000105 - DROGARIA JEQUERI LTDA | H67: MG | I67: 21622.73 | J67: 21622.73 | K67: 23059.26 | L67: 1436.53 | M67: 0.066436107 | N67: - | O67: 20281.032 | P67: 20281.032 | Q67: 20201.09 | R67: -79.942 | S67: -0.0039417126 | T67: -0.1239489 | U67: 23783.38 | V67: 23783.38 | W67: 21825.98 | X67: -1957.4 | Y67: -0.08230117 | Z67: 0.080435759 | AA67: =SUM(K67,Q67,W67)/3 -> 21695.443
A68: =_xlfn.XLOOKUP('[1]CMK - 30.09.2025'!$N$1:$N$1048576,'[1]CMK - 30.09.2025'!$J$1:$J$1048576,"-",0) -> #NAME? | B68: INDIVIDUAL | C68: INDIVIDUAL | D68: INDEPENDENTES | E68: 1991040000105 | F68: 01991040000105 - DROGARIA MM IPATINGA LTDA ME | H68: MG | I68: 6879.678 | J68: 6879.678 | K68: 3219.43 | L68: -3660.248 | M68: -0.53203769 | N68: - | O68: 7942.177 | P68: 7942.177 | Q68: 5447.71 | R68: -2494.467 | S68: -0.3140785 | T68: 0.69213494 | U68: 9852.227 | V68: 9852.227 | W68: 7304.72 | X68: -2547.507 | Y68: -0.25857169 | Z68: 0.34087901 | AA68: =SUM(K68,Q68,W68)/3 -> 5323.9533
A69: =_xlfn.XLOOKUP('[1]CMK - 30.09.2025'!$N$1:$N$1048576,'[1]CMK - 30.09.2025'!$J$1:$J$1048576,"-",0) -> #NAME? | B69: INDIVIDUAL | C69: INDIVIDUAL | D69: INDEPENDENTES | E69: 2055664000183 | F69: 02055664000183 - SIMONE CRISTINA C M CIA LTDA | H69: MG | I69: 549.435 | J69: 549.435 | K69: 571.35 | L69: 21.915 | M69: 0.039886429 | N69: - | O69: 9.949 | P69: 9.949 | Q69: 116.11 | R69: 106.161 | S69: 10.67052 | T69: -0.79677956 | U69: 817.51 | V69: 817.51 | W69: 1791.82 | X69: 974.31 | Y69: 1.1918019 | Z69: 14.43209 | AA69: =SUM(K69,Q69,W69)/3 -> 826.42667
A70: =_xlfn.XLOOKUP('[1]CMK - 30.09.2025'!$N$1:$N$1048576,'[1]CMK - 30.09.2025'!$J$1:$J$1048576,"-",0) -> #NAME? | B70: INDIVIDUAL | C70: INDIVIDUAL | D70: INDEPENDENTES | E70: 2099282000151 | F70: 02099282000151 - DROG AFONSO QUEIROZ LT ME | H70: MG | I70: 5027.876 | J70: 5027.876 | K70: 3216.39 | L70: -1811.486 | M70: -0.36028852 | N70: - | O70: 4056.341 | P70: 4056.341 | Q70: 607.83 | R70: -3448.511 | S70: -0.85015313 | T70: -0.81102105 | U70: 3878.098 | V70: 3878.098 | W70: 4019.4 | X70: 141.302 | Y70: 0.036435902 | Z70: 5.6127042 | AA70: =SUM(K70,Q70,W70)/3 -> 2614.54
A71: =_xlfn.XLOOKUP('[1]CMK - 30.09.2025'!$N$1:$N$1048576,'[1]CMK - 30.09.2025'!$J$1:$J$1048576,"-",0) -> #NAME? | B71: INDIVIDUAL | C71: INDIVIDUAL | D71: INDEPENDENTES | E71: 2117038000174 | F71: 02117038000174 - DROGARIA BOCAIUVA LTDA | H71: MG | I71: 20033.5 | J71: 20033.5 | K71: 5842.11 | L71: -14191.39 | M71: -0.70838296 | N71: - | O71: 26673.066 | P71: 26673.066 | Q71: 7906.24 | R71: -18766.826 | S71: -0.70358713 | T71: 0.35331926 | U71: 30006.222 | V71: 30006.222 | W71: 11273.82 | X71: -18732.402 | Y71: -0.62428392 | Z71: 0.42593951 | AA71: =SUM(K71,Q71,W71)/3 -> 8340.7233
A72: =_xlfn.XLOOKUP('[1]CMK - 30.09.2025'!$N$1:$N$1048576,'[1]CMK - 30.09.2025'!$J$1:$J$1048576,"-",0) -> #NAME? | B72: INDIVIDUAL | C72: INDIVIDUAL | D72: INDEPENDENTES | E72: 2231291000154 | F72: 02231291000154 - DROGARIA SOUZA COSTA LTDA ME | H72: MG | I72: 42802.692 | J72: 42802.692 | K72: 40909.96 | L72: -1892.732 | M72: -0.044219929 | N72: - | O72: 47506.556 | P72: 47506.556 | Q72: 38049.28 | R72: -9457.276 | S72: -0.19907307 | T72: -0.069926248 | U72: 47097.328 | V72: 47097.328 | W72: 74984.5 | X72: 27887.172 | Y72: 0.59211792 | Z72: 0.9707206 | AA72: =SUM(K72,Q72,W72)/3 -> 51314.58
A73: =_xlfn.XLOOKUP('[1]CMK - 30.09.2025'!$N$1:$N$1048576,'[1]CMK - 30.09.2025'!$J$1:$J$1048576,"-",0) -> #NAME? | B73: INDIVIDUAL | C73: INDIVIDUAL | D73: INDEPENDENTES | E73: 2250283000155 | F73: 02250283000155 - DROGARIA RABELO E MARCAL LTDA | H73: MG | I73: 8528.717 | J73: 8528.717 | K73: 5569.48 | L73: -2959.237 | M73: -0.34697329 | N73: - | O73: 8178.425 | P73: 8178.425 | Q73: 6500.05 | R73: -1678.375 | S73: -0.20521983 | T73: 0.16708382 | U73: 5430.962 | V73: 5430.962 | W73: 10136.69 | X73: 4705.728 | Y73: 0.86646307 | Z73: 0.55947877 | AA73: =SUM(K73,Q73,W73)/3 -> 7402.0733
A74: =_xlfn.XLOOKUP('[1]CMK - 30.09.2025'!$N$1:$N$1048576,'[1]CMK - 30.09.2025'!$J$1:$J$1048576,"-",0) -> #NAME? | B74: INDIVIDUAL | C74: INDIVIDUAL | D74: INDEPENDENTES | E74: 2251802000108 | F74: 02251802000108 - MERCHID MORAIS LTDA | H74: MG | I74: 2637.609 | J74: 2637.609 | K74: 1188.53 | L74: -1449.079 | M74: -0.54939113 | N74: - | O74: 1061.7 | P74: 1061.7 | Q74: 936.47 | R74: -125.23 | S74: -0.11795234 | T74: -0.2120771 | U74: 1943.875 | V74: 1943.875 | W74: 2387.9 | X74: 444.025 | Y74: 0.22842261 | Z74: 1.5498948 | AA74: =SUM(K74,Q74,W74)/3 -> 1504.3
A75: =_xlfn.XLOOKUP('[1]CMK - 30.09.2025'!$N$1:$N$1048576,'[1]CMK - 30.09.2025'!$J$1:$J$1048576,"-",0) -> #NAME? | B75: INDIVIDUAL | C75: INDIVIDUAL | D75: INDEPENDENTES | E75: 2262894000113 | F75: 02262894000113 - DROGA NAVES LTDA | H75: MG | I75: 163.972 | J75: 163.972 | K75: 619.94 | L75: 455.968 | M75: 2.7807674 | N75: - | O75: 159.145 | P75: 159.145 | Q75: 392.26 | R75: 233.115 | S75: 1.4647963 | T75: -0.36726135 | U75: 233.436 | V75: 233.436 | W75: 1339.94 | X75: 1106.504 | Y75: 4.7400744 | Z75: 2.4159486 | AA75: =SUM(K75,Q75,W75)/3 -> 784.04667
A76: =_xlfn.XLOOKUP('[1]CMK - 30.09.2025'!$N$1:$N$1048576,'[1]CMK - 30.09.2025'!$J$1:$J$1048576,"-",0) -> #NAME? | B76: INDIVIDUAL | C76: INDIVIDUAL | D76: INDEPENDENTES | E76: 2297735000154 | F76: 02297735000154 - JOEL LUIS VELASCO ME | H76: MG | I76: 476.104 | J76: 476.104 | K76: 0 | L76: -476.104 | M76: -1 | N76: - | O76: 832.419 | P76: 832.419 | Q76: 0 | R76: -832.419 | S76: -1 | T76: - | U76: 1764.612 | V76: 1764.612 | W76: 90.03 | X76: -1674.582 | Y76: -0.94898029 | Z76: - | AA76: =SUM(K76,Q76,W76)/3 -> 30.01
A77: =_xlfn.XLOOKUP('[1]CMK - 30.09.2025'!$N$1:$N$1048576,'[1]CMK - 30.09.2025'!$J$1:$J$1048576,"-",0) -> #NAME? | B77: INDIVIDUAL | C77: INDIVIDUAL | D77: INDEPENDENTES | E77: 2297735000235 | F77: 02297735000235 - JOEL LUIS VELASCO | H77: MG | I77: 1535.38 | J77: 1535.38 | K77: 1045.9 | L77: -489.48 | M77: -0.31880056 | N77: - | O77: 1799.665 | P77: 1799.665 | Q77: 2286.31 | R77: 486.645 | S77: 0.27040866 | T77: 1.1859738 | U77: 1331.587 | V77: 1331.587 | W77: 2684.38 | X77: 1352.793 | Y77: 1.0159254 | Z77: 0.17411025 | AA77: =SUM(K77,Q77,W77)/3 -> 2005.53
A78: =_xlfn.XLOOKUP('[1]CMK - 30.09.2025'!$N$1:$N$1048576,'[1]CMK - 30.09.2025'!$J$1:$J$1048576,"-",0) -> #NAME? | B78: INDIVIDUAL | C78: INDIVIDUAL | D78: INDEPENDENTES | E78: 2305091000107 | F78: 02305091000107 - MEIRE BETANIA C P PINTO ME | H78: MG | I78: 6522.486 | J78: 6522.486 | K78: 8462.82 | L78: 1940.334 | M78: 0.29748381 | N78: - | O78: 6179.055 | P78: 6179.055 | Q78: 18887.61 | R78: 12708.555 | S78: 2.056715 | T78: 1.2318341 | U78: 8467.703 | V78: 8467.703 | W78: 8829.8 | X78: 362.097 | Y78: 0.042762128 | Z78: -0.53250835 | AA78: =SUM(K78,Q78,W78)/3 -> 12060.077
A79: =_xlfn.XLOOKUP('[1]CMK - 30.09.2025'!$N$1:$N$1048576,'[1]CMK - 30.09.2025'!$J$1:$J$1048576,"-",0) -> #NAME? | B79: INDIVIDUAL | C79: INDIVIDUAL | D79: INDEPENDENTES | E79: 2305091000280 | F79: 02305091000280 - DROGARIA CELESTINO LTDA | H79: MG | I79: 0 | J79: 0 | K79: 5699.24 | L79: 5699.24 | M79: - | N79: - | O79: 0 | P79: 0 | Q79: 3778.77 | R79: 3778.77 | S79: - | T79: -0.33696949 | U79: 0 | V79: 0 | W79: 8128.28 | X79: 8128.28 | Y79: - | Z79: 1.1510386 | AA79: =SUM(K79,Q79,W79)/3 -> 5868.7633
A80: =_xlfn.XLOOKUP('[1]CMK - 30.09.2025'!$N$1:$N$1048576,'[1]CMK - 30.09.2025'!$J$1:$J$1048576,"-",0) -> #NAME? | B80: INDIVIDUAL | C80: INDIVIDUAL | D80: INDEPENDENTES | E80: 2316243000169 | F80: 02316243000169 - JAKSON LOPES MAIA | H80: MG | I80: 4459.089 | J80: 4459.089 | K80: 6992.32 | L80: 2533.231 | M80: 0.56810505 | N80: - | O80: 3431.369 | P80: 3431.369 | Q80: 7058.2 | R80: 3626.831 | S80: 1.0569633 | T80: 0.0094217656 | U80: 4679.325 | V80: 4679.325 | W80: 8773.9 | X80: 4094.575 | Y80: 0.8750354 | Z80: 0.24307897 | AA80: =SUM(K80,Q80,W80)/3 -> 7608.14
A81: =_xlfn.XLOOKUP('[1]CMK - 30.09.2025'!$N$1:$N$1048576,'[1]CMK - 30.09.2025'!$J$1:$J$1048576,"-",0) -> #NAME? | B81: INDIVIDUAL | C81: INDIVIDUAL | D81: INDEPENDENTES | E81: 2336828000140 | F81: 02336828000140 - DROGARIA LM LTDA | H81: MG | I81: 2139.215 | J81: 2139.215 | K81: 2693.37 | L81: 554.155 | M81: 0.25904596 | N81: - | O81: 2457.585 | P81: 2457.585 | Q81: 1325.23 | R81: -1132.355 | S81: -0.46075924 | T81: -0.50796586 | U81: 2862.282 | V81: 2862.282 | W81: 2814.15 | X81: -48.132 | Y81: -0.016815953 | Z81: 1.1235182 | AA81: =SUM(K81,Q81,W81)/3 -> 2277.5833
A82: =_xlfn.XLOOKUP('[1]CMK - 30.09.2025'!$N$1:$N$1048576,'[1]CMK - 30.09.2025'!$J$1:$J$1048576,"-",0) -> #NAME? | B82: INDIVIDUAL | C82: INDIVIDUAL | D82: INDEPENDENTES | E82: 2346582000198 | F82: 02346582000198 - DROG E CIRURGICA STA RITA DE SALINA | H82: MG | I82: 3725.768 | J82: 3725.768 | K82: 648.02 | L82: -3077.748 | M82: -0.82607076 | N82: - | O82: 701.113 | P82: 701.113 | Q82: 6178.01 | R82: 5476.897 | S82: 7.8117179 | T82: 8.5336718 | U82: 1069.697 | V82: 1069.697 | W82: 5986.65 | X82: 4916.953 | Y82: 4.5965848 | Z82: -0.030974375 | AA82: =SUM(K82,Q82,W82)/3 -> 4270.8933
A83: =_xlfn.XLOOKUP('[1]CMK - 30.09.2025'!$N$1:$N$1048576,'[1]CMK - 30.09.2025'!$J$1:$J$1048576,"-",0) -> #NAME? | B83: INDIVIDUAL | C83: INDIVIDUAL | D83: INDEPENDENTES | E83: 2349790000140 | F83: 02349790000140 - CLEUZA DOMINGUES ALVES E CIA | H83: MG | I83: 0 | J83: 0 | K83: 1542.53 | L83: 1542.53 | M83: - | N83: - | O83: 0 | P83: 0 | Q83: 0 | R83: 0 | S83: - | T83: -1 | U83: 0 | V83: 0 | W83: 728.82 | X83: 728.82 | Y83: - | Z83: - | AA83: =SUM(K83,Q83,W83)/3 -> 757.11667
A84: =_xlfn.XLOOKUP('[1]CMK - 30.09.2025'!$N$1:$N$1048576,'[1]CMK - 30.09.2025'!$J$1:$J$1048576,"-",0) -> #NAME? | B84: INDIVIDUAL | C84: INDIVIDUAL | D84: INDEPENDENTES | E84: 2351726000102 | F84: 02351726000102 - COSMETICA PERFUMARIA LTDA | H84: MG | I84: 2390.857 | J84: 2390.857 | K84: 1493.76 | L84: -897.097 | M84: -0.37521985 | N84: - | O84: 2864.753 | P84: 2864.753 | Q84: 4968.86 | R84: 2104.107 | S84: 0.73448112 | T84: 2.3264112 | U84: 3173.047 | V84: 3173.047 | W84: 0 | X84: -3173.047 | Y84: -1 | Z84: -1 | AA84: =SUM(K84,Q84,W84)/3 -> 2154.2067
A85: =_xlfn.XLOOKUP('[1]CMK - 30.09.2025'!$N$1:$N$1048576,'[1]CMK - 30.09.2025'!$J$1:$J$1048576,"-",0) -> #NAME? | B85: INDIVIDUAL | C85: INDIVIDUAL | D85: INDEPENDENTES | E85: 2351726000366 | F85: 02351726000366 - COSMETICA PERFUMARIA LTDA | H85: MG | I85: 1557.989 | J85: 1557.989 | K85: 0 | L85: -1557.989 | M85: -1 | N85: - | O85: 1866.8 | P85: 1866.8 | Q85: 2695.66 | R85: 828.86 | S85: 0.44400043 | T85: - | U85: 2067.699 | V85: 2067.699 | W85: 0 | X85: -2067.699 | Y85: -1 | Z85: -1 | AA85: =SUM(K85,Q85,W85)/3 -> 898.55333
A86: =_xlfn.XLOOKUP('[1]CMK - 30.09.2025'!$N$1:$N$1048576,'[1]CMK - 30.09.2025'!$J$1:$J$1048576,"-",0) -> #NAME? | B86: INDIVIDUAL | C86: INDIVIDUAL | D86: INDEPENDENTES | E86: 2351726000447 | F86: 02351726000447 - COSM PERF LT | H86: MG | I86: 622.251 | J86: 622.251 | K86: 0 | L86: -622.251 | M86: -1 | N86: - | O86: 745.588 | P86: 745.588 | Q86: 1151.68 | R86: 406.092 | S86: 0.54466005 | T86: - | U86: 825.825 | V86: 825.825 | W86: 0 | X86: -825.825 | Y86: -1 | Z86: -1 | AA86: =SUM(K86,Q86,W86)/3 -> 383.89333
A87: =_xlfn.XLOOKUP('[1]CMK - 30.09.2025'!$N$1:$N$1048576,'[1]CMK - 30.09.2025'!$J$1:$J$1048576,"-",0) -> #NAME? | B87: INDIVIDUAL | C87: INDIVIDUAL | D87: INDEPENDENTES | E87: 2374995000186 | F87: 02374995000186 - FABIO ALEXANDRE BARBOSA | H87: MG | I87: 10754.173 | J87: 10754.173 | K87: 7373.03 | L87: -3381.143 | M87: -0.31440288 | N87: - | O87: 20418.393 | P87: 20418.393 | Q87: 7012.3 | R87: -13406.093 | S87: -0.65656945 | T87: -0.048925611 | U87: 5702.744 | V87: 5702.744 | W87: 8925.16 | X87: 3222.416 | Y87: 0.56506412 | Z87: 0.27278639 | AA87: =SUM(K87,Q87,W87)/3 -> 7770.1633
A88: =_xlfn.XLOOKUP('[1]CMK - 30.09.2025'!$N$1:$N$1048576,'[1]CMK - 30.09.2025'!$J$1:$J$1048576,"-",0) -> #NAME? | B88: INDIVIDUAL | C88: INDIVIDUAL | D88: INDEPENDENTES | E88: 2441215000173 | F88: 02441215000173 - DROG RAMOS & CARVALHO LT EPP | H88: MG | I88: 19292.715 | J88: 19292.715 | K88: 16647.48 | L88: -2645.235 | M88: -0.13711056 | N88: - | O88: 13270.777 | P88: 13270.777 | Q88: 15703.69 | R88: 2432.913 | S88: 0.1833286 | T88: -0.056692665 | U88: 20007.906 | V88: 20007.906 | W88: 15510.75 | X88: -4497.156 | Y88: -0.22476895 | Z88: -0.012286284 | AA88: =SUM(K88,Q88,W88)/3 -> 15953.973
A89: =_xlfn.XLOOKUP('[1]CMK - 30.09.2025'!$N$1:$N$1048576,'[1]CMK - 30.09.2025'!$J$1:$J$1048576,"-",0) -> #NAME? | B89: INDIVIDUAL | C89: INDIVIDUAL | D89: INDEPENDENTES | E89: 2489195000100 | F89: 02489195000100 - DROGARIA GONCALVES E BARBOSA LT | H89: MG | I89: 4085.56 | J89: 4085.56 | K89: 3580.93 | L89: -504.63 | M89: -0.1235155 | N89: - | O89: 3006.031 | P89: 3006.031 | Q89: 4070.99 | R89: 1064.959 | S89: 0.35427412 | T89: 0.13685272 | U89: 4353.638 | V89: 4353.638 | W89: 3133.52 | X89: -1220.118 | Y89: -0.28025252 | Z89: -0.2302806 | AA89: =SUM(K89,Q89,W89)/3 -> 3595.1467
A90: =_xlfn.XLOOKUP('[1]CMK - 30.09.2025'!$N$1:$N$1048576,'[1]CMK - 30.09.2025'!$J$1:$J$1048576,"-",0) -> #NAME? | B90: INDIVIDUAL | C90: INDIVIDUAL | D90: INDEPENDENTES | E90: 2491217000177 | F90: 02491217000177 - DROGARIA MATOLA LTDA | H90: MG | I90: 2624.278 | J90: 2624.278 | K90: 2638.81 | L90: 14.532 | M90: 0.0055375231 | N90: - | O90: 2244.996 | P90: 2244.996 | Q90: 2304.56 | R90: 59.564 | S90: 0.026531896 | T90: -0.12666694 | U90: 2966.249 | V90: 2966.249 | W90: 2934.33 | X90: -31.919 | Y90: -0.010760728 | Z90: 0.27327125 | AA90: =SUM(K90,Q90,W90)/3 -> 2625.9
A91: =_xlfn.XLOOKUP('[1]CMK - 30.09.2025'!$N$1:$N$1048576,'[1]CMK - 30.09.2025'!$J$1:$J$1048576,"-",0) -> #NAME? | B91: INDIVIDUAL | C91: INDIVIDUAL | D91: INDEPENDENTES | E91: 2509530000195 | F91: 02509530000195 - DROG ELDORADO MONTES CLAROS LT | H91: MG | I91: 10350.581 | J91: 10350.581 | K91: 3393.4 | L91: -6957.181 | M91: -0.67215367 | N91: - | O91: 2567.761 | P91: 2567.761 | Q91: 4401.24 | R91: 1833.479 | S91: 0.71403803 | T91: 0.29700006 | U91: 860.646 | V91: 860.646 | W91: 6253.31 | X91: 5392.664 | Y91: 6.2658329 | Z91: 0.42080641 | AA91: =SUM(K91,Q91,W91)/3 -> 4682.65
A92: =_xlfn.XLOOKUP('[1]CMK - 30.09.2025'!$N$1:$N$1048576,'[1]CMK - 30.09.2025'!$J$1:$J$1048576,"-",0) -> #NAME? | B92: INDIVIDUAL | C92: INDIVIDUAL | D92: INDEPENDENTES | E92: 2524024000175 | F92: 02524024000175 - DROGARIA FALCONIERE LTDA ME | H92: MG | I92: 595.52 | J92: 595.52 | K92: 0 | L92: -595.52 | M92: -1 | N92: - | O92: 523.711 | P92: 523.711 | Q92: 562.86 | R92: 39.149 | S92: 0.07475306 | T92: - | U92: 795.538 | V92: 795.538 | W92: 1651.12 | X92: 855.582 | Y92: 1.075476 | Z92: 1.933447 | AA92: =SUM(K92,Q92,W92)/3 -> 737.99333
A93: =_xlfn.XLOOKUP('[1]CMK - 30.09.2025'!$N$1:$N$1048576,'[1]CMK - 30.09.2025'!$J$1:$J$1048576,"-",0) -> #NAME? | B93: INDIVIDUAL | C93: INDIVIDUAL | D93: INDEPENDENTES | E93: 2579089000118 | F93: 02579089000118 - DROG E PERF LISBOA LT | H93: MG | I93: 13909.711 | J93: 13909.711 | K93: 0 | L93: -13909.711 | M93: -1 | N93: - | O93: 7053.808 | P93: 7053.808 | Q93: 0 | R93: -7053.808 | S93: -1 | T93: - | U93: 14305.417 | V93: 14305.417 | W93: 19242.41 | X93: 4936.993 | Y93: 0.34511353 | Z93: - | AA93: =SUM(K93,Q93,W93)/3 -> 6414.1367
A94: =_xlfn.XLOOKUP('[1]CMK - 30.09.2025'!$N$1:$N$1048576,'[1]CMK - 30.09.2025'!$J$1:$J$1048576,"-",0) -> #NAME? | B94: INDIVIDUAL | C94: INDIVIDUAL | D94: INDEPENDENTES | E94: 2598350000127 | F94: 02598350000127 - DROGARIA ARAUJO E ANA LTDA | H94: MG | I94: 299.75 | J94: 299.75 | K94: 303.31 | L94: 3.56 | M94: 0.011876564 | N94: - | O94: 116.129 | P94: 116.129 | Q94: 183.75 | R94: 67.621 | S94: 0.58229211 | T94: -0.39418417 | U94: 0 | V94: 0 | W94: 0 | X94: 0 | Y94: - | Z94: -1 | AA94: =SUM(K94,Q94,W94)/3 -> 162.35333
A95: =_xlfn.XLOOKUP('[1]CMK - 30.09.2025'!$N$1:$N$1048576,'[1]CMK - 30.09.2025'!$J$1:$J$1048576,"-",0) -> #NAME? | B95: INDIVIDUAL | C95: INDIVIDUAL | D95: INDEPENDENTES | E95: 2598760000178 | F95: 02598760000178 - DOSE EFETIVA MED PERF E MANIP | H95: MG | I95: 7891.325 | J95: 7891.325 | K95: 9061.3 | L95: 1169.975 | M95: 0.14826091 | N95: - | O95: 6269.547 | P95: 6269.547 | Q95: 7977.68 | R95: 1708.133 | S95: 0.27244919 | T95: -0.1195877 | U95: 10129.419 | V95: 10129.419 | W95: 11081.06 | X95: 951.641 | Y95: 0.093948231 | Z95: 0.38900783 | AA95: =SUM(K95,Q95,W95)/3 -> 9373.3467
A96: =_xlfn.XLOOKUP('[1]CMK - 30.09.2025'!$N$1:$N$1048576,'[1]CMK - 30.09.2025'!$J$1:$J$1048576,"-",0) -> #NAME? | B96: INDIVIDUAL | C96: INDIVIDUAL | D96: INDEPENDENTES | E96: 2712638000180 | F96: 02712638000180 - GONCALVES E GONCALVES MED PERF | H96: MG | I96: 1451.956 | J96: 1451.956 | K96: 2493.89 | L96: 1041.934 | M96: 0.71760715 | N96: - | O96: 836.888 | P96: 836.888 | Q96: 0 | R96: -836.888 | S96: -1 | T96: -1 | U96: 191.108 | V96: 191.108 | W96: 602.31 | X96: 411.202 | Y96: 2.1516734 | Z96: - | AA96: =SUM(K96,Q96,W96)/3 -> 1032.0667
A97: =_xlfn.XLOOKUP('[1]CMK - 30.09.2025'!$N$1:$N$1048576,'[1]CMK - 30.09.2025'!$J$1:$J$1048576,"-",0) -> #NAME? | B97: INDIVIDUAL | C97: INDIVIDUAL | D97: INDEPENDENTES | E97: 2717804000131 | F97: 02717804000131 - DROGARIA BORGES LTDA | H97: MG | I97: 12293.256 | J97: 12293.256 | K97: 13094.85 | L97: 801.594 | M97: 0.065205996 | N97: - | O97: 9093.089 | P97: 9093.089 | Q97: 11039.78 | R97: 1946.691 | S97: 0.21408467 | T97: -0.15693727 | U97: 11302.349 | V97: 11302.349 | W97: 17397.53 | X97: 6095.181 | Y97: 0.53928444 | Z97: 0.57589463 | AA97: =SUM(K97,Q97,W97)/3 -> 13844.053
A98: =_xlfn.XLOOKUP('[1]CMK - 30.09.2025'!$N$1:$N$1048576,'[1]CMK - 30.09.2025'!$J$1:$J$1048576,"-",0) -> #NAME? | B98: INDIVIDUAL | C98: INDIVIDUAL | D98: INDEPENDENTES | E98: 2727175000120 | F98: 02727175000120 - GONCALVES & LINHARES LTDA | H98: MG | I98: 0 | J98: 0 | K98: 602.76 | L98: 602.76 | M98: - | N98: - | O98: 0 | P98: 0 | Q98: 205.44 | R98: 205.44 | S98: - | T98: -0.65916783 | U98: 0 | V98: 0 | W98: 687.6 | X98: 687.6 | Y98: - | Z98: 2.3469626 | AA98: =SUM(K98,Q98,W98)/3 -> 498.6
A99: =_xlfn.XLOOKUP('[1]CMK - 30.09.2025'!$N$1:$N$1048576,'[1]CMK - 30.09.2025'!$J$1:$J$1048576,"-",0) -> #NAME? | B99: INDIVIDUAL | C99: INDIVIDUAL | D99: INDEPENDENTES | E99: 2763557000100 | F99: 02763557000100 - FCIA ESSENCIA EIRELI ME | H99: MG | I99: 1484.396 | J99: 1484.396 | K99: 1054.75 | L99: -429.646 | M99: -0.28944163 | N99: - | O99: 1838.72 | P99: 1838.72 | Q99: 817.66 | R99: -1021.06 | S99: -0.55531022 | T99: -0.22478312 | U99: 2652.62 | V99: 2652.62 | W99: 2109.6 | X99: -543.02 | Y99: -0.20471081 | Z99: 1.5800455 | AA99: =SUM(K99,Q99,W99)/3 -> 1327.3367
A100: =_xlfn.XLOOKUP('[1]CMK - 30.09.2025'!$N$1:$N$1048576,'[1]CMK - 30.09.2025'!$J$1:$J$1048576,"-",0) -> #NAME? | B100: INDIVIDUAL | C100: INDIVIDUAL | D100: INDEPENDENTES | E100: 2778141000165 | F100: 02778141000165 - BRAULIO MAGELA ALVES BARBOSA E | H100: MG | I100: 13853.328 | J100: 13853.328 | K100: 8412.53 | L100: -5440.798 | M100: -0.39274303 | N100: - | O100: 17420.034 | P100: 17420.034 | Q100: 7677.69 | R100: -9742.344 | S100: -0.55926091 | T100: -0.087350654 | U100: 15033.859 | V100: 15033.859 | W100: 6566.58 | X100: -8467.279 | Y100: -0.56321394 | Z100: -0.14471931 | AA100: =SUM(K100,Q100,W100)/3 -> 7552.2667
A101: =_xlfn.XLOOKUP('[1]CMK - 30.09.2025'!$N$1:$N$1048576,'[1]CMK - 30.09.2025'!$J$1:$J$1048576,"-",0) -> #NAME? | B101: INDIVIDUAL | C101: INDIVIDUAL | D101: INDEPENDENTES | E101: 2863465000100 | F101: 02863465000100 - FARMACIA SANTANA LIMITADA | H101: MG | I101: 3464.476 | J101: 3464.476 | K101: 7103.09 | L101: 3638.614 | M101: 1.0502639 | N101: - | O101: 2706.359 | P101: 2706.359 | Q101: 1683.37 | R101: -1022.989 | S101: -0.37799457 | T101: -0.76300878 | U101: 4290.601 | V101: 4290.601 | W101: 1801.77 | X101: -2488.831 | Y101: -0.58006582 | Z101: 0.070335102 | AA101: =SUM(K101,Q101,W101)/3 -> 3529.41
...

Sheet Base 1
A1: CODIGO | B1: CNPJ | C1: COD SAP CLIENTE | D1: SET | E1: RAZÃO SOCIAL | F1: COD. BAND. | G1: BANDEIRA | H1: COND PZ | I1: DIAS PZ | J1: COND AV | K1: DIAS AV | L1: MATRIZ | M1: STATUS | N1: NOME GV | O1: NOME SUP | P1: MEDIA TRI | Q1: COD REDE | R1: REDE | S1: FILIAL | T1: ORG VENDAS | U1: CNPJ | V1: Grp.preço | W1: Den.Grp.Preços
A2: B00006 | B2: 42849414000130 | C2: 101414 | D2: 207 | E2: DROGARIA NESTORAO LTDA | F2: 10437 | G2: INDIVIDUAL | H2: 35993 | I2: 30 | J2: 35993 | K2: 7 | L2: B00006 | M2: ATIVO | N2: GABRIEL GONCALVES FONSECA | O2: ALEX DE SOUSA PEREIRA | P2: =_xlfn.XLOOKUP('MEDIA TRI'!$E:$E,'MEDIA TRI'!$AA:$AA,"-",0) -> #NAME? | Q2: =_xlfn.XLOOKUP($U:$U,$V:$V,0,0) -> #NAME? | R2: =_xlfn.XLOOKUP($U:$U,$W:$W,0,0) -> #NAME? | S2: MG | T2: MG | U2: 57214900000230 | V2: O4 | W2: DROGARIA TOTAL
A3: B00014 | B3: 21217971000168 | C3: 134634 | D3: 1791 | E3: DROGARIA AMARANTE LTDA | F3: 10437 | G3: INDIVIDUAL | H3: 35186 | I3: 28 | J3: 35186 | K3: 7 | L3: B00014 | M3: ATIVO | N3: GABRIEL GONCALVES FONSECA | O3: ANDRE DIAS DE OLIVEIRA | P3: =_xlfn.XLOOKUP('MEDIA TRI'!$E:$E,'MEDIA TRI'!$AA:$AA,"-",0) -> #NAME? | Q3: =_xlfn.XLOOKUP($U:$U,$V:$V,0,0) -> #NAME? | R3: =_xlfn.XLOOKUP($U:$U,$W:$W,0,0) -> #NAME? | S3: MG | T3: MG | U3: 57214900000230 | V3: O4 | W3: DROGARIA TOTAL
A4: B00016 | B4: 9440889000100 | C4: 125405 | D4: 542 | E4: DROGARIA BORBOLETA LTDA | F4: 14516 | G4: ABRAFAD REDE SOMA | H4: 35195 | I4: 27 | J4: 35195 | K4: 7 | L4: B00016 | M4: ATIVO | N4: JULIANO DE MOURA HIDAKA | O4: VAGO - ZONA DA MATA - MG | P4: =_xlfn.XLOOKUP('MEDIA TRI'!$E:$E,'MEDIA TRI'!$AA:$AA,"-",0) -> #NAME? | Q4: =_xlfn.XLOOKUP($U:$U,$V:$V,0,0) -> #NAME? | R4: =_xlfn.XLOOKUP($U:$U,$W:$W,0,0) -> #NAME? | S4: MG | T4: MGI | U4: 87497368000195 | V4: 1P | W4: MIX FARMA
A5: B00018 | B5: 9519515000177 | C5: 105857 | D5: 1146 | E5: DROGARIA E FARMACIA LOGOS LTDA | F5: 10437 | G5: INDIVIDUAL | H5: 36001 | I5: 28 | J5: 36001 | K5: 7 | L5: B00018 | M5: ATIVO | N5: GABRIEL GONCALVES FONSECA | O5: INATIVO - MG3 | P5: =_xlfn.XLOOKUP('MEDIA TRI'!$E:$E,'MEDIA TRI'!$AA:$AA,"-",0) -> #NAME? | Q5: =_xlfn.XLOOKUP($U:$U,$V:$V,0,0) -> #NAME? | R5: =_xlfn.XLOOKUP($U:$U,$W:$W,0,0) -> #NAME? | S5: MG | T5: MG | U5: 87497368000195 | V5: 1P | W5: MIX FARMA
A6: B00021 | B6: 71159388000469 | C6: 116212 | D6: 1440 | E6: NOSSAS ERVAS PROD NATURIAS LTD | F6: 95 | G6: REDEFARMA | H6: 35999 | I6: 28 | J6: 35999 | K6: 7 | L6: B07670 | M6: ATIVO | N6: JULIANO DE MOURA HIDAKA | O6: LUIS CARLOS SILVEIRA | P6: =_xlfn.XLOOKUP('MEDIA TRI'!$E:$E,'MEDIA TRI'!$AA:$AA,"-",0) -> #NAME? | Q6: =_xlfn.XLOOKUP($U:$U,$V:$V,0,0) -> #NAME? | R6: =_xlfn.XLOOKUP($U:$U,$W:$W,0,0) -> #NAME? | S6: MG | T6: MG | U6: 82602327000360 | V6: 1P | W6: MIX FARMA
A7: B00022 | B7: 17601675000199 | C7: 130363 | D7: 529 | E7: DROGARIA LPP LTDA EPP | F7: 14608 | G7: HIPER SAUDE | H7: 34925 | I7: 42 | J7: 34925 | K7: 7 | L7: B00022 | M7: ATIVO | N7: JULIANO DE MOURA HIDAKA | O7: VAGNER LUIZ BUENO CAMBRAIA | P7: =_xlfn.XLOOKUP('MEDIA TRI'!$E:$E,'MEDIA TRI'!$AA:$AA,"-",0) -> #NAME? | Q7: =_xlfn.XLOOKUP($U:$U,$V:$V,0,0) -> #NAME? | R7: =_xlfn.XLOOKUP($U:$U,$W:$W,0,0) -> #NAME? | S7: MG | T7: MGI | U7: 82602327000360 | V7: 1P | W7: MIX FARMA
A8: B00023 | B8: 9408863000177 | C8: 147363 | D8: 1146 | E8: PLENA DROG E COM LT | F8: 14329 | G8: ABRAFAD MELHORCOMPRA | H8: 30015 | I8: 21 | J8: 30015 | K8: 7 | L8: B00023 | M8: ATIVO | N8: GABRIEL GONCALVES FONSECA | O8: INATIVO - MG3 | P8: =_xlfn.XLOOKUP('MEDIA TRI'!$E:$E,'MEDIA TRI'!$AA:$AA,"-",0) -> #NAME? | Q8: =_xlfn.XLOOKUP($U:$U,$V:$V,0,0) -> #NAME? | R8: =_xlfn.XLOOKUP($U:$U,$W:$W,0,0) -> #NAME? | S8: MG | T8: MG | U8: 1647867000287 | V8: 5H | W8: UNIMED MG
A9: B00024 | B9: 9398614000148 | C9: 131002 | D9: 363 | E9: DROGARIA ALVARENGA E FERREIRA | F9: 10437 | G9: INDIVIDUAL | H9: 34924 | I9: 26 | J9: 34924 | K9: 7 | L9: B00024 | M9: ATIVO | N9: JULIANO DE MOURA HIDAKA | O9: LUIS CARLOS SILVEIRA | P9: =_xlfn.XLOOKUP('MEDIA TRI'!$E:$E,'MEDIA TRI'!$AA:$AA,"-",0) -> #NAME? | Q9: =_xlfn.XLOOKUP($U:$U,$V:$V,0,0) -> #NAME? | R9: =_xlfn.XLOOKUP($U:$U,$W:$W,0,0) -> #NAME? | S9: MG | T9: MG | U9: 1647867000287 | V9: 5H | W9: UNIMED MG
A10: B00025 | B10: 9409548000164 | C10: 105173 | D10: 2255 | E10: DROGARIA TUTA S LTDA | F10: 10437 | G10: INDIVIDUAL | H10: 35999 | I10: 7 | J10: 35999 | K10: 7 | L10: B00025 | M10: ATIVO | N10: GABRIEL GONCALVES FONSECA | O10: CIRO DE CARVALHO MIRANDA | P10: =_xlfn.XLOOKUP('MEDIA TRI'!$E:$E,'MEDIA TRI'!$AA:$AA,"-",0) -> #NAME? | Q10: =_xlfn.XLOOKUP($U:$U,$V:$V,0,0) -> #NAME? | R10: =_xlfn.XLOOKUP($U:$U,$W:$W,0,0) -> #NAME? | S10: MG | T10: MG | U10: 45359213000223 | V10: HW | W10: REDE UNIMED SAO CARL
A11: B00026 | B11: 21705181000121 | C11: 106994 | D11: 512 | E11: DROGARIA MATOS LTDA | F11: 14261 | G11: FARMELHOR | H11: 35993 | I11: 28 | J11: 35993 | K11: 7 | L11: B00026 | M11: ATIVO | N11: JULIANO DE MOURA HIDAKA | O11: DOUGLAS ALCANTARA PEREIRA | P11: =_xlfn.XLOOKUP('MEDIA TRI'!$E:$E,'MEDIA TRI'!$AA:$AA,"-",0) -> #NAME? | Q11: =_xlfn.XLOOKUP($U:$U,$V:$V,0,0) -> #NAME? | R11: =_xlfn.XLOOKUP($U:$U,$W:$W,0,0) -> #NAME? | S11: MG | T11: MGI | U11: 45359213000223 | V11: HW | W11: REDE UNIMED SAO CARL
A12: B00027 | B12: 23954233000200 | C12: 138036 | D12: 3412 | E12: DROGA MELLO LTDA | F12: 10437 | G12: INDIVIDUAL | H12: 30015 | I12: 21 | J12: 30015 | K12: 7 | L12: B26225 | M12: ATIVO | N12: JULIANO DE MOURA HIDAKA | O12: INATIVO - MG4 | P12: =_xlfn.XLOOKUP('MEDIA TRI'!$E:$E,'MEDIA TRI'!$AA:$AA,"-",0) -> #NAME? | Q12: =_xlfn.XLOOKUP($U:$U,$V:$V,0,0) -> #NAME? | R12: =_xlfn.XLOOKUP($U:$U,$W:$W,0,0) -> #NAME? | S12: MG | T12: MGI | U12: 69087922000427 | V12: 1P | W12: MIX FARMA
A13: B00028 | B13: 26046821000152 | C13: 110720 | D13: 1792 | E13: CENTRO ESP N SRA D ASSUNCAO LT | F13: 10437 | G13: INDIVIDUAL | H13: 35186 | I13: 27 | J13: 35186 | K13: 7 | L13: B00028 | M13: ATIVO | N13: JULIANO DE MOURA HIDAKA | O13: VAGO - ZONA DA MATA - MG | P13: =_xlfn.XLOOKUP('MEDIA TRI'!$E:$E,'MEDIA TRI'!$AA:$AA,"-",0) -> #NAME? | Q13: =_xlfn.XLOOKUP($U:$U,$V:$V,0,0) -> #NAME? | R13: =_xlfn.XLOOKUP($U:$U,$W:$W,0,0) -> #NAME? | S13: MG | T13: MG | U13: 69087922000427 | V13: 1P | W13: MIX FARMA
... A19: B00055 | B19: 1072371000141 | C19: 117710 | D19: 2069 | E19: COMERCIAL BARRON LTDA | F19: 14157 | G19: LUMAF | H19: 35999 | I19: 21 | J19: 35999 | K19: 7 | L19: B00055 | M19: ATIVO | N19: GABRIEL GONCALVES FONSECA | O19: THIAGO DE CASTRO MARIA | P19: =_xlfn.XLOOKUP('MEDIA TRI'!$E:$E,'MEDIA TRI'!$AA:$AA,"-",0) -> #NAME? | Q19: =_xlfn.XLOOKUP($U:$U,$V:$V,0,0) -> #NAME? | R19: =_xlfn.XLOOKUP($U:$U,$W:$W,0,0) -> #NAME? | S19: MG | T19: MGI | U19: 87300448000109 | V19: 1P | W19: MIX FARMA
A20: B00063 | B20: 71166672000110 | C20: 114104 | D20: 388 | E20: DROG PASSAGEM DE MARIANA LT ME | F20: 10437 | G20: INDIVIDUAL | H20: 34841 | I20: 35 | J20: 34841 | K20: 7 | L20: B00063 | M20: ATIVO | N20: GABRIEL GONCALVES FONSECA | O20: CIRO DE CARVALHO MIRANDA | P20: =_xlfn.XLOOKUP('MEDIA TRI'!$E:$E,'MEDIA TRI'!$AA:$AA,"-",0) -> #NAME? | Q20: =_xlfn.XLOOKUP($U:$U,$V:$V,0,0) -> #NAME? | R20: =_xlfn.XLOOKUP($U:$U,$W:$W,0,0) -> #NAME? | S20: MG | T20: MG | U20: 3980208000102 | V20: 28 | W20: MIX FARMA B
A21: B00071 | B21: 7386243000159 | C21: 114563 | D21: 1791 | E21: DROGARIA BARROS E GOMES LTDA | F21: 14516 | G21: ABRAFAD REDE SOMA | H21: 34925 | I21: 35 | J21: 34925 | K21: 7 | L21: B00071 | M21: ATIVO | N21: GABRIEL GONCALVES FONSECA | O21: ANDRE DIAS DE OLIVEIRA | P21: =_xlfn.XLOOKUP('MEDIA TRI'!$E:$E,'MEDIA TRI'!$AA:$AA,"-",0) -> #NAME? | Q21: =_xlfn.XLOOKUP($U:$U,$V:$V,0,0) -> #NAME? | R21: =_xlfn.XLOOKUP($U:$U,$W:$W,0,0) -> #NAME? | S21: MG | T21: MG | U21: 3980208000102 | V21: 28 | W21: MIX FARMA B
A22: B00121 | B22: 66342650000123 | C22: 127643 | D22: 302 | E22: DROGARIA KARISHA LTDA ME | F22: 10437 | G22: INDIVIDUAL | H22: 35998 | I22: 35 | J22: 35998 | K22: 7 | L22: B00121 | M22: ATIVO | N22: GABRIEL GONCALVES FONSECA | O22: GUSTAVO GONCALVES | P22: =_xlfn.XLOOKUP('MEDIA TRI'!$E:$E,'MEDIA TRI'!$AA:$AA,"-",0) -> #NAME? | Q22: =_xlfn.XLOOKUP($U:$U,$V:$V,0,0) -> #NAME? | R22: =_xlfn.XLOOKUP($U:$U,$W:$W,0,0) -> #NAME? | S22: MG | T22: MG | U22: 25471574001060 | V22: XZ | W22: MINAS MASTER
A23: B00162 | B23: 66194234000125 | C23: 128316 | D23: 1791 | E23: DROGARIA E DRUGSTORE FERNANDO | F23: 10437 | G23: INDIVIDUAL | H23: 34808 | I23: 19 | J23: 34808 | K23: 7 | L23: B00162 | M23: ATIVO | N23: GABRIEL GONCALVES FONSECA | O23: ANDRE DIAS DE OLIVEIRA | P23: =_xlfn.XLOOKUP('MEDIA TRI'!$E:$E,'MEDIA TRI'!$AA:$AA,"-",0) -> #NAME? | Q23: =_xlfn.XLOOKUP($U:$U,$V:$V,0,0) -> #NAME? | R23: =_xlfn.XLOOKUP($U:$U,$W:$W,0,0) -> #NAME? | S23: MG | T23: MG | U23: 25471574001060 | V23: XZ | W23: MINAS MASTER
A24: B00188 | B24: 1119450000160 | C24: 124189 | D24: 1146 | E24: EFEITTO FCIA E MANIP LT | F24: 10437 | G24: INDIVIDUAL | H24: 30015 | I24: 20 | J24: 30015 | K24: 7 | L24: B00188 | M24: ATIVO | N24: GABRIEL GONCALVES FONSECA | O24: INATIVO - MG3 | P24: =_xlfn.XLOOKUP('MEDIA TRI'!$E:$E,'MEDIA TRI'!$AA:$AA,"-",0) -> #NAME? | Q24: =_xlfn.XLOOKUP($U:$U,$V:$V,0,0) -> #NAME? | R24: =_xlfn.XLOOKUP($U:$U,$W:$W,0,0) -> #NAME? | S24: MG | T24: MGI | U24: 54012406000385 | V24: 1P | W24: MIX FARMA
A25: B00279 | B25: 18806430000160 | C25: 106716 | D25: 333 | E25: DROGARIA USIFARMA LTDA EPP | F25: 10437 | G25: INDIVIDUAL | H25: 35992 | I25: 7 | J25: 35992 | K25: 7 | L25: B00279 | M25: ATIVO | N25: GABRIEL GONCALVES FONSECA | O25: GUSTAVO GONCALVES | P25: =_xlfn.XLOOKUP('MEDIA TRI'!$E:$E,'MEDIA TRI'!$AA:$AA,"-",0) -> #NAME? | Q25: =_xlfn.XLOOKUP($U:$U,$V:$V,0,0) -> #NAME? | R25: =_xlfn.XLOOKUP($U:$U,$W:$W,0,0) -> #NAME? | S25: MG | T25: MG | U25: 54012406000385 | V25: 1P | W25: MIX FARMA
A26: B00287 | B26: 25791013000157 | C26: 114183 | D26: 282 | E26: DROG SAO FELIX LTDA EPP | F26: 10437 | G26: INDIVIDUAL | H26: 35997 | I26: 14 | J26: 35997 | K26: 7 | L26: B26951 | M26: ATIVO | N26: GABRIEL GONCALVES FONSECA | O26: GUSTAVO GONCALVES | P26: =_xlfn.XLOOKUP('MEDIA TRI'!$E:$E,'MEDIA TRI'!$AA:$AA,"-",0) -> #NAME? | Q26: =_xlfn.XLOOKUP($U:$U,$V:$V,0,0) -> #NAME? | R26: =_xlfn.XLOOKUP($U:$U,$W:$W,0,0) -> #NAME? | S26: MG | T26: MG | U26: 2322043000208 | V26: D9 | W26: REDE UNIMED
A27: B00337 | B27: 18366237000156 | C27: 110938 | D27: 1828 | E27: DROGARIA FERRAZ DE RECREIO LT | F27: 14175 | G27: INOVA DROGARIA | H27: 34925 | I27: 56 | J27: 34925 | K27: 7 | L27: B00337 | M27: ATIVO | N27: JULIANO DE MOURA HIDAKA | O27: VAGO - ZONA DA MATA - MG | P27: =_xlfn.XLOOKUP('MEDIA TRI'!$E:$E,'MEDIA TRI'!$AA:$AA,"-",0) -> #NAME? | Q27: =_xlfn.XLOOKUP($U:$U,$V:$V,0,0) -> #NAME? | R27: =_xlfn.XLOOKUP($U:$U,$W:$W,0,0) -> #NAME? | S27: MG | T27: MGI | U27: 2322043000208 | V27: D9 | W27: REDE UNIMED
A28: B00410 | B28: 2806415000182 | C28: 163077 | D28: 3412 | E28: DROGARIA FRAGA & BARROS LTDA | F28: 10437 | G28: INDIVIDUAL | H28: 30015 | I28: 21 | J28: 30015 | K28: 7 | L28: B00410 | M28: ATIVO | N28: JULIANO DE MOURA HIDAKA | O28: INATIVO - MG4 | P28: =_xlfn.XLOOKUP('MEDIA TRI'!$E:$E,'MEDIA TRI'!$AA:$AA,"-",0) -> #NAME? | Q28: =_xlfn.XLOOKUP($U:$U,$V:$V,0,0) -> #NAME? | R28: =_xlfn.XLOOKUP($U:$U,$W:$W,0,0) -> #NAME? | S28: MG | T28: MGI | U28: 45425899000637 | V28: D9 | W28: REDE UNIMED
A29: B00444 | B29: 25178070000165 | C29: 145698 | D29: 346 | E29: DROGARIA VIEIRA E BERNO LTDA | F29: 10437 | G29: INDIVIDUAL | H29: 30015 | I29: 21 | J29: 30015 | K29: 7 | L29: B00444 | M29: ATIVO | N29: GABRIEL GONCALVES FONSECA | O29: ANDRE DIAS DE OLIVEIRA | P29: =_xlfn.XLOOKUP('MEDIA TRI'!$E:$E,'MEDIA TRI'!$AA:$AA,"-",0) -> #NAME? | Q29: =_xlfn.XLOOKUP($U:$U,$V:$V,0,0) -> #NAME? | R29: =_xlfn.XLOOKUP($U:$U,$W:$W,0,0) -> #NAME? | S29: MG | T29: MG | U29: 45425899000637 | V29: D9 | W29: REDE UNIMED
A30: B00477 | B30: 22603286000132 | C30: 113973 | D30: 3503 | E30: DROG CENTRAL DE MONTE CARMELO | F30: 10437 | G30: INDIVIDUAL | H30: 30015 | I30: 21 | J30: 30015 | K30: 7 | L30: B00477 | M30: ATIVO | N30: GABRIEL GONCALVES FONSECA | O30: THIAGO DE CASTRO MARIA | P30: =_xlfn.XLOOKUP('MEDIA TRI'!$E:$E,'MEDIA TRI'!$AA:$AA,"-",0) -> #NAME? | Q30: =_xlfn.XLOOKUP($U:$U,$V:$V,0,0) -> #NAME? | R30: =_xlfn.XLOOKUP($U:$U,$W:$W,0,0) -> #NAME? | S30: MG | T30: MGI | U30: 86483542000340 | V30: 5H | W30: UNIMED MG
A31: B00501 | B31: 19260967000130 | C31: 140153 | D31: 542 | E31: ALVIM E LIMA LTDA | F31: 10437 | G31: INDIVIDUAL | H31: 35181 | I31: 55 | J31: 35181 | K31: 7 | L31: B00501 | M31: ATIVO | N31: JULIANO DE MOURA HIDAKA | O31: VAGO - ZONA DA MATA - MG | P31: =_xlfn.XLOOKUP('MEDIA TRI'!$E:$E,'MEDIA TRI'!$AA:$AA,"-",0) -> #NAME? | Q31: =_xlfn.XLOOKUP($U:$U,$V:$V,0,0) -> #NAME? | R31: =_xlfn.XLOOKUP($U:$U,$W:$W,0,0) -> #NAME? | S31: MG | T31: MGI | U31: 86483542000340 | V31: 5H | W31: UNIMED MG
A32: B00543 | B32: 20295028000100 | C32: 135251 | D32: 1828 | E32: DROGARIA ATLAS LTDA | F32: 10437 | G32: INDIVIDUAL | H32: 30015 | I32: 21 | J32: 30015 | K32: 7 | L32: B00543 | M32: ATIVO | N32: JULIANO DE MOURA HIDAKA | O32: VAGO - ZONA DA MATA - MG | P32: =_xlfn.XLOOKUP('MEDIA TRI'!$E:$E,'MEDIA TRI'!$AA:$AA,"-",0) -> #NAME? | Q32: =_xlfn.XLOOKUP($U:$U,$V:$V,0,0) -> #NAME? | R32: =_xlfn.XLOOKUP($U:$U,$W:$W,0,0) -> #NAME? | S32: MG | T32: MGI | U32: 45399961000310 | V32: SE | W32: REDE UNIMED SOROCABA
A33: B00550 | B33: 17076878000103 | C33: 121980 | D33: 530 | E33: RICCO DROGARIA LTDA | F33: 614 | G33: GRUPOFARMA | H33: 35993 | I33: 35 | J33: 35993 | K33: 7 | L33: B00550 | M33: ATIVO | N33: JULIANO DE MOURA HIDAKA | O33: VAGO - ZONA DA MATA - MG | P33: =_xlfn.XLOOKUP('MEDIA TRI'!$E:$E,'MEDIA TRI'!$AA:$AA,"-",0) -> #NAME? | Q33: =_xlfn.XLOOKUP($U:$U,$V:$V,0,0) -> #NAME? | R33: =_xlfn.XLOOKUP($U:$U,$W:$W,0,0) -> #NAME? | S33: MG | T33: MGI | U33: 45399961000310 | V33: D9 | W33: REDE UNIMED
... A45: B00949 | B45: 21314943000169 | C45: 139512 | D45: 1792 | E45: DROGAFAT LTDA ME | F45: 10437 | G45: INDIVIDUAL | H45: 34808 | I45: 7 | J45: 34808 | K45: 7 | L45: B00949 | M45: ATIVO | N45: JULIANO DE MOURA HIDAKA | O45: VAGO - ZONA DA MATA - MG | P45: =_xlfn.XLOOKUP('MEDIA TRI'!$E:$E,'MEDIA TRI'!$AA:$AA,"-",0) -> #NAME? | Q45: =_xlfn.XLOOKUP($U:$U,$V:$V,0,0) -> #NAME? | R45: =_xlfn.XLOOKUP($U:$U,$W:$W,0,0) -> #NAME? | S45: MG | T45: MG | U45: 89100135000132 | V45: 1P | W45: MIX FARMA
A46: B00972 | B46: 42953463000118 | C46: 146199 | D46: 673 | E46: FARMACIA BITTENCOURT LTDA | F46: 12837 | G46: ENTREFARMA FARMARCAS | H46: 35993 | I46: 14 | J46: 35993 | K46: 7 | L46: B00972 | M46: ATIVO | N46: JULIANO DE MOURA HIDAKA | O46: LUIS CARLOS SILVEIRA | P46: =_xlfn.XLOOKUP('MEDIA TRI'!$E:$E,'MEDIA TRI'!$AA:$AA,"-",0) -> #NAME? | Q46: =_xlfn.XLOOKUP($U:$U,$V:$V,0,0) -> #NAME? | R46: =_xlfn.XLOOKUP($U:$U,$W:$W,0,0) -> #NAME? | S46: MG | T46: MG | U46: 75584193000174 | V46: 29 | W46: INDIVIDUAL
A47: B00998 | B47: 7332186000125 | C47: 119277 | D47: 2252 | E47: DROG E PERF CARBONITA LT | F47: 14175 | G47: INOVA DROGARIA | H47: 34808 | I47: 21 | J47: 34808 | K47: 7 | L47: B00998 | M47: ATIVO | N47: GABRIEL GONCALVES FONSECA | O47: ANDRE DIAS DE OLIVEIRA | P47: =_xlfn.XLOOKUP('MEDIA TRI'!$E:$E,'MEDIA TRI'!$AA:$AA,"-",0) -> #NAME? | Q47: =_xlfn.XLOOKUP($U:$U,$V:$V,0,0) -> #NAME? | R47: =_xlfn.XLOOKUP($U:$U,$W:$W,0,0) -> #NAME? | S47: MG | T47: MG | U47: 75584193000174 | V47: 29 | W47: INDIVIDUAL
A48: B01004 | B48: 20716312000103 | C48: 110855 | D48: 2251 | E48: DROGARIA PIRAUBA LTDA | F48: 10437 | G48: INDIVIDUAL | H48: 35195 | I48: 35 | J48: 35195 | K48: 7 | L48: B01004 | M48: ATIVO | N48: JULIANO DE MOURA HIDAKA | O48: VAGO - ZONA DA MATA - MG | P48: =_xlfn.XLOOKUP('MEDIA TRI'!$E:$E,'MEDIA TRI'!$AA:$AA,"-",0) -> #NAME? | Q48: =_xlfn.XLOOKUP($U:$U,$V:$V,0,0) -> #NAME? | R48: =_xlfn.XLOOKUP($U:$U,$W:$W,0,0) -> #NAME? | S48: MG | T48: MGI | U48: 44863959000207
A49: B01020 | B49: 42811083000149 | C49: 148569 | D49: 598 | E49: DROGARIA FRANERI LTDA | F49: 10437 | G49: INDIVIDUAL | H49: 35993 | I49: 30 | J49: 35993 | K49: 7 | L49: B01020 | M49: ATIVO | N49: GABRIEL GONCALVES FONSECA | O49: CIRO DE CARVALHO MIRANDA | P49: =_xlfn.XLOOKUP('MEDIA TRI'!$E:$E,'MEDIA TRI'!$AA:$AA,"-",0) -> #NAME? | Q49: =_xlfn.XLOOKUP($U:$U,$V:$V,0,0) -> #NAME? | R49: =_xlfn.XLOOKUP($U:$U,$W:$W,0,0) -> #NAME? | S49: MG | T49: MG | U49: 44863959000207
A50: B01061 | B50: 38603999000136 | C50: 127960 | D50: 327 | E50: FARMACIA BOY E ALVES LTDA | F50: 10437 | G50: INDIVIDUAL | H50: 35160 | I50: 7 | J50: 35160 | K50: 7 | L50: B01061 | M50: ATIVO | N50: GABRIEL GONCALVES FONSECA | O50: CIRO DE CARVALHO MIRANDA | P50: =_xlfn.XLOOKUP('MEDIA TRI'!$E:$E,'MEDIA TRI'!$AA:$AA,"-",0) -> #NAME? | Q50: =_xlfn.XLOOKUP($U:$U,$V:$V,0,0) -> #NAME? | R50: =_xlfn.XLOOKUP($U:$U,$W:$W,0,0) -> #NAME? | S50: MG | T50: MG | U50: 65732836000207 | V50: 1P | W50: MIX FARMA
A51: B01103 | B51: 25357922000181 | C51: 105167 | D51: 327 | E51: ALTIVO RICARDO ROCHA | F51: 14175 | G51: INOVA DROGARIA | H51: 35997 | I51: 35 | J51: 35997 | K51: 7 | L51: B01103 | M51: ATIVO | N51: GABRIEL GONCALVES FONSECA | O51: CIRO DE CARVALHO MIRANDA | P51: =_xlfn.XLOOKUP('MEDIA TRI'!$E:$E,'MEDIA TRI'!$AA:$AA,"-",0) -> #NAME? | Q51: =_xlfn.XLOOKUP($U:$U,$V:$V,0,0) -> #NAME? | R51: =_xlfn.XLOOKUP($U:$U,$W:$W,0,0) -> #NAME? | S51: MG | T51: MG | U51: 65732836000207 | V51: 1P | W51: MIX FARMA
A52: B01111 | B52: 21264171000106 | C52: 101066 | D52: 327 | E52: J CORREA DE FARIA E CIA LTDA | F52: 10437 | G52: INDIVIDUAL | H52: 34880 | I52: 21 | J52: 34880 | K52: 7 | L52: B01111 | M52: ATIVO | N52: GABRIEL GONCALVES FONSECA | O52: CIRO DE CARVALHO MIRANDA | P52: =_xlfn.XLOOKUP('MEDIA TRI'!$E:$E,'MEDIA TRI'!$AA:$AA,"-",0) -> #NAME? | Q52: =_xlfn.XLOOKUP($U:$U,$V:$V,0,0) -> #NAME? | R52: =_xlfn.XLOOKUP($U:$U,$W:$W,0,0) -> #NAME? | S52: MG | T52: MGI | U52: 20909271000171 | V52: 29 | W52: INDIVIDUAL
A53: B01160 | B53: 66399924000110 | C53: 112840 | D53: 836 | E53: DROGAEFICAZ LTDA | F53: 11423 | G53: MINASDROGAS | H53: 34925 | I53: 52 | J53: 34925 | K53: 7 | L53: B49896 | M53: ATIVO | N53: GABRIEL GONCALVES FONSECA | O53: GUSTAVO GONCALVES | P53: =_xlfn.XLOOKUP('MEDIA TRI'!$E:$E,'MEDIA TRI'!$AA:$AA,"-",0) -> #NAME? | Q53: =_xlfn.XLOOKUP($U:$U,$V:$V,0,0) -> #NAME? | R53: =_xlfn.XLOOKUP($U:$U,$W:$W,0,0) -> #NAME? | S53: MG | T53: MG | U53: 20909271000171 | V53: 29 | W53: INDIVIDUAL
A54: B01178 | B54: 71337737000142 | C54: 102638 | D54: 388 | E54: JOSIANE MONTEIRO B OLIVEIRA ME | F54: 10437 | G54: INDIVIDUAL | H54: 35999 | I54: 8 | J54: 35999 | K54: 7 | L54: B01178 | M54: ATIVO | N54: GABRIEL GONCALVES FONSECA | O54: CIRO DE CARVALHO MIRANDA | P54: =_xlfn.XLOOKUP('MEDIA TRI'!$E:$E,'MEDIA TRI'!$AA:$AA,"-",0) -> #NAME? | Q54: =_xlfn.XLOOKUP($U:$U,$V:$V,0,0) -> #NAME? | R54: =_xlfn.XLOOKUP($U:$U,$W:$W,0,0) -> #NAME? | S54: MG | T54: MG | U54: 20909271000171 | V54: 5H | W54: UNIMED MG
A55: B01186 | B55: 22147631000170 | C55: 131319 | D55: 1828 | E55: FARMACIA BARBOSA LTDA | F55: 9336 | G55: FECOFAR AMERICANA | H55: 35677 | I55: 35 | J55: 35677 | K55: 7 | L55: B01186 | M55: ATIVO | N55: JULIANO DE MOURA HIDAKA | O55: VAGO - ZONA DA MATA - MG | P55: =_xlfn.XLOOKUP('MEDIA TRI'!$E:$E,'MEDIA TRI'!$AA:$AA,"-",0) -> #NAME? | Q55: =_xlfn.XLOOKUP($U:$U,$V:$V,0,0) -> #NAME? | R55: =_xlfn.XLOOKUP($U:$U,$W:$W,0,0) -> #NAME? | S55: MG | T55: MGI | U55: 50480953000334 | V55: VI | W55: REDE UNIMED LIMEIRA
A56: B01202 | B56: 21673132000154 | C56: 104466 | D56: 363 | E56: DROGARIA GARCIAS LTDA | F56: 14059 | G56: DSG MAIS BRASIL | H56: 35993 | I56: 20 | J56: 35993 | K56: 7 | L56: B01202 | M56: ATIVO | N56: JULIANO DE MOURA HIDAKA | O56: LUIS CARLOS SILVEIRA | P56: =_xlfn.XLOOKUP('MEDIA TRI'!$E:$E,'MEDIA TRI'!$AA:$AA,"-",0) -> #NAME? | Q56: =_xlfn.XLOOKUP($U:$U,$V:$V,0,0) -> #NAME? | R56: =_xlfn.XLOOKUP($U:$U,$W:$W,0,0) -> #NAME? | S56: MG | T56: MG | U56: 50480953000334 | V56: VI | W56: REDE UNIMED LIMEIRA
A57: B01228 | B57: 4315972000398 | C57: 133655 | D57: 1650 | E57: DIAS E ROCHA LTDA | F57: 14576 | G57: UNIFABRA NATUS FARMA | H57: 35169 | I57: 56 | J57: 35169 | K57: 7 | L57: B99057 | M57: ATIVO | N57: ALEXANDRO CAIREZ BRIANEZ | O57: GISELLE AMORIM | P57: =_xlfn.XLOOKUP('MEDIA TRI'!$E:$E,'MEDIA TRI'!$AA:$AA,"-",0) -> #NAME? | Q57: =_xlfn.XLOOKUP($U:$U,$V:$V,0,0) -> #NAME? | R57: =_xlfn.XLOOKUP($U:$U,$W:$W,0,0) -> #NAME? | S57: MG | T57: MGI | U57: 45359213000304 | V57: HW | W57: REDE UNIMED SAO CARL
A58: B01244 | B58: 71344436000146 | C58: 117347 | D58: 1438 | E58: MONICA DAS GRACAS RAIMUNDO BER | F58: 14608 | G58: HIPER SAUDE | H58: 34925 | I58: 40 | J58: 34925 | K58: 7 | L58: B01244 | M58: ATIVO | N58: JULIANO DE MOURA HIDAKA | O58: VAGNER LUIZ BUENO CAMBRAIA | P58: =_xlfn.XLOOKUP('MEDIA TRI'!$E:$E,'MEDIA TRI'!$AA:$AA,"-",0) -> #NAME? | Q58: =_xlfn.XLOOKUP($U:$U,$V:$V,0,0) -> #NAME? | R58: =_xlfn.XLOOKUP($U:$U,$W:$W,0,0) -> #NAME? | S58: MG | T58: MGI | U58: 45359213000304 | V58: HW | W58: REDE UNIMED SAO CARL
A59: B01269 | B59: 64296155000280 | C59: 143719 | D59: 1146 | E59: VALADAO & GUERRA LTDA ME | F59: 10437 | G59: INDIVIDUAL | H59: 30015 | I59: 21 | J59: 30015 | K59: 7 | L59: B18255 | M59: ATIVO | N59: GABRIEL GONCALVES FONSECA | O59: INATIVO - MG3 | P59: =_xlfn.XLOOKUP('MEDIA TRI'!$E:$E,'MEDIA TRI'!$AA:$AA,"-",0) -> #NAME? | Q59: =_xlfn.XLOOKUP($U:$U,$V:$V,0,0) -> #NAME? | R59: =_xlfn.XLOOKUP($U:$U,$W:$W,0,0) -> #NAME? | S59: MG | T59: MG | U59: 365720000231 | V59: 5H | W59: UNIMED MG
A60: B01327 | B60: 38700555000119 | C60: 143407 | D60: 542 | E60: DROGARIA GLEBA LTDA | F60: 104 | G60: MG FARMA | H60: 35993 | I60: 36 | J60: 35993 | K60: 7 | L60: B01327 | M60: ATIVO | N60: JULIANO DE MOURA HIDAKA | O60: VAGO - ZONA DA MATA - MG | P60: =_xlfn.XLOOKUP('MEDIA TRI'!$E:$E,'MEDIA TRI'!$AA:$AA,"-",0) -> #NAME? | Q60: =_xlfn.XLOOKUP($U:$U,$V:$V,0,0) -> #NAME? | R60: =_xlfn.XLOOKUP($U:$U,$W:$W,0,0) -> #NAME? | S60: MG | T60: MGI | U60: 365720000231 | V60: 5H | W60: UNIMED MG
A61: B01343 | B61: 24038598000176 | C61: 162961 | D61: 804 | E61: FELIPE ANDRADE CARNEIRO E CIA | F61: 10437 | G61: INDIVIDUAL | H61: 35939 | I61: 32 | J61: 35939 | K61: 7 | L61: B01343 | M61: ATIVO | N61: GABRIEL GONCALVES FONSECA | O61: THIAGO DE CASTRO MARIA | P61: =_xlfn.XLOOKUP('MEDIA TRI'!$E:$E,'MEDIA TRI'!$AA:$AA,"-",0) -> #NAME? | Q61: =_xlfn.XLOOKUP($U:$U,$V:$V,0,0) -> #NAME? | R61: =_xlfn.XLOOKUP($U:$U,$W:$W,0,0) -> #NAME? | S61: MG | T61: MG | U61: 45198009000278 | V61: 9O | W61: REDE UNIMED SP
A62: B01368 | B62: 25552167000196 | C62: 124077 | D62: 1828 | E62: LEODROGAS LTDA | F62: 614 | G62: GRUPOFARMA | H62: 34925 | I62: 40 | J62: 34925 | K62: 40 | L62: B01368 | M62: ATIVO | N62: JULIANO DE MOURA HIDAKA | O62: VAGO - ZONA DA MATA - MG | P62: =_xlfn.XLOOKUP('MEDIA TRI'!$E:$E,'MEDIA TRI'!$AA:$AA,"-",0) -> #NAME? | Q62: =_xlfn.XLOOKUP($U:$U,$V:$V,0,0) -> #NAME? | R62: =_xlfn.XLOOKUP($U:$U,$W:$W,0,0) -> #NAME? | S62: MG | T62: MGI | U62: 45198009000278 | V62: 9O | W62: REDE UNIMED SP
A63: B01392 | B63: 4111232000178 | C63: 142765 | D63: 2255 | E63: DROGARIA CHALE LTDA | F63: 10437 | G63: INDIVIDUAL | H63: 35992 | I63: 7 | J63: 35992 | K63: 7 | L63: B01392 | M63: ATIVO | N63: GABRIEL GONCALVES FONSECA | O63: CIRO DE CARVALHO MIRANDA | P63: =_xlfn.XLOOKUP('MEDIA TRI'!$E:$E,'MEDIA TRI'!$AA:$AA,"-",0) -> #NAME? | Q63: =_xlfn.XLOOKUP($U:$U,$V:$V,0,0) -> #NAME? | R63: =_xlfn.XLOOKUP($U:$U,$W:$W,0,0) -> #NAME? | S63: MG | T63: MG | U63: 25910449000207 | V63: AG | W63: UNIMED TRIANGULO
A64: B01434 | B64: 7646013000181 | C64: 123833 | D64: 1440 | E64: DROGARIA DE MEDICAMENTOS DE CL | F64: 9336 | G64: FECOFAR AMERICANA | H64: 36000 | I64: 28 | J64: 36000 | K64: 28 | L64: L02905 | M64: ATIVO | N64: JULIANO DE MOURA HIDAKA | O64: LUIS CARLOS SILVEIRA | P64: =_xlfn.XLOOKUP('MEDIA TRI'!$E:$E,'MEDIA TRI'!$AA:$AA,"-",0) -> #NAME? | Q64: =_xlfn.XLOOKUP($U:$U,$V:$V,0,0) -> #NAME? | R64: =_xlfn.XLOOKUP($U:$U,$W:$W,0,0) -> #NAME? | S64: MG | T64: MGI | U64: 25910449000207 | V64: AG | W64: UNIMED TRIANGULO
A65: B01459 | B65: 86587912000127 | C65: 128503 | D65: 1829 | E65: DROG NOSSA SRA APARECIDA DE LU | F65: 10437 | G65: INDIVIDUAL | H65: 30015 | I65: 21 | J65: 30015 | K65: 7 | L65: B01459 | M65: ATIVO | N65: JULIANO DE MOURA HIDAKA | O65: LUIS CARLOS SILVEIRA | P65: =_xlfn.XLOOKUP('MEDIA TRI'!$E:$E,'MEDIA TRI'!$AA:$AA,"-",0) -> #NAME? | Q65: =_xlfn.XLOOKUP($U:$U,$V:$V,0,0) -> #NAME? | R65: =_xlfn.XLOOKUP($U:$U,$W:$W,0,0) -> #NAME? | S65: MG | T65: MG | U65: 1559455000295 | V65: 1P | W65: MIX FARMA
A66: B01509 | B66: 25283375000137 | C66: 143411 | D66: 2226 | E66: MARCO TULIO NASCIMENTO SILVA | F66: 10437 | G66: INDIVIDUAL | H66: 34880 | I66: 27 | J66: 34880 | K66: 7 | L66: B01509 | M66: ATIVO | N66: JULIANO DE MOURA HIDAKA | O66: VAGNER LUIZ BUENO CAMBRAIA | P66: =_xlfn.XLOOKUP('MEDIA TRI'!$E:$E,'MEDIA TRI'!$AA:$AA,"-",0) -> #NAME? | Q66: =_xlfn.XLOOKUP($U:$U,$V:$V,0,0) -> #NAME? | R66: =_xlfn.XLOOKUP($U:$U,$W:$W,0,0) -> #NAME? | S66: MG | T66: MGI | U66: 1559455000295 | V66: 1P | W66: MIX FARMA
A67: B01517 | B67: 23955016000153 | C67: 148509 | D67: 327 | E67: MV COMERCIAL FARMACEUTICA LTDA | F67: 10437 | G67: INDIVIDUAL | H67: 35993 | I67: 34 | J67: 35993 | K67: 7 | L67: B01517 | M67: ATIVO | N67: GABRIEL GONCALVES FONSECA | O67: CIRO DE CARVALHO MIRANDA | P67: =_xlfn.XLOOKUP('MEDIA TRI'!$E:$E,'MEDIA TRI'!$AA:$AA,"-",0) -> #NAME? | Q67: =_xlfn.XLOOKUP($U:$U,$V:$V,0,0) -> #NAME? | R67: =_xlfn.XLOOKUP($U:$U,$W:$W,0,0) -> #NAME? | S67: MG | T67: MG | U67: 71925531000214 | V67: 29 | W67: INDIVIDUAL
A68: B01541 | B68: 4514978000122 | C68: 114086 | D68: 968 | E68: DROGARIA PONTUAL LTDA ME | F68: 14329 | G68: ABRAFAD MELHORCOMPRA | H68: 35997 | I68: 28 | J68: 35997 | K68: 7 | L68: B01541 | M68: ATIVO | N68: GABRIEL GONCALVES FONSECA | O68: ANDRE DIAS DE OLIVEIRA | P68: =_xlfn.XLOOKUP('MEDIA TRI'!$E:$E,'MEDIA TRI'!$AA:$AA,"-",0) -> #NAME? | Q68: =_xlfn.XLOOKUP($U:$U,$V:$V,0,0) -> #NAME? | R68: =_xlfn.XLOOKUP($U:$U,$W:$W,0,0) -> #NAME? | S68: MG | T68: MG | U68: 71925531000214 | V68: 29 | W68: INDIVIDUAL
A69: B01558 | B69: 21683362000102 | C69: 127326 | D69: 548 | E69: DROGARIA PONTUAL GUANHAES HUM | F69: 14329 | G69: ABRAFAD MELHORCOMPRA | H69: 34808 | I69: 28 | J69: 34808 | K69: 7 | L69: B01541 | M69: ATIVO | N69: GABRIEL GONCALVES FONSECA | O69: ANDRE DIAS DE OLIVEIRA | P69: =_xlfn.XLOOKUP('MEDIA TRI'!$E:$E,'MEDIA TRI'!$AA:$AA,"-",0) -> #NAME? | Q69: =_xlfn.XLOOKUP($U:$U,$V:$V,0,0) -> #NAME? | R69: =_xlfn.XLOOKUP($U:$U,$W:$W,0,0) -> #NAME? | S69: MG | T69: MG | U69: 47565155000210 | V69: 9O | W69: REDE UNIMED SP
A70: B01582 | B70: 20520383000136 | C70: 133160 | D70: 3433 | E70: SANTA GEMA COMERCIAL LTDA | F70: 8917 | G70: DROGANORTE | H70: 30015 | I70: 21 | J70: 30015 | K70: 7 | L70: B02366 | M70: ATIVO | N70: GABRIEL GONCALVES FONSECA | O70: GUSTAVO GONCALVES | P70: =_xlfn.XLOOKUP('MEDIA TRI'!$E:$E,'MEDIA TRI'!$AA:$AA,"-",0) -> #NAME? | Q70: =_xlfn.XLOOKUP($U:$U,$V:$V,0,0) -> #NAME? | R70: =_xlfn.XLOOKUP($U:$U,$W:$W,0,0) -> #NAME? | S70: MG | T70: MG | U70: 47565155000210 | V70: 9O | W70: REDE UNIMED SP
A71: B01616 | B71: 7262143000110 | C71: 118905 | D71: 1828 | E71: DROGARIA CIDADE ALTA LTDA | F71: 14608 | G71: HIPER SAUDE | H71: 35993 | I71: 45 | J71: 35993 | K71: 7 | L71: L03473 | M71: ATIVO | N71: JULIANO DE MOURA HIDAKA | O71: VAGO - ZONA DA MATA - MG | P71: =_xlfn.XLOOKUP('MEDIA TRI'!$E:$E,'MEDIA TRI'!$AA:$AA,"-",0) -> #NAME? | Q71: =_xlfn.XLOOKUP($U:$U,$V:$V,0,0) -> #NAME? | R71: =_xlfn.XLOOKUP($U:$U,$W:$W,0,0) -> #NAME? | S71: MG | T71: MGI | U71: 88258884001444 | V71: 1P | W71: MIX FARMA
A72: B01624 | B72: 65271744000196 | C72: 146688 | D72: 530 | E72: DROGARIA VALENTE LTDA | F72: 10437 | G72: INDIVIDUAL | H72: 35191 | I72: 40 | J72: 35191 | K72: 7 | L72: B01624 | M72: ATIVO | N72: JULIANO DE MOURA HIDAKA | O72: VAGO - ZONA DA MATA - MG | P72: =_xlfn.XLOOKUP('MEDIA TRI'!$E:$E,'MEDIA TRI'!$AA:$AA,"-",0) -> #NAME? | Q72: =_xlfn.XLOOKUP($U:$U,$V:$V,0,0) -> #NAME? | R72: =_xlfn.XLOOKUP($U:$U,$W:$W,0,0) -> #NAME? | S72: MG | T72: MGI | U72: 88258884001444 | V72: 1P | W72: MIX FARMA
A73: B01632 | B73: 21645304000186 | C73: 115188 | D73: 512 | E73: M F DEOLIVEIRA MIRANDA E CIA L | F73: 10437 | G73: INDIVIDUAL | H73: 34925 | I73: 36 | J73: 34925 | K73: 7 | L73: B01632 | M73: ATIVO | N73: JULIANO DE MOURA HIDAKA | O73: DOUGLAS ALCANTARA PEREIRA | P73: =_xlfn.XLOOKUP('MEDIA TRI'!$E:$E,'MEDIA TRI'!$AA:$AA,"-",0) -> #NAME? | Q73: =_xlfn.XLOOKUP($U:$U,$V:$V,0,0) -> #NAME? | R73: =_xlfn.XLOOKUP($U:$U,$W:$W,0,0) -> #NAME? | S73: MG | T73: MG | U73: 103956000119 | V73: 1P | W73: MIX FARMA
A74: B01657 | B74: 71049878000160 | C74: 100867 | D74: 1146 | E74: DROG NV MILENIO LT ME | F74: 10437 | G74: INDIVIDUAL | H74: 30015 | I74: 21 | J74: 30015 | K74: 7 | L74: B01657 | M74: ATIVO | N74: GABRIEL GONCALVES FONSECA | O74: INATIVO - MG3 | P74: =_xlfn.XLOOKUP('MEDIA TRI'!$E:$E,'MEDIA TRI'!$AA:$AA,"-",0) -> #NAME? | Q74: =_xlfn.XLOOKUP($U:$U,$V:$V,0,0) -> #NAME? | R74: =_xlfn.XLOOKUP($U:$U,$W:$W,0,0) -> #NAME? | S74: MG | T74: MG | U74: 103956000119 | V74: 1P | W74: MIX FARMA
A75: B01665 | B75: 17715558000156 | C75: 128994 | D75: 230 | E75: DROGAMINAS LTDA | F75: 614 | G75: GRUPOFARMA | H75: 35997 | I75: 35 | J75: 35997 | K75: 7 | L75: B01665 | M75: ATIVO | N75: JULIANO DE MOURA HIDAKA | O75: VAGO - ZONA DA MATA - MG | P75: =_xlfn.XLOOKUP('MEDIA TRI'!$E:$E,'MEDIA TRI'!$AA:$AA,"-",0) -> #NAME? | Q75: =_xlfn.XLOOKUP($U:$U,$V:$V,0,0) -> #NAME? | R75: =_xlfn.XLOOKUP($U:$U,$W:$W,0,0) -> #NAME? | S75: MG | T75: MGI | U75: 2687852000205 | V75: HX | W75: REDE UNIMED ANDRADI
A76: B01673 | B76: 2702895000131 | C76: 121243 | D76: 529 | E76: ROSANGELA ALVES DE LIMA ME | F76: 14608 | G76: HIPER SAUDE | H76: 33408 | I76: 7 | J76: 33408 | K76: 7 | L76: B01673 | M76: ATIVO | N76: JULIANO DE MOURA HIDAKA | O76: VAGNER LUIZ BUENO CAMBRAIA | P76: =_xlfn.XLOOKUP('MEDIA TRI'!$E:$E,'MEDIA TRI'!$AA:$AA,"-",0) -> #NAME? | Q76: =_xlfn.XLOOKUP($U:$U,$V:$V,0,0) -> #NAME? | R76: =_xlfn.XLOOKUP($U:$U,$W:$W,0,0) -> #NAME? | S76: MG | T76: MGI | U76: 2687852000205 | V76: HX | W76: REDE UNIMED ANDRADI
A77: B01681 | B77: 20907150000190 | C77: 100024 | D77: 327 | E77: ANDRE FELIPE LAET SOUZA E CIA | F77: 14516 | G77: ABRAFAD REDE SOMA | H77: 34925 | I77: 29 | J77: 34925 | K77: 7 | L77: B01681 | M77: ATIVO | N77: GABRIEL GONCALVES FONSECA | O77: CIRO DE CARVALHO MIRANDA | P77: =_xlfn.XLOOKUP('MEDIA TRI'!$E:$E,'MEDIA TRI'!$AA:$AA,"-",0) -> #NAME? | Q77: =_xlfn.XLOOKUP($U:$U,$V:$V,0,0) -> #NAME? | R77: =_xlfn.XLOOKUP($U:$U,$W:$W,0,0) -> #NAME? | S77: MG | T77: MG | U77: 44663631000247 | V77: HT | W77: REDE UNIMED RIO CLAR
A78: B01707 | B78: 22154330000174 | C78: 111984 | D78: 1828 | E78: DROGARIA AVENIDA COTEGIPE LTDA | F78: 104 | G78: MG FARMA | H78: 35993 | I78: 50 | J78: 35993 | K78: 7 | L78: B01707 | M78: ATIVO | N78: JULIANO DE MOURA HIDAKA | O78: VAGO - ZONA DA MATA - MG | P78: =_xlfn.XLOOKUP('MEDIA TRI'!$E:$E,'MEDIA TRI'!$AA:$AA,"-",0) -> #NAME? | Q78: =_xlfn.XLOOKUP($U:$U,$V:$V,0,0) -> #NAME? | R78: =_xlfn.XLOOKUP($U:$U,$W:$W,0,0) -> #NAME? | S78: MG | T78: MGI | U78: 44663631000247 | V78: 1P | W78: MIX FARMA
A79: B01749 | B79: 23234339000158 | C79: 108281 | D79: 1828 | E79: NEUZA MARIA NEV OLIV EIRELI ME | F79: 10437 | G79: INDIVIDUAL | H79: 34887 | I79: 32 | J79: 34887 | K79: 7 | L79: B01749 | M79: ATIVO | N79: JULIANO DE MOURA HIDAKA | O79: VAGO - ZONA DA MATA - MG | P79: =_xlfn.XLOOKUP('MEDIA TRI'!$E:$E,'MEDIA TRI'!$AA:$AA,"-",0) -> #NAME? | Q79: =_xlfn.XLOOKUP($U:$U,$V:$V,0,0) -> #NAME? | R79: =_xlfn.XLOOKUP($U:$U,$W:$W,0,0) -> #NAME? | S79: MG | T79: MGI | U79: 71695746000377 | V79: 1P | W79: MIX FARMA
A80: B01756 | B80: 19691302000181 | C80: 136255 | D80: 228 | E80: FCIA CONGONHAS DO CAMPO LT | F80: 10437 | G80: INDIVIDUAL | H80: 35939 | I80: 7 | J80: 35939 | K80: 7 | L80: B01756 | M80: ATIVO | N80: JULIANO DE MOURA HIDAKA | O80: VAGO - ZONA DA MATA - MG | P80: =_xlfn.XLOOKUP('MEDIA TRI'!$E:$E,'MEDIA TRI'!$AA:$AA,"-",0) -> #NAME? | Q80: =_xlfn.XLOOKUP($U:$U,$V:$V,0,0) -> #NAME? | R80: =_xlfn.XLOOKUP($U:$U,$W:$W,0,0) -> #NAME? | S80: MG | T80: MG | U80: 71695746000377 | V80: 1P | W80: MIX FARMA
... A84: B01822 | B84: 3458345000181 | C84: 148192 | D84: 3059 | E84: MATERMARIA FARMACIA LTDA ME | F84: 10437 | G84: INDIVIDUAL | H84: 34925 | I84: 35 | J84: 34925 | K84: 7 | L84: B01822 | M84: ATIVO | N84: GABRIEL GONCALVES FONSECA | O84: GUSTAVO GONCALVES | P84: =_xlfn.XLOOKUP('MEDIA TRI'!$E:$E,'MEDIA TRI'!$AA:$AA,"-",0) -> #NAME? | Q84: =_xlfn.XLOOKUP($U:$U,$V:$V,0,0) -> #NAME? | R84: =_xlfn.XLOOKUP($U:$U,$W:$W,0,0) -> #NAME? | S84: MG | T84: MG | U84: 50480953000253 | V84: 1P | W84: MIX FARMA
A85: B01855 | B85: 19671403000190 | C85: 110200 | D85: 1828 | E85: DROGARIA LEOPOLDINA LTDA | F85: 10437 | G85: INDIVIDUAL | H85: 35195 | I85: 43 | J85: 35195 | K85: 7 | L85: B01855 | M85: ATIVO | N85: JULIANO DE MOURA HIDAKA | O85: VAGO - ZONA DA MATA - MG | P85: =_xlfn.XLOOKUP('MEDIA TRI'!$E:$E,'MEDIA TRI'!$AA:$AA,"-",0) -> #NAME? | Q85: =_xlfn.XLOOKUP($U:$U,$V:$V,0,0) -> #NAME? | R85: =_xlfn.XLOOKUP($U:$U,$W:$W,0,0) -> #NAME? | S85: MG | T85: MGI | U85: 532888000294 | V85: 29 | W85: INDIVIDUAL
A86: B01863 | B86: 2633061000111 | C86: 134342 | D86: 1146 | E86: DROGA LIVA LTDA | F86: 8917 | G86: DROGANORTE | H86: 30015 | I86: 21 | J86: 30015 | K86: 7 | L86: B02366 | M86: ATIVO | N86: GABRIEL GONCALVES FONSECA | O86: INATIVO - MG3 | P86: =_xlfn.XLOOKUP('MEDIA TRI'!$E:$E,'MEDIA TRI'!$AA:$AA,"-",0) -> #NAME? | Q86: =_xlfn.XLOOKUP($U:$U,$V:$V,0,0) -> #NAME? | R86: =_xlfn.XLOOKUP($U:$U,$W:$W,0,0) -> #NAME? | S86: MG | T86: MG | U86: 532888000294 | V86: 29 | W86: INDIVIDUAL
A87: B01897 | B87: 71094213000178 | C87: 134759 | D87: 2251 | E87: L S R PRATA & CIA LTDA | F87: 10437 | G87: INDIVIDUAL | H87: 34925 | I87: 7 | J87: 34925 | K87: 7 | L87: B01897 | M87: ATIVO | N87: JULIANO DE MOURA HIDAKA | O87: VAGO - ZONA DA MATA - MG | P87: =_xlfn.XLOOKUP('MEDIA TRI'!$E:$E,'MEDIA TRI'!$AA:$AA,"-",0) -> #NAME? | Q87: =_xlfn.XLOOKUP($U:$U,$V:$V,0,0) -> #NAME? | R87: =_xlfn.XLOOKUP($U:$U,$W:$W,0,0) -> #NAME? | S87: MG | T87: MGI | U87: 87306361000653 | V87: 1P | W87: MIX FARMA
A88: B01970 | B88: 7402830000194 | C88: 124698 | D88: 1146 | E88: FARMAREI LTDA EPP | F88: 10437 | G88: INDIVIDUAL | H88: 30015 | I88: 21 | J88: 30015 | K88: 7 | L88: B01970 | M88: ATIVO | N88: GABRIEL GONCALVES FONSECA | O88: INATIVO - MG3 | P88: =_xlfn.XLOOKUP('MEDIA TRI'!$E:$E,'MEDIA TRI'!$AA:$AA,"-",0) -> #NAME? | Q88: =_xlfn.XLOOKUP($U:$U,$V:$V,0,0) -> #NAME? | R88: =_xlfn.XLOOKUP($U:$U,$W:$W,0,0) -> #NAME? | S88: MG | T88: MG | U88: 87306361000653 | V88: 1P | W88: MIX FARMA
A89: B02002 | B89: 17528092000180 | C89: 136866 | D89: 3412 | E89: DROGARIA SAUDE NEPOMUCENO LTDA | F89: 10437 | G89: INDIVIDUAL | H89: 30015 | I89: 21 | J89: 30015 | K89: 7 | L89: B02002 | M89: ATIVO | N89: JULIANO DE MOURA HIDAKA | O89: INATIVO - MG4 | P89: =_xlfn.XLOOKUP('MEDIA TRI'!$E:$E,'MEDIA TRI'!$AA:$AA,"-",0) -> #NAME? | Q89: =_xlfn.XLOOKUP($U:$U,$V:$V,0,0) -> #NAME? | R89: =_xlfn.XLOOKUP($U:$U,$W:$W,0,0) -> #NAME? | S89: MG | T89: MGI | U89: 87827689002405 | V89: 1P | W89: MIX FARMA
A90: B02010 | B90: 41699398000183 | C90: 125730 | D90: 327 | E90: MELANIA E SANTANNA COM DE MED | F90: 15894 | G90: ABRAFAD META DROGARIAS | H90: 35181 | I90: 55 | J90: 35181 | K90: 7 | L90: L09724 | M90: ATIVO | N90: GABRIEL GONCALVES FONSECA | O90: CIRO DE CARVALHO MIRANDA | P90: =_xlfn.XLOOKUP('MEDIA TRI'!$E:$E,'MEDIA TRI'!$AA:$AA,"-",0) -> #NAME? | Q90: =_xlfn.XLOOKUP($U:$U,$V:$V,0,0) -> #NAME? | R90: =_xlfn.XLOOKUP($U:$U,$W:$W,0,0) -> #NAME? | S90: MG | T90: MG | U90: 87827689002405 | V90: 1P | W90: MIX FARMA
A91: B02028 | B91: 22284392000109 | C91: 139886 | D91: 1828 | E91: DROG BAIRRO BELA VTA LT | F91: 614 | G91: GRUPOFARMA | H91: 35939 | I91: 40 | J91: 35939 | K91: 7 | L91: B02028 | M91: ATIVO | N91: JULIANO DE MOURA HIDAKA | O91: VAGO - ZONA DA MATA - MG | P91: =_xlfn.XLOOKUP('MEDIA TRI'!$E:$E,'MEDIA TRI'!$AA:$AA,"-",0) -> #NAME? | Q91: =_xlfn.XLOOKUP($U:$U,$V:$V,0,0) -> #NAME? | R91: =_xlfn.XLOOKUP($U:$U,$W:$W,0,0) -> #NAME? | S91: MG | T91: MGI | U91: 87647756000296 | V91: 1P | W91: MIX FARMA
A92: B02044 | B92: 38753968000161 | C92: 122260 | D92: 2129 | E92: CLAUDIO LOPES DE LANA | F92: 10437 | G92: INDIVIDUAL | H92: 35187 | I92: 8 | J92: 35187 | K92: 7 | L92: B02044 | M92: ATIVO | N92: GABRIEL GONCALVES FONSECA | O92: GUSTAVO GONCALVES | P92: =_xlfn.XLOOKUP('MEDIA TRI'!$E:$E,'MEDIA TRI'!$AA:$AA,"-",0) -> #NAME? | Q92: =_xlfn.XLOOKUP($U:$U,$V:$V,0,0) -> #NAME? | R92: =_xlfn.XLOOKUP($U:$U,$W:$W,0,0) -> #NAME? | S92: MG | T92: MG | U92: 87647756000296 | V92: 1P | W92: MIX FARMA
A93: B02093 | B93: 25171067000110 | C93: 104102 | D93: 1828 | E93: PAULO A DE OL CARVALHO & CIA | F93: 104 | G93: MG FARMA | H93: 35997 | I93: 21 | J93: 35997 | K93: 7 | L93: B02093 | M93: ATIVO | N93: JULIANO DE MOURA HIDAKA | O93: VAGO - ZONA DA MATA - MG | P93: =_xlfn.XLOOKUP('MEDIA TRI'!$E:$E,'MEDIA TRI'!$AA:$AA,"-",0) -> #NAME? | Q93: =_xlfn.XLOOKUP($U:$U,$V:$V,0,0) -> #NAME? | R93: =_xlfn.XLOOKUP($U:$U,$W:$W,0,0) -> #NAME? | S93: MG | T93: MGI | U93: 17790718000121 | V93: 28 | W93: MIX FARMA B
A94: B02127 | B94: 5264412000152 | C94: 102078 | D94: 3412 | E94: ZANOTTI MEDICAMENTOS LTDA | F94: 10437 | G94: INDIVIDUAL | H94: 30015 | I94: 21 | J94: 30015 | K94: 7 | L94: B02127 | M94: ATIVO | N94: JULIANO DE MOURA HIDAKA | O94: INATIVO - MG4 | P94: =_xlfn.XLOOKUP('MEDIA TRI'!$E:$E,'MEDIA TRI'!$AA:$AA,"-",0) -> #NAME? | Q94: =_xlfn.XLOOKUP($U:$U,$V:$V,0,0) -> #NAME? | R94: =_xlfn.XLOOKUP($U:$U,$W:$W,0,0) -> #NAME? | S94: MG | T94: MGI | U94: 17790718000121 | V94: 28 | W94: MIX FARMA B
A95: B02135 | B95: 20962817000158 | C95: 162684 | D95: 529 | E95: DROGARIA FAMILIAR LTDA ME | F95: 13510 | G95: UAI FARMA | H95: 34925 | I95: 35 | J95: 34925 | K95: 7 | L95: L07895 | M95: ATIVO | N95: JULIANO DE MOURA HIDAKA | O95: VAGNER LUIZ BUENO CAMBRAIA | P95: =_xlfn.XLOOKUP('MEDIA TRI'!$E:$E,'MEDIA TRI'!$AA:$AA,"-",0) -> #NAME? | Q95: =_xlfn.XLOOKUP($U:$U,$V:$V,0,0) -> #NAME? | R95: =_xlfn.XLOOKUP($U:$U,$W:$W,0,0) -> #NAME? | S95: MG | T95: MGI | U95: 59499251000296 | V95: 1P | W95: MIX FARMA
A96: B02143 | B96: 24332843000153 | C96: 107240 | D96: 678 | E96: DROGALMEIDA LTDA | F96: 10437 | G96: INDIVIDUAL | H96: 34925 | I96: 60 | J96: 34925 | K96: 7 | L96: B02143 | M96: ATIVO | N96: GABRIEL GONCALVES FONSECA | O96: THIAGO DE CASTRO MARIA | P96: =_xlfn.XLOOKUP('MEDIA TRI'!$E:$E,'MEDIA TRI'!$AA:$AA,"-",0) -> #NAME? | Q96: =_xlfn.XLOOKUP($U:$U,$V:$V,0,0) -> #NAME? | R96: =_xlfn.XLOOKUP($U:$U,$W:$W,0,0) -> #NAME? | S96: MG | T96: MGI | U96: 59499251000296 | V96: 1P | W96: MIX FARMA
A97: B02150 | B97: 6212469000170 | C97: 141667 | D97: 1439 | E97: VILLANI MEDICAMENTOS LTDA ME | F97: 10437 | G97: INDIVIDUAL | H97: 35181 | I97: 35 | J97: 35181 | K97: 7 | L97: B02150 | M97: ATIVO | N97: JULIANO DE MOURA HIDAKA | O97: VAGNER LUIZ BUENO CAMBRAIA | P97: =_xlfn.XLOOKUP('MEDIA TRI'!$E:$E,'MEDIA TRI'!$AA:$AA,"-",0) -> #NAME? | Q97: =_xlfn.XLOOKUP($U:$U,$V:$V,0,0) -> #NAME? | R97: =_xlfn.XLOOKUP($U:$U,$W:$W,0,0) -> #NAME? | S97: MG | T97: MGI | U97: 59499251000296 | V97: 1P | W97: MIX FARMA
A98: B02168 | B98: 2641919000190 | C98: 105696 | D98: 819 | E98: DROGARIA D LIVEIRA LTDA | F98: 14305 | G98: ULTRAPOPULAR FARMARCAS | H98: 35992 | I98: 7 | J98: 35992 | K98: 7 | L98: B02168 | M98: ATIVO | N98: GABRIEL GONCALVES FONSECA | O98: THIAGO DE CASTRO MARIA | P98: =_xlfn.XLOOKUP('MEDIA TRI'!$E:$E,'MEDIA TRI'!$AA:$AA,"-",0) -> #NAME? | Q98: =_xlfn.XLOOKUP($U:$U,$V:$V,0,0) -> #NAME? | R98: =_xlfn.XLOOKUP($U:$U,$W:$W,0,0) -> #NAME? | S98: MG | T98: MG | U98: 45399961000230 | V98: 1P | W98: MIX FARMA
A99: B02176 | B99: 26028035000122 | C99: 163048 | D99: 836 | E99: DROGA FARMA SHOPPING LTDA ME | F99: 14326 | G99: ABRAFAD UNIVERSAL | H99: 35994 | I99: 21 | J99: 35994 | K99: 7 | L99: B48328 | M99: ATIVO | N99: GABRIEL GONCALVES FONSECA | O99: GUSTAVO GONCALVES | P99: =_xlfn.XLOOKUP('MEDIA TRI'!$E:$E,'MEDIA TRI'!$AA:$AA,"-",0) -> #NAME? | Q99: =_xlfn.XLOOKUP($U:$U,$V:$V,0,0) -> #NAME? | R99: =_xlfn.XLOOKUP($U:$U,$W:$W,0,0) -> #NAME? | S99: MG | T99: MG | U99: 45399961000230 | V99: 1P | W99: MIX FARMA
A100: B02184 | B100: 22152797000185 | C100: 139872 | D100: 1828 | E100: DROG SAO GERALDO LEOPOLDIN LTD | F100: 10994 | G100: ABRAFAD GRUPO MF | H100: 34871 | I100: 7 | J100: 34871 | K100: 7 | L100: B02184 | M100: ATIVO | N100: JULIANO DE MOURA HIDAKA | O100: VAGO - ZONA DA MATA - MG | P100: =_xlfn.XLOOKUP('MEDIA TRI'!$E:$E,'MEDIA TRI'!$AA:$AA,"-",0) -> #NAME? | Q100: =_xlfn.XLOOKUP($U:$U,$V:$V,0,0) -> #NAME? | R100: =_xlfn.XLOOKUP($U:$U,$W:$W,0,0) -> #NAME? | S100: MG | T100: MGI | U100: 57214900000159 | V100: 1P | W100: MIX FARMA
A101: B02242 | B101: 65242646000120 | C101: 109444 | D101: 543 | E101: C A DROGARIA LTDA | F101: 10994 | G101: ABRAFAD GRUPO MF | H101: 34925 | I101: 28 | J101: 34925 | K101: 7 | L101: B02242 | M101: ATIVO | N101: GABRIEL GONCALVES FONSECA | O101: CIRO DE CARVALHO MIRANDA | P101: =_xlfn.XLOOKUP('MEDIA TRI'!$E:$E,'MEDIA TRI'!$AA:$AA,"-",0) -> #NAME? | Q101: =_xlfn.XLOOKUP($U:$U,$V:$V,0,0) -> #NAME? | R101: =_xlfn.XLOOKUP($U:$U,$W:$W,0,0) -> #NAME? | S101: MG | T101: MG | U101: 57214900000159 | V101: 1P | W101: MIX FARMA
A102: B02267 | B102: 22048219000101 | C102: 139972 | D102: 3412 | E102: DROGANELK LTDA | F102: 10437 | G102: INDIVIDUAL | H102: 30015 | I102: 21 | J102: 30015 | K102: 7 | L102: B02267 | M102: ATIVO | N102: JULIANO DE MOURA HIDAKA | O102: INATIVO - MG4 | P102: =_xlfn.XLOOKUP('MEDIA TRI'!$E:$E,'MEDIA TRI'!$AA:$AA,"-",0) -> #NAME? | Q102: =_xlfn.XLOOKUP($U:$U,$V:$V,0,0) -> #NAME? | R102: =_xlfn.XLOOKUP($U:$U,$W:$W,0,0) -> #NAME? | S102: MG | T102: MGI | U102: 53678264000246 | V102: IS | W102: REDE SAO VICENTE
A103: B02275 | B103: 23890072000157 | C103: 142731 | D103: 1437 | E103: DROGARIA SAUDE VARGENSE LTDA | F103: 9336 | G103: FECOFAR AMERICANA | H103: 35677 | I103: 14 | J103: 35677 | K103: 7 | L103: B02275 | M103: ATIVO | N103: JULIANO DE MOURA HIDAKA | O103: VAGNER LUIZ BUENO CAMBRAIA | P103: =_xlfn.XLOOKUP('MEDIA TRI'!$E:$E,'MEDIA TRI'!$AA:$AA,"-",0) -> #NAME? | Q103: =_xlfn.XLOOKUP($U:$U,$V:$V,0,0) -> #NAME? | R103: =_xlfn.XLOOKUP($U:$U,$W:$W,0,0) -> #NAME? | S103: MG | T103: MGI | U103: 53678264000246 | V103: IS | W103: REDE SAO VICENTE
A104: B02283 | B104: 1126794000105 | C104: 141389 | D104: 543 | E104: DROG E FCIA DE MANIPULACAO SAO | F104: 14175 | G104: INOVA DROGARIA | H104: 35992 | I104: 8 | J104: 35992 | K104: 7 | L104: B02283 | M104: ATIVO | N104: GABRIEL GONCALVES FONSECA | O104: CIRO DE CARVALHO MIRANDA | P104: =_xlfn.XLOOKUP('MEDIA TRI'!$E:$E,'MEDIA TRI'!$AA:$AA,"-",0) -> #NAME? | Q104: =_xlfn.XLOOKUP($U:$U,$V:$V,0,0) -> #NAME? | R104: =_xlfn.XLOOKUP($U:$U,$W:$W,0,0) -> #NAME? | S104: MG | T104: MG | U104: 51427540000359 | V104: 1P | W104: MIX FARMA
A105: B02291 | B105: 18758383000127 | C105: 111236 | D105: 227 | E105: DROG S SEBASTIAO DE BICAS LT | F105: 10437 | G105: INDIVIDUAL | H105: 35993 | I105: 60 | J105: 35993 | K105: 7 | L105: B02291 | M105: ATIVO | N105: JULIANO DE MOURA HIDAKA | O105: VAGO - ZONA DA MATA - MG | P105: =_xlfn.XLOOKUP('MEDIA TRI'!$E:$E,'MEDIA TRI'!$AA:$AA,"-",0) -> #NAME? | Q105: =_xlfn.XLOOKUP($U:$U,$V:$V,0,0) -> #NAME? | R105: =_xlfn.XLOOKUP($U:$U,$W:$W,0,0) -> #NAME? | S105: MG | T105: MGI | U105: 51427540000359 | V105: 1P | W105: MIX FARMA
A106: B02325 | B106: 42846147000147 | C106: 138418 | D106: 3412 | E106: GIOVANNA SILVA MUSARRA | F106: 15140 | G106: SMALL FARMA | H106: 30015 | I106: 21 | J106: 30015 | K106: 7 | L106: B02325 | M106: ATIVO | N106: JULIANO DE MOURA HIDAKA | O106: INATIVO - MG4 | P106: =_xlfn.XLOOKUP('MEDIA TRI'!$E:$E,'MEDIA TRI'!$AA:$AA,"-",0) -> #NAME? | Q106: =_xlfn.XLOOKUP($U:$U,$V:$V,0,0) -> #NAME? | R106: =_xlfn.XLOOKUP($U:$U,$W:$W,0,0) -> #NAME? | S106: MG | T106: MGI | U106: 41781949000234 | V106: 28 | W106: MIX FARMA B
A107: B02341 | B107: 24231284000195 | C107: 145688 | D107: 328 | E107: FARMACIA CENTRAL MACHADO EIREL | F107: 14329 | G107: ABRAFAD MELHORCOMPRA | H107: 35181 | I107: 32 | J107: 35181 | K107: 7 | L107: B02341 | M107: ATIVO | N107: GABRIEL GONCALVES FONSECA | O107: CIRO DE CARVALHO MIRANDA | P107: =_xlfn.XLOOKUP('MEDIA TRI'!$E:$E,'MEDIA TRI'!$AA:$AA,"-",0) -> #NAME? | Q107: =_xlfn.XLOOKUP($U:$U,$V:$V,0,0) -> #NAME? | R107: =_xlfn.XLOOKUP($U:$U,$W:$W,0,0) -> #NAME? | S107: MG | T107: MG | U107: 41781949000234 | V107: 28 | W107: MIX FARMA B
A108: B02366 | B108: 41740796000104 | C108: 147107 | D108: 333 | E108: DRUGSTAR LTDA | F108: 8917 | G108: DROGANORTE | H108: 35994 | I108: 35 | J108: 35994 | K108: 35 | L108: B02366 | M108: ATIVO | N108: GABRIEL GONCALVES FONSECA | O108: GUSTAVO GONCALVES | P108: =_xlfn.XLOOKUP('MEDIA TRI'!$E:$E,'MEDIA TRI'!$AA:$AA,"-",0) -> #NAME? | Q108: =_xlfn.XLOOKUP($U:$U,$V:$V,0,0) -> #NAME? | R108: =_xlfn.XLOOKUP($U:$U,$W:$W,0,0) -> #NAME? | S108: MG | T108: MG | U108: 25471574001302 | V108: XZ | W108: MINAS MASTER
A109: B02390 | B109: 25813189000162 | C109: 105911 | D109: 1791 | E109: DROGARIA FAZOLLO LTDA | F109: 14548 | G109: REDE FARMACRO | H109: 35996 | I109: 14 | J109: 35996 | K109: 7 | L109: B02390 | M109: ATIVO | N109: GABRIEL GONCALVES FONSECA | O109: ANDRE DIAS DE OLIVEIRA | P109: =_xlfn.XLOOKUP('MEDIA TRI'!$E:$E,'MEDIA TRI'!$AA:$AA,"-",0) -> #NAME? | Q109: =_xlfn.XLOOKUP($U:$U,$V:$V,0,0) -> #NAME? | R109: =_xlfn.XLOOKUP($U:$U,$W:$W,0,0) -> #NAME? | S109: MG | T109: MG | U109: 25471574001302 | V109: XZ | W109: MINAS MASTER
A110: B02408 | B110: 22263180000137 | C110: 117948 | D110: 2255 | E110: FARM PAGUE FACIL MANHUMIRIM L | F110: 13531 | G110: DSG POUPE BRASIL | H110: 34925 | I110: 7 | J110: 34925 | K110: 7 | L110: L05914 | M110: ATIVO | N110: GABRIEL GONCALVES FONSECA | O110: CIRO DE CARVALHO MIRANDA | P110: =_xlfn.XLOOKUP('MEDIA TRI'!$E:$E,'MEDIA TRI'!$AA:$AA,"-",0) -> #NAME? | Q110: =_xlfn.XLOOKUP($U:$U,$V:$V,0,0) -> #NAME? | R110: =_xlfn.XLOOKUP($U:$U,$W:$W,0,0) -> #NAME? | S110: MG | T110: MG | U110: 75222224000147 | V110: 1P | W110: MIX FARMA
A111: B02416 | B111: 2633185000105 | C111: 150380 | D111: 1146 | E111: ANTONIO RAFAEL ROELLA ME | F111: 8639 | G111: DROG FONSECA LTDA | H111: 30015 | I111: 21 | J111: 30015 | K111: 7 | L111: B02416 | M111: ATIVO | N111: GABRIEL GONCALVES FONSECA | O111: INATIVO - MG3 | P111: =_xlfn.XLOOKUP('MEDIA TRI'!$E:$E,'MEDIA TRI'!$AA:$AA,"-",0) -> #NAME? | Q111: =_xlfn.XLOOKUP($U:$U,$V:$V,0,0) -> #NAME? | R111: =_xlfn.XLOOKUP($U:$U,$W:$W,0,0) -> #NAME? | S111: MG | T111: MG | U111: 75222224000147 | V111: 1P | W111: MIX FARMA
A112: B02515 | B112: 7470506000103 | C112: 145628 | D112: 1828 | E112: DROGASERV DROGARIA LTDA ME | F112: 14175 | G112: INOVA DROGARIA | H112: 35993 | I112: 45 | J112: 35993 | K112: 7 | L112: B05898 | M112: ATIVO | N112: JULIANO DE MOURA HIDAKA | O112: VAGO - ZONA DA MATA - MG | P112: =_xlfn.XLOOKUP('MEDIA TRI'!$E:$E,'MEDIA TRI'!$AA:$AA,"-",0) -> #NAME? | Q112: =_xlfn.XLOOKUP($U:$U,$V:$V,0,0) -> #NAME? | R112: =_xlfn.XLOOKUP($U:$U,$W:$W,0,0) -> #NAME? | S112: MG | T112: MGI | U112: 85377174000392 | V112: 1P | W112: MIX FARMA
A113: B02523 | B113: 17193350000114 | C113: 114096 | D113: 1444 | E113: DROGARIA DO POVAO LTDA-ME | F113: 10437 | G113: INDIVIDUAL | H113: 30015 | I113: 21 | J113: 30015 | K113: 7 | L113: B02523 | M113: ATIVO | N113: GABRIEL GONCALVES FONSECA | O113: GUSTAVO GONCALVES | P113: =_xlfn.XLOOKUP('MEDIA TRI'!$E:$E,'MEDIA TRI'!$AA:$AA,"-",0) -> #NAME? | Q113: =_xlfn.XLOOKUP($U:$U,$V:$V,0,0) -> #NAME? | R113: =_xlfn.XLOOKUP($U:$U,$W:$W,0,0) -> #NAME? | S113: MG | T113: MG | U113: 85377174000392 | V113: 1P | W113: MIX FARMA
A114: B02549 | B114: 65380792000112 | C114: 105955 | D114: 1829 | E114: SOLIS FARMA DROGARIA E DRUGSTO | F114: 14305 | G114: ULTRAPOPULAR FARMARCAS | H114: 35999 | I114: 30 | J114: 35999 | K114: 7 | L114: B02549 | M114: ATIVO | N114: JULIANO DE MOURA HIDAKA | O114: LUIS CARLOS SILVEIRA | P114: =_xlfn.XLOOKUP('MEDIA TRI'!$E:$E,'MEDIA TRI'!$AA:$AA,"-",0) -> #NAME? | Q114: =_xlfn.XLOOKUP($U:$U,$V:$V,0,0) -> #NAME? | R114: =_xlfn.XLOOKUP($U:$U,$W:$W,0,0) -> #NAME? | S114: MG | T114: MG | U114: 37436920000248 | V114: IB | W114: REDE UNIMED OURINHOS
A115: B02572 | B115: 17722513000109 | C115: 125045 | D115: 227 | E115: DROG DROGAMARA DE BICAS LT | F115: 10437 | G115: INDIVIDUAL | H115: 36010 | I115: 35 | J115: 36010 | K115: 7 | L115: B02572 | M115: ATIVO | N115: JULIANO DE MOURA HIDAKA | O115: VAGO - ZONA DA MATA - MG | P115: =_xlfn.XLOOKUP('MEDIA TRI'!$E:$E,'MEDIA TRI'!$AA:$AA,"-",0) -> #NAME? | Q115: =_xlfn.XLOOKUP($U:$U,$V:$V,0,0) -> #NAME? | R115: =_xlfn.XLOOKUP($U:$U,$W:$W,0,0) -> #NAME? | S115: MG | T115: MGI | U115: 37436920000248 | V115: IB | W115: REDE UNIMED OURINHOS
A116: B02606 | B116: 743533000163 | C116: 101759 | D116: 529 | E116: DROGARIA TURVOLANDIA LTDA | F116: 14175 | G116: INOVA DROGARIA | H116: 33581 | I116: 27 | J116: 33581 | K116: 7 | L116: B02606 | M116: ATIVO | N116: JULIANO DE MOURA HIDAKA | O116: VAGNER LUIZ BUENO CAMBRAIA | P116: =_xlfn.XLOOKUP('MEDIA TRI'!$E:$E,'MEDIA TRI'!$AA:$AA,"-",0) -> #NAME? | Q116: =_xlfn.XLOOKUP($U:$U,$V:$V,0,0) -> #NAME? | R116: =_xlfn.XLOOKUP($U:$U,$W:$W,0,0) -> #NAME? | S116: MG | T116: MGI | U116: 37436920000248 | V116: IB | W116: REDE UNIMED OURINHOS
A117: B02648 | B117: 71345441000173 | C117: 140118 | D117: 3412 | E117: CARMELL PRODS FARM LT | F117: 10437 | G117: INDIVIDUAL | H117: 30015 | I117: 21 | J117: 30015 | K117: 7 | L117: B02648 | M117: ATIVO | N117: JULIANO DE MOURA HIDAKA | O117: INATIVO - MG4 | P117: =_xlfn.XLOOKUP('MEDIA TRI'!$E:$E,'MEDIA TRI'!$AA:$AA,"-",0) -> #NAME? | Q117: =_xlfn.XLOOKUP($U:$U,$V:$V,0,0) -> #NAME? | R117: =_xlfn.XLOOKUP($U:$U,$W:$W,0,0) -> #NAME? | S117: MG | T117: MGI | U117: 2597394000213 | V117: D9 | W117: REDE UNIMED
A118: B02663 | B118: 5843231000180 | C118: 162925 | D118: 3412 | E118: DROG MELQUITA LTDA | F118: 10437 | G118: INDIVIDUAL | H118: 30015 | I118: 21 | J118: 30015 | K118: 7 | L118: B02663 | M118: ATIVO | N118: JULIANO DE MOURA HIDAKA | O118: INATIVO - MG4 | P118: =_xlfn.XLOOKUP('MEDIA TRI'!$E:$E,'MEDIA TRI'!$AA:$AA,"-",0) -> #NAME? | Q118: =_xlfn.XLOOKUP($U:$U,$V:$V,0,0) -> #NAME? | R118: =_xlfn.XLOOKUP($U:$U,$W:$W,0,0) -> #NAME? | S118: MG | T118: MGI | U118: 2597394000213 | V118: D9 | W118: REDE UNIMED
A119: B02697 | B119: 21670054000134 | C119: 121512 | D119: 393 | E119: DROGA CENTRO LIMITADA ME | F119: 14594 | G119: REDEMAIS MINAS | H119: 34925 | I119: 21 | J119: 34925 | K119: 7 | L119: B02697 | M119: ATIVO | N119: JULIANO DE MOURA HIDAKA | O119: DOUGLAS ALCANTARA PEREIRA | P119: =_xlfn.XLOOKUP('MEDIA TRI'!$E:$E,'MEDIA TRI'!$AA:$AA,"-",0) -> #NAME? | Q119: =_xlfn.XLOOKUP($U:$U,$V:$V,0,0) -> #NAME? | R119: =_xlfn.XLOOKUP($U:$U,$W:$W,0,0) -> #NAME? | S119: MG | T119: MGI | U119: 2597394000213 | V119: D9 | W119: REDE UNIMED
...

Sheet SOMA
T2: ↓ | U2: ↓
B3: V. 4.0 08/04 | C3: 46120
B4: USAR PONTO ( . ) NAS DATAS | Q4: PREENCHER PARA CADASTRAR SOMA
L5: ↓ | Q5: PROPOSTO | V5: ↓ | W5: ↓ | X5: ↓
B6: PERÍODO NEGOCIAÇÃO INÍCIO | C6: PERÍODO NEGOCIAÇÃO FIM | D6: MARCA SOLICITANTE | E6: FILIAL | F6: GV | G6: SUPERVISOR | H6: ORGANIZAÇÃO DE VENDAS | I6: CÓDIGO SAP CLIENTE | J6: CÓDIGO PFAT CLIENTE | K6: RAZÃO SOCIAL | L6: CÓD. REDE | M6: NOME REDE | N6: CÓD. BAND | O6: NOME BANDEIRA | P6: AÇÃO PARA REDE OU CLIENTE? | Q6: % SOMA TOTAL | R6: % COMERCIAL | S6: % FINANCEIRO | T6: MATERIAL BANDEIRA GMR GERAL | U6: DESCRIÇÃO | V6: MD TRIM | W6: VOLUME PROPOSTO PARA O PERÍODO | X6: OBS
B8: =TODAY() -> 46135 | C8: INDETERMINADO | D8: SANTA CRUZ | E8: =IFERROR(VLOOKUP($J8,'Base 1'!A:S,19,0),"-") -> - | F8: =IFERROR(VLOOKUP($J8,'Base 1'!$A:$N,14,0),"-") -> - | G8: =IFERROR(VLOOKUP($J8,'Base 1'!$A:$O,15,0),"-") -> - | H8: =IFERROR(VLOOKUP($J8,'Base 1'!$A:$T,20,0),"-") -> - | I8: =IFERROR(VLOOKUP($J8,'Base 1'!$A:$C,3,0),"-") -> - | K8: =IFERROR(VLOOKUP($J8,'Base 1'!$A:$E,5,0),"-") -> - | L8: =IFERROR(VLOOKUP($J8,'Base 1'!$A:$Q,17,0),"-") -> - | M8: =IFERROR(VLOOKUP($J8,'Base 1'!$A:$R,18,0),"-") -> - | N8: =IFERROR(VLOOKUP($J8,'Base 1'!$A:$F,6,0),"-") -> - | O8: =IFERROR(VLOOKUP($J8,'Base 1'!$A:$G,7,0),"-") -> - | Q8: - | R8: - | U8: - | V8: =IFERROR(VLOOKUP($J8,'Base 1'!$A:$Q,16,0),"-") -> - | W8: - | X8: -
B9: =TODAY() -> 46135 | C9: INDETERMINADO | D9: SANTA CRUZ | E9: =IFERROR(VLOOKUP($J9,'Base 1'!A:S,19,0),"-") -> - | F9: =IFERROR(VLOOKUP($J9,'Base 1'!$A:$N,14,0),"-") -> - | G9: =IFERROR(VLOOKUP($J9,'Base 1'!$A:$O,15,0),"-") -> - | H9: =IFERROR(VLOOKUP($J9,'Base 1'!$A:$T,20,0),"-") -> - | I9: =IFERROR(VLOOKUP($J9,'Base 1'!$A:$C,3,0),"-") -> - | K9: =IFERROR(VLOOKUP($J9,'Base 1'!$A:$E,5,0),"-") -> - | L9: =IFERROR(VLOOKUP($J9,'Base 1'!$A:$Q,17,0),"-") -> - | M9: =IFERROR(VLOOKUP($J9,'Base 1'!$A:$R,18,0),"-") -> - | N9: =IFERROR(VLOOKUP($J9,'Base 1'!$A:$F,6,0),"-") -> - | O9: =IFERROR(VLOOKUP($J9,'Base 1'!$A:$G,7,0),"-") -> - | Q9: - | R9: - | U9: - | V9: =IFERROR(VLOOKUP($J9,'Base 1'!$A:$Q,16,0),"-") -> - | W9: - | X9: -
B10: =TODAY() -> 46135 | C10: INDETERMINADO | D10: SANTA CRUZ | E10: =IFERROR(VLOOKUP($J10,'Base 1'!A:S,19,0),"-") -> - | F10: =IFERROR(VLOOKUP($J10,'Base 1'!$A:$N,14,0),"-") -> - | G10: =IFERROR(VLOOKUP($J10,'Base 1'!$A:$O,15,0),"-") -> - | H10: =IFERROR(VLOOKUP($J10,'Base 1'!$A:$T,20,0),"-") -> - | I10: =IFERROR(VLOOKUP($J10,'Base 1'!$A:$C,3,0),"-") -> - | K10: =IFERROR(VLOOKUP($J10,'Base 1'!$A:$E,5,0),"-") -> - | L10: =IFERROR(VLOOKUP($J10,'Base 1'!$A:$Q,17,0),"-") -> - | M10: =IFERROR(VLOOKUP($J10,'Base 1'!$A:$R,18,0),"-") -> - | N10: =IFERROR(VLOOKUP($J10,'Base 1'!$A:$F,6,0),"-") -> - | O10: =IFERROR(VLOOKUP($J10,'Base 1'!$A:$G,7,0),"-") -> - | Q10: - | R10: - | U10: - | V10: =IFERROR(VLOOKUP($J10,'Base 1'!$A:$Q,16,0),"-") -> - | W10: - | X10: -
B11: =TODAY() -> 46135 | C11: INDETERMINADO | D11: SANTA CRUZ | E11: =IFERROR(VLOOKUP($J11,'Base 1'!A:S,19,0),"-") -> - | F11: =IFERROR(VLOOKUP($J11,'Base 1'!$A:$N,14,0),"-") -> - | G11: =IFERROR(VLOOKUP($J11,'Base 1'!$A:$O,15,0),"-") -> - | H11: =IFERROR(VLOOKUP($J11,'Base 1'!$A:$T,20,0),"-") -> - | I11: =IFERROR(VLOOKUP($J11,'Base 1'!$A:$C,3,0),"-") -> - | K11: =IFERROR(VLOOKUP($J11,'Base 1'!$A:$E,5,0),"-") -> - | L11: =IFERROR(VLOOKUP($J11,'Base 1'!$A:$Q,17,0),"-") -> - | M11: =IFERROR(VLOOKUP($J11,'Base 1'!$A:$R,18,0),"-") -> - | N11: =IFERROR(VLOOKUP($J11,'Base 1'!$A:$F,6,0),"-") -> - | O11: =IFERROR(VLOOKUP($J11,'Base 1'!$A:$G,7,0),"-") -> - | Q11: - | R11: - | U11: - | V11: =IFERROR(VLOOKUP($J11,'Base 1'!$A:$Q,16,0),"-") -> - | W11: - | X11: -
B12: =TODAY() -> 46135 | C12: INDETERMINADO | D12: SANTA CRUZ | E12: =IFERROR(VLOOKUP($J12,'Base 1'!A:S,19,0),"-") -> - | F12: =IFERROR(VLOOKUP($J12,'Base 1'!$A:$N,14,0),"-") -> - | G12: =IFERROR(VLOOKUP($J12,'Base 1'!$A:$O,15,0),"-") -> - | H12: =IFERROR(VLOOKUP($J12,'Base 1'!$A:$T,20,0),"-") -> - | I12: =IFERROR(VLOOKUP($J12,'Base 1'!$A:$C,3,0),"-") -> - | K12: =IFERROR(VLOOKUP($J12,'Base 1'!$A:$E,5,0),"-") -> - | L12: =IFERROR(VLOOKUP($J12,'Base 1'!$A:$Q,17,0),"-") -> - | M12: =IFERROR(VLOOKUP($J12,'Base 1'!$A:$R,18,0),"-") -> - | N12: =IFERROR(VLOOKUP($J12,'Base 1'!$A:$F,6,0),"-") -> - | O12: =IFERROR(VLOOKUP($J12,'Base 1'!$A:$G,7,0),"-") -> - | Q12: - | R12: - | U12: - | V12: =IFERROR(VLOOKUP($J12,'Base 1'!$A:$Q,16,0),"-") -> - | W12: - | X12: -
B13: =TODAY() -> 46135 | C13: INDETERMINADO | D13: SANTA CRUZ | E13: =IFERROR(VLOOKUP($J13,'Base 1'!A:S,19,0),"-") -> - | F13: =IFERROR(VLOOKUP($J13,'Base 1'!$A:$N,14,0),"-") -> - | G13: =IFERROR(VLOOKUP($J13,'Base 1'!$A:$O,15,0),"-") -> - | H13: =IFERROR(VLOOKUP($J13,'Base 1'!$A:$T,20,0),"-") -> - | I13: =IFERROR(VLOOKUP($J13,'Base 1'!$A:$C,3,0),"-") -> - | K13: =IFERROR(VLOOKUP($J13,'Base 1'!$A:$E,5,0),"-") -> - | L13: =IFERROR(VLOOKUP($J13,'Base 1'!$A:$Q,17,0),"-") -> - | M13: =IFERROR(VLOOKUP($J13,'Base 1'!$A:$R,18,0),"-") -> - | N13: =IFERROR(VLOOKUP($J13,'Base 1'!$A:$F,6,0),"-") -> - | O13: =IFERROR(VLOOKUP($J13,'Base 1'!$A:$G,7,0),"-") -> - | Q13: - | R13: - | U13: - | V13: =IFERROR(VLOOKUP($J13,'Base 1'!$A:$Q,16,0),"-") -> - | W13: - | X13: -
B14: =TODAY() -> 46135 | C14: INDETERMINADO | D14: SANTA CRUZ | E14: =IFERROR(VLOOKUP($J14,'Base 1'!A:S,19,0),"-") -> - | F14: =IFERROR(VLOOKUP($J14,'Base 1'!$A:$N,14,0),"-") -> - | G14: =IFERROR(VLOOKUP($J14,'Base 1'!$A:$O,15,0),"-") -> - | H14: =IFERROR(VLOOKUP($J14,'Base 1'!$A:$T,20,0),"-") -> - | I14: =IFERROR(VLOOKUP($J14,'Base 1'!$A:$C,3,0),"-") -> - | K14: =IFERROR(VLOOKUP($J14,'Base 1'!$A:$E,5,0),"-") -> - | L14: =IFERROR(VLOOKUP($J14,'Base 1'!$A:$Q,17,0),"-") -> - | M14: =IFERROR(VLOOKUP($J14,'Base 1'!$A:$R,18,0),"-") -> - | N14: =IFERROR(VLOOKUP($J14,'Base 1'!$A:$F,6,0),"-") -> - | O14: =IFERROR(VLOOKUP($J14,'Base 1'!$A:$G,7,0),"-") -> - | Q14: - | R14: - | U14: - | V14: =IFERROR(VLOOKUP($J14,'Base 1'!$A:$Q,16,0),"-") -> - | W14: - | X14: -
B15: =TODAY() -> 46135 | C15: INDETERMINADO | D15: SANTA CRUZ | E15: =IFERROR(VLOOKUP($J15,'Base 1'!A:S,19,0),"-") -> - | F15: =IFERROR(VLOOKUP($J15,'Base 1'!$A:$N,14,0),"-") -> - | G15: =IFERROR(VLOOKUP($J15,'Base 1'!$A:$O,15,0),"-") -> - | H15: =IFERROR(VLOOKUP($J15,'Base 1'!$A:$T,20,0),"-") -> - | I15: =IFERROR(VLOOKUP($J15,'Base 1'!$A:$C,3,0),"-") -> - | K15: =IFERROR(VLOOKUP($J15,'Base 1'!$A:$E,5,0),"-") -> - | L15: =IFERROR(VLOOKUP($J15,'Base 1'!$A:$Q,17,0),"-") -> - | M15: =IFERROR(VLOOKUP($J15,'Base 1'!$A:$R,18,0),"-") -> - | N15: =IFERROR(VLOOKUP($J15,'Base 1'!$A:$F,6,0),"-") -> - | O15: =IFERROR(VLOOKUP($J15,'Base 1'!$A:$G,7,0),"-") -> - | Q15: - | R15: - | U15: - | V15: =IFERROR(VLOOKUP($J15,'Base 1'!$A:$Q,16,0),"-") -> - | W15: - | X15: -
B16: =TODAY() -> 46135 | C16: INDETERMINADO | D16: SANTA CRUZ | E16: =IFERROR(VLOOKUP($J16,'Base 1'!A:S,19,0),"-") -> - | F16: =IFERROR(VLOOKUP($J16,'Base 1'!$A:$N,14,0),"-") -> - | G16: =IFERROR(VLOOKUP($J16,'Base 1'!$A:$O,15,0),"-") -> - | H16: =IFERROR(VLOOKUP($J16,'Base 1'!$A:$T,20,0),"-") -> - | I16: =IFERROR(VLOOKUP($J16,'Base 1'!$A:$C,3,0),"-") -> - | K16: =IFERROR(VLOOKUP($J16,'Base 1'!$A:$E,5,0),"-") -> - | L16: =IFERROR(VLOOKUP($J16,'Base 1'!$A:$Q,17,0),"-") -> - | M16: =IFERROR(VLOOKUP($J16,'Base 1'!$A:$R,18,0),"-") -> - | N16: =IFERROR(VLOOKUP($J16,'Base 1'!$A:$F,6,0),"-") -> - | O16: =IFERROR(VLOOKUP($J16,'Base 1'!$A:$G,7,0),"-") -> - | Q16: - | R16: - | U16: - | V16: =IFERROR(VLOOKUP($J16,'Base 1'!$A:$Q,16,0),"-") -> - | W16: - | X16: -
B17: =TODAY() -> 46135 | C17: INDETERMINADO | D17: SANTA CRUZ | E17: =IFERROR(VLOOKUP($J17,'Base 1'!A:S,19,0),"-") -> - | F17: =IFERROR(VLOOKUP($J17,'Base 1'!$A:$N,14,0),"-") -> - | G17: =IFERROR(VLOOKUP($J17,'Base 1'!$A:$O,15,0),"-") -> - | H17: =IFERROR(VLOOKUP($J17,'Base 1'!$A:$T,20,0),"-") -> - | I17: =IFERROR(VLOOKUP($J17,'Base 1'!$A:$C,3,0),"-") -> - | K17: =IFERROR(VLOOKUP($J17,'Base 1'!$A:$E,5,0),"-") -> - | L17: =IFERROR(VLOOKUP($J17,'Base 1'!$A:$Q,17,0),"-") -> - | M17: =IFERROR(VLOOKUP($J17,'Base 1'!$A:$R,18,0),"-") -> - | N17: =IFERROR(VLOOKUP($J17,'Base 1'!$A:$F,6,0),"-") -> - | O17: =IFERROR(VLOOKUP($J17,'Base 1'!$A:$G,7,0),"-") -> - | Q17: - | R17: - | U17: - | V17: =IFERROR(VLOOKUP($J17,'Base 1'!$A:$Q,16,0),"-") -> - | W17: - | X17: -
B18: =TODAY() -> 46135 | C18: INDETERMINADO | D18: SANTA CRUZ | E18: =IFERROR(VLOOKUP($J18,'Base 1'!A:S,19,0),"-") -> - | F18: =IFERROR(VLOOKUP($J18,'Base 1'!$A:$N,14,0),"-") -> - | G18: =IFERROR(VLOOKUP($J18,'Base 1'!$A:$O,15,0),"-") -> - | H18: =IFERROR(VLOOKUP($J18,'Base 1'!$A:$T,20,0),"-") -> - | I18: =IFERROR(VLOOKUP($J18,'Base 1'!$A:$C,3,0),"-") -> - | K18: =IFERROR(VLOOKUP($J18,'Base 1'!$A:$E,5,0),"-") -> - | L18: =IFERROR(VLOOKUP($J18,'Base 1'!$A:$Q,17,0),"-") -> - | M18: =IFERROR(VLOOKUP($J18,'Base 1'!$A:$R,18,0),"-") -> - | N18: =IFERROR(VLOOKUP($J18,'Base 1'!$A:$F,6,0),"-") -> - | O18: =IFERROR(VLOOKUP($J18,'Base 1'!$A:$G,7,0),"-") -> - | Q18: - | R18: - | U18: - | V18: =IFERROR(VLOOKUP($J18,'Base 1'!$A:$Q,16,0),"-") -> - | W18: - | X18: -
B19: =TODAY() -> 46135 | C19: INDETERMINADO | D19: SANTA CRUZ | E19: =IFERROR(VLOOKUP($J19,'Base 1'!A:S,19,0),"-") -> - | F19: =IFERROR(VLOOKUP($J19,'Base 1'!$A:$N,14,0),"-") -> - | G19: =IFERROR(VLOOKUP($J19,'Base 1'!$A:$O,15,0),"-") -> - | H19: =IFERROR(VLOOKUP($J19,'Base 1'!$A:$T,20,0),"-") -> - | I19: =IFERROR(VLOOKUP($J19,'Base 1'!$A:$C,3,0),"-") -> - | K19: =IFERROR(VLOOKUP($J19,'Base 1'!$A:$E,5,0),"-") -> - | L19: =IFERROR(VLOOKUP($J19,'Base 1'!$A:$Q,17,0),"-") -> - | M19: =IFERROR(VLOOKUP($J19,'Base 1'!$A:$R,18,0),"-") -> - | N19: =IFERROR(VLOOKUP($J19,'Base 1'!$A:$F,6,0),"-") -> - | O19: =IFERROR(VLOOKUP($J19,'Base 1'!$A:$G,7,0),"-") -> - | Q19: - | R19: - | U19: - | V19: =IFERROR(VLOOKUP($J19,'Base 1'!$A:$Q,16,0),"-") -> - | W19: - | X19: -
... B504: =TODAY() -> 46135 | C504: INDETERMINADO | D504: SANTA CRUZ | E504: =IFERROR(VLOOKUP($J504,'Base 1'!A:S,19,0),"-") -> - | F504: =IFERROR(VLOOKUP($J504,'Base 1'!$A:$N,14,0),"-") -> - | G504: =IFERROR(VLOOKUP($J504,'Base 1'!$A:$O,15,0),"-") -> - | H504: =IFERROR(VLOOKUP($J504,'Base 1'!$A:$T,20,0),"-") -> - | I504: =IFERROR(VLOOKUP($J504,'Base 1'!$A:$C,3,0),"-") -> - | K504: =IFERROR(VLOOKUP($J504,'Base 1'!$A:$E,5,0),"-") -> - | L504: =IFERROR(VLOOKUP($J504,'Base 1'!$A:$Q,17,0),"-") -> - | M504: =IFERROR(VLOOKUP($J504,'Base 1'!$A:$R,18,0),"-") -> - | N504: =IFERROR(VLOOKUP($J504,'Base 1'!$A:$F,6,0),"-") -> - | O504: =IFERROR(VLOOKUP($J504,'Base 1'!$A:$G,7,0),"-") -> - | Q504: - | R504: - | U504: - | V504: =IFERROR(VLOOKUP($J504,'Base 1'!$A:$Q,16,0),"-") -> - | W504: - | X504: -

Sheet GMR
A1: Descrição Bandeira GMR | B1: Subsor | C1: NomeFornec | D1: Grupo | E1: GRUPO SIMUL
A2: ABBOTT DIAG | B2: F01495 | C2: ABBOTT LABORATORIOS DO BRASIL LTDA | D2: G4
A3: ABBOTT NUT | B3: F00357 | C3: ABBOTT LABORATORIOS BRASIL LTDA | D3: G8 | E3: G5
A4: ABBOTT RX | B4: F00556 | C4: ABBOTT LABORATORIOS BRASIL LTDA | D4: G8 | E4: G5
A5: ABBOTT RX | B5: F01227 | C5: ABBOTT LABORATORIOS BRASIL LTDA | D5: G8 | E5: G5
A6: ABBOTT RX | B6: F00588 | C6: ABBOTT LABORATORIOS BRASIL LTDA | D6: G8 | E6: G5
A7: ABBOTT RX | B7: F01032 | C7: ABBOTT LABORATORIOS BRASIL LTDA | D7: G6 | E7: G6
A8: ABBVIE RX | B8: F01546 | C8: ABBVIE FARMACEUTICA LTDA | D8: G5 | E8: G5
A9: ACCUMED CONS | B9: F01327 | C9: ACCUMED PRODUTOS MEDICO HOSPITALARE | D9: G42
A10: ACCUMED CONS | B10: F01343 | C10: ACCUMED PRODUTOS MEDICO HOSPITALARE | D10: G42
A11: ACHE GEN | B11: F01645 | C11: LABOFARMA PRODUTOS FARMACEUTICOS LT | D11: G6 | E11: G6
A12: ACHE GEN | B12: F00915 | C12: ACHE LABORATORIOS FARMACEUTICOS SA | D12: G6 | E12: G6
A13: ACHE OTC | B13: F01646 | C13: LABOFARMA PRODUTOS FARMACEUTICOS LT | D13: G3 | E13: G3
A14: ACHE OTC | B14: F14123 | C14: ACHE LABORATORIOS FARMACEUTICOS SA | D14: G3 | E14: G3
A15: ACHE OTC | B15: F01690 | C15: ACHE LABORATORIOS FARMACEUTICOS SA | D15: G4
A16: ACHE RX | B16: F22910 | C16: ACHE LABORATORIOS FARMACEUTICOS SA | D16: G8 | E16: G3
A17: ACHE RX | B17: F01639 | C17: LABOFARMA PRODUTOS FARMACEUTICOS LT | D17: G3 | E17: G3
A18: ADIUM(ZODIAC) | B18: F13349 | C18: ADIUM S.A | D18: G5 | E18: G5
A19: ADIUM(ZODIAC) | B19: F01604 | C19: ADIUM S A | D19: G8 | E19: G5
A20: ADVERTISING | B20: F01589 | C20: ADVERTISING OPERATIONS ASS PLAN E P | D20: G4
A21: ADVERTISING | B21: F02896 | C21: ADVERTISING OPERATIONS ASS. PLAN. P | D21: G4
A22: ALCON | B22: F01701 | C22: ALCON BRASIL CUIDADOS COM A SAUDE L | D22: G8 | E22: G5
A23: ALCON | B23: F01743 | C23: ALCON BRASIL CUIDADOS COM A SAUDE L | D23: G5 | E23: G5
A24: ALCON | B24: F01710 | C24: ALCON BRASIL CUIDADOS COM A SAUDE L | D24: G42
A25: ALMEIDA PR | B25: F55654 | C25: FCIA.E LAB.HOM.ALMEIDA PRADO L | D25: G5 | E25: G5
A26: ALTHAIA | B26: F01421 | C26: ALTHAIA S.A. INDUSTRIA FARMACEUTICA | D26: G6 | E26: G6
A27: APSEN RX | B27: F01640 | C27: APSEN FARMACEUTICA S A | D27: G3 | E27: G3
A28: ARESE | B28: F01558 | C28: ARESE PHARMA LTDA | D28: G5 | E28: G5
A29: ARESE | B29: F00922 | C29: ARESE NUTRITION LTDA | D29: G42
A30: ASPEN | B30: F00417 | C30: A PHARMA DISTRIBUIDORA LTDA | D30: G8 | E30: G5
A31: ASPEN | B31: F28404 | C31: ASPEN PHARMA INDUSTRIA FARMACEUTICA | D31: G8 | E31: G5
A32: ASPEN | B32: F01334 | C32: ASPEN PHARMA INDUSTRIA FARMACEUTICA | D32: G5 | E32: G5
A33: ASPEN | B33: F00558 | C33: ASPEN PHARMA INDUSTRIA FARMACEUTICA | D33: G5 | E33: G5
A34: ASTELLAS | B34: F00265 | C34: ASTELLAS FARMA BRASIL IMP DIST LTDA | D34: G8 | E34: G5
A35: ASTRAZENECA | B35: F46455 | C35: ASTRAZENECA DO BRASIL LTDA | D35: G8 | E35: G2
A36: BAGO | B36: F00405 | C36: LABORATORIOS BAGO DO BRASIL SA | D36: G8 | E36: G5
A37: BAGO | B37: F01322 | C37: LABORATORIOS BAGO DO BRASIL SA | D37: G4
A38: BALDACCI | B38: F01502 | C38: LABORATORIOS BALDACCI S A | D38: G5 | E38: G5
A39: BALDACCI | B39: F18249 | C39: LABORATORIOS BALDACCI S A | D39: G42
A40: BAUSCH OTC | B40: F01783 | C40: BL INDUSTRIA OTICA LTDA | D40: G1 | E40: G1
A41: BAUSCH OTC | B41: F01409 | C41: BL INDUSTRIA OTICA LTDA | D41: G8 | E41: G5
A42: BAUSCH OTC | B42: F01410 | C42: BL INDUSTRIA OTICA LTDA | D42: G8 | E42: G5
A43: BAYER CONS | B43: F01098 | C43: BAYER S A | D43: G4
A44: BAYER OTC | B44: F01099 | C44: BAYER S A | D44: G8 | E44: G5
A45: BAYER RX | B45: F01089 | C45: BAYER S A | D45: G5 | E45: G5
A46: BAYER RX | B46: F01092 | C46: BAYER S A | D46: G8 | E46: G5
A47: BAYER RX | B47: F01087 | C47: BAYER S A | D47: G8 | E47: G5
A48: BD | B48: F25079 | C48: BECTON DICKISON IND CIR LTDA | D48: G4
A49: BESINS | B49: F00985 | C49: BESINS HEALTHCARE BRASIL COM DIST M | D49: G8 | E49: G5
A50: BIOCHIMICO | B50: F01552 | C50: INSTITUTO BIOCHIMICO IND FARMA LTDA | D50: G5 | E50: G5
A51: BIODERMA | B51: F00582 | C51: LABORATORIOS NAOS DO BRASIL LTDA | D51: G4
A52: BIOLAB GEN | B52: F01725 | C52: BIOLAB FARMA GENERICOS LTDA | D52: G6 | E52: G6
A53: BIOLAB GEN | B53: F01216 | C53: BIOLAB FARMA GENERICOS LTDA | D53: G8 | E53: G6
A54: BIOLAB RX | B54: F01215 | C54: BIOLAB SANUS FARMACEUTICA LTDA | D54: G3 | E54: G3
A55: BIOLAB RX | B55: F01217 | C55: BIOLAB SANUS FARMACEUTICA LTDA | D55: G3 | E55: G3
A56: BIOLAB RX | B56: F01647 | C56: BIOLAB SANUS FARMACEUTICA LTDA | D56: G8 | E56: G3
A57: BIOLAB RX | B57: F01643 | C57: BIOLAB FARMA GENERICOS LTDA | D57: G8 | E57: G3
A58: BIOMM | B58: F01767 | C58: BIOMM SA | D58: G1 | E58: G1
A59: BIOPAS | B59: F01354 | C59: BIOPAS BRASIL PRODUTOS FARMACEUTICO | D59: G5 | E59: G5
A60: BIOSINTETICA RX | B60: F01446 | C60: ACHE LABORATORIOS FARMACEUTICOS SA | D60: G5 | E60: G5
A61: BIOSINTETICA RX | B61: F01642 | C61: LABOFARMA PRODUTOS FARMACEUTICOS LT | D61: G8 | E61: G5
A62: BLANVER | B62: F01414 | C62: BLANVER FARMOQUIMICA E FARMACEUTICA | D62: G8 | E62: G5
A63: BLANVER | B63: F01774 | C63: BLANVER FARMOQUIMICA E FARMACEUTICA | D63: G1 | E63: G1
A64: BLOWTEX | B64: F12077 | C64: FABRICA ARTEF.LATEX BLOWTEX LT | D64: G4
A65: BOEHRINGER RX | B65: F01597 | C65: BOEHRINGER INGELHEIM DO BRASIL QUIM | D65: G2 | E65: G2
A66: BOEHRINGER RX | B66: F01553 | C66: BOEHRINGER INGELHEIM DO BRASIL QUIM | D66: G2 | E66: G2
A67: BOEHRINGER RX | B67: F01570 | C67: BOEHRINGER INGELHEIM DO BRASIL QUIM | D67: G8 | E67: G2
A68: BOTICARIO | B68: F01691 | C68: BOTICARIO PRODUTOS DE BELEZA LTDA | D68: G4
A69: BOTICARIO | B69: F01752 | C69: BOTICARIO PRODUTOS DE BELEZA LTDA | D69: G4
A70: BOTICARIO | B70: F01689 | C70: BOTICARIO PRODUTOS DE BELEZA LTDA | D70: G4
A71: CATARINENSE | B71: F01282 | C71: LABORATORIO CATARINENSE LTDA | D71: G5 | E71: G5
A72: CELLERA RX | B72: F00682 | C72: CELLERA CONSUMO LTDA | D72: G5 | E72: G5
A73: CELLERA RX | B73: F01623 | C73: CELLERA CONSUMO LTDA | D73: G5 | E73: G5
A74: CELLERA RX | B74: F01679 | C74: CELLERA FARMACEUTICA S.A. | D74: G42
A75: CERAS JOHNSON | B75: F00798 | C75: CERAS JOHNSON LTDA | D75: G4
A76: CERAS JOHNSON | B76: F00800 | C76: CERAS JOHNSON LTDA | D76: G4
A77: CHIESI RX | B77: F01378 | C77: CHIESI FARMACEUTICA LTDA | D77: G8 | E77: G5
A78: CHIESI RX | B78: F01556 | C78: CHIESI FARMACEUTICA LTDA | D78: G1 | E78: G1
A79: COLGATE | B79: F01024 | C79: COLGATE-PALMOLIVE COMERCIAL LTDA | D79: G4
A80: COLGATE | B80: F26432 | C80: COLGATE-PALMOLIVE IND E COM LT | D80: G4
A81: COLGATE | B81: F01144 | C81: COLGATE-PALMOLIVE IND E COM LT | D81: G4
A82: COLGATE | B82: F01206 | C82: COLGATE-PALMOLIVE COMERCIAL LTDA | D82: G4
A83: COTY | B83: F00476 | C83: COTY BRASIL COMERCIO LTDA | D83: G4
A84: COTY | B84: F01424 | C84: COTY BRASIL COMERCIO LTDA | D84: G4
A85: COTY | B85: F00519 | C85: COTY BRASIL COMERCIO LTDA | D85: G4
A86: CREMER | B86: F00228 | C86: CREMER S A | D86: G4
A87: CREMER | B87: F00390 | C87: CREMER S A | D87: G4
A88: CREMER | B88: F39971 | C88: CREMER S A | D88: G4
A89: CRISTALIA RX | B89: F01299 | C89: CRISTALIA PRODS QUIMICOS FARMACEUT | D89: G5 | E89: G5
A90: CRISTALIA RX | B90: F01772 | C90: CRISTALIA PRODS QUIMICOS FARMACEUT | D90: G1 | E90: G1
A91: DAIICHI SANKYO RX | B91: F01684 | C91: DAIICHI SANKYO BRASIL FARMACEUTICA | D91: G8 | E91: G5
A92: DANONE | B92: F00436 | C92: DANONE LTDA | D92: G4
A93: DANONE | B93: F01516 | C93: DANONE LTDA | D93: G4
A94: DELTA | B94: F00382 | C94: COMERCIO E DISTRIBUIDORA DELTA LTD | D94: G42
A95: DERMAGE | B95: F01744 | C95: DISTRIPRIME DISTRIBUIDORA DE COSMET | D95: G4
A96: DIFFUCAP | B96: F21151 | C96: DIFFUCAP CHEMOBRAS | D96: G5 | E96: G5
A97: EASELABS /CBD | B97: F01694 | C97: EASELABS LABORATORIO FARMACEUTICO L | D97: G8 | E97: G5
A98: EMBECTA | B98: F01681 | C98: EMBECTA BRASIL LTDA | D98: G4
A99: EMS BRACE PHARMA | B99: F01296 | C99: EMS S A | D99: G8 | E99: G3
A100: EMS BRACE PHARMA | B100: F01721 | C100: EMS S/A | D100: G3 | E100: G3
...

Sheet BANDEIRA
D1: ALTERAÇÃO DE BANDEIRA-REDE
H5: ATUAL | L5: PROPOSTO
B6: CÓDIGO PFAT CLIENTE | C6: CÓDIGO SAP CLIENTE | D6: RAZÃO SOCIAL | E6: CNPJ | F6: ORGANIZAÇÃO DE VENDAS | G6: AÇÃO | H6: CÓD. BAND | I6: NOME BANDEIRA | J6: GRUPO DE PREÇO | K6: NOME GP | L6: CÓD. BAND | M6: NOME BANDEIRA | N6: GRUPO DE PREÇO | O6: NOME GP

Sheet  VN
B1: NOTA DE CREDITO | C1: VN e NOTA DE CRÉDITO
B3: Cliente (Farmácia): | E3: CNPJ:
B4: Banco: | C4: AG: | E4: Conta:
B5: Valor VN: | C5: Nome Indústria : | D5: Código F: | E5: Cód do Fornecedor Cliente:
B6: Solicitado por: | C6: Marca para Abertura da VN: | E6: Periodo Negociação:
B7: Justificativa:

Sheet PRORROGAÇÃO
E3: AUTORIZAÇÃO PARA PRORROGAÇÃO E PARCELAMENTO | Q3: TÍTULOS
A8: ( 01 ) Prazo cadastrado incorretamente | M8: ( 04 ) Pedido Negociado faturado com prazo errado
A9: ( 02) Negociação com cliente | M9: ( 05 ) Outros - Especificar
A10: ( 03 ) Pedido duplicado, negociação p/ evitar devolução
A12: ESCLARECIMENTO (obrigatório)
A14: CLIENTE / TÍTULOS | L14: CONDIÇÕES DA PRORROGAÇÃO
A15: NomeSupervisor | B15: CD/ FILIAL | C15: Código SAP | D15: Razão Social | E15: Nº do boleto | F15: Parcela | G15: Emissão Original | H15: Vencimento Original | I15: Prazo faturamento | J15: Valor Original | K15: Nº Motivo | L15: Prorrogar para | M15: Novo prazo prorrogação | N15: Novo prazo parcelamento | O15: nº Parcelas | P15: Valor parcelamento | Q15: Novo prazo prorrogado
L16: 45499
L17: 26/008/2024
A21: TOTAL | J21: =J16 -> 0

Sheet LISTAS SUSPENSAS
A3: INDETERMINADO | B3: AMBAS | C3: SIM | E3: REDE | G3: EPAN | I3: EXCLUSÃO
A4: {=_xlfn.SEQUENCE(1,"08/04/2026")} -> #NAME? | B4: PANPHARMA | C4: NÃO | E4: CLIENTE | G4: TVL | I4: INCLUSÃO
A5: #NAME? | B5: SANTA CRUZ | G5: OL
A6: #NAME? | G6: TODOS
A7: #NAME?
A8: #NAME?
A9: #NAME?
A10: #NAME?
A11: #NAME?
A12: #NAME?
A13: #NAME?
A14: #NAME?
A15: #NAME?
A16: #NAME?
A17: #NAME?
A18: #NAME?
... A203: #NAME?

Sheet RECÁLCULO DESCONTO
C3: RECALCULO PARA REEMBOLSO DE CREDITO
G4: DATA:
C7: JUSTIFICATIVA PARA O CREDITO
C11: Ctrl. | D11: Solicitante | E11: Marca Solicitante | F11: Filial/CD | G11: Codigo Cliente | H11: Razão Social | I11: N° Danfe (NF) | J11: Data Danfe (NF) | K11: Cod. Produto | L11: Produto | M11: Desc. Concedido (incorreto) | N11: Desc. Correto
C12: 1
C13: 2
C14: 3
C15: 4
C16: 5
C17: 6
C18: 7
C19: 8
C20: 9
C21: 10
C22: 11
C23: 12
... C91: 80

Sheet RECÁLCULO PREÇO FABRICA
C3: RECALCULO PARA REEMBOLSO DE CREDITO
F4: DATA:
C7: JUSTIFICATIVA PARA O CREDITO
C11: Ctrl. | D11: Solicitante | E11: Marca Solicitante | F11: Filial/CD | G11: Codigo Cliente | H11: Razão Social | I11: N° Danfe (NF) | J11: Data Danfe (NF) | K11: Cod. Produto | L11: Produto | M11: Preço Fábrica (incorreto) | N11: Preço Fábrica Correto
C12: 1
C13: 2
C14: 3
C15: 4
C16: 5
C17: 6
C18: 7
C19: 8
C20: 9
C21: 10
C22: 11
C23: 12
... C91: 80
